Workbook
Name NativeTimeline_Fecha1: #N/A
Name NativeTimeline_Fecha2: #N/A
Name SegmentaciónDeDatos_C.C.: #N/A
Name SegmentaciónDeDatos_C.C.1: #N/A
Name SegmentaciónDeDatos_Cuenta1: #N/A
Name SegmentaciónDeDatos_Cuenta11: #N/A
Name SegmentaciónDeDatos_Detalle: #N/A
Name SegmentaciónDeDatos_Detalle1: #N/A
Name SegmentaciónDeDatos_Mes: #N/A
Name SegmentaciónDeDatos_Nombre_Solicitante: #N/A
Name SegmentaciónDeDatos_Nombre_Solicitante1: #N/A
Name SegmentaciónDeDatos_Nro_Rend.: #N/A

Sheet Proyeccion 2025
C1: Heca - Chile
C2: Proyeccion de Efectivo y de necesidades de financiamiento
C3: del 01/01/2025 al 31/12/2025
C5: 45658 | D5: 45689 | E5: 45717 | F5: 45748 | G5: 45778 | H5: 45809 | I5: 45839 | J5: 45870 | K5: 45901 | L5: 45931 | M5: 45962 | N5: 45992
B6: Ventas | C6: 500000000 | D6: 650000000 | E6: 700000000 | F6: =+E6*1.03 -> 721000000 | G6: =+F6*1.03 -> 742630000 | H6: =+G6*1.03 -> 764908900 | I6: =+H6*1.03 -> 787856167 | J6: =+I6*1.03 -> 8.1149185e+08 | K6: =+J6*1.03 -> 8.3583661e+08 | L6: =+K6*1.03 -> 8.6091171e+08 | M6: =+L6*1.03 -> 8.8673906e+08 | N6: =+M6*1.03 -> 9.1334123e+08
B7: Ingresos
B8: Total Ingresos | C8: =+C6 -> 500000000 | D8: =+D6 -> 650000000 | E8: =+E6 -> 700000000 | F8: =+F6 -> 721000000 | G8: =+G6 -> 742630000 | H8: =+H6 -> 764908900 | I8: =+I6 -> 787856167 | J8: =+J6 -> 8.1149185e+08 | ... N8: =+N6 -> 9.1334123e+08
B9: Egresos
B10: Compras | C10: =+C8*50% -> 250000000 | D10: =+D8*50% -> 325000000 | E10: =+E8*50% -> 350000000 | F10: =+F8*50% -> 360500000 | G10: =+G8*50% -> 371315000 | H10: =+H8*50% -> 382454450 | I10: =+I8*50% -> 3.9392808e+08 | J10: =+J8*50% -> 4.0574593e+08 | ... N10: =+N8*50% -> 4.5667061e+08
B11: Gasto General | C11: =C30 -> 1.2759667e+08 | D11: =D30 -> 91321694 | E11: =E30 -> 99450000 | F11: =F30 -> 86450000 | G11: =G30 -> 86450000 | H11: =H30 -> 82950000 | I11: =I30 -> 82950000 | J11: =J30 -> 82950000 | ... N11: =N30 -> 82950000
B12: Cancelacion de Pasivos | D12: =27152000+27254400 -> 54406400 | E12: 29924650
B13: Total Egresos | C13: =+SUM(C10:C12) -> 3.7759667e+08 | D13: =+SUM(D10:D12) -> 4.7072809e+08 | E13: =+SUM(E10:E12) -> 479374650 | F13: =+SUM(F10:F12) -> 446950000 | G13: =+SUM(G10:G12) -> 457765000 | H13: =+SUM(H10:H12) -> 465404450 | I13: =+SUM(I10:I12) -> 4.7687808e+08 | J13: =+SUM(J10:J12) -> 4.8869593e+08 | ... N13: =+SUM(N10:N12) -> 5.3962061e+08
B15: Total al final de mes | C15: =+C8-C13 -> 1.2240333e+08 | D15: =+D8-D13 -> 1.7927191e+08 | E15: =+E8-E13 -> 220625350 | F15: =+F8-F13 -> 274050000 | G15: =+G8-G13 -> 284865000 | H15: =+H8-H13 -> 299504450 | I15: =+I8-I13 -> 3.1097808e+08 | J15: =+J8-J13 -> 3.2279593e+08 | ... N15: =+N8-N13 -> 3.7372061e+08
B21: Gastos de Oficina | C21: 6502027 | D21: 4545177 | E21: 6000000 | F21: 6000000 | G21: 6000000 | H21: 2500000 | I21: 2500000 | J21: 2500000 | K21: 2500000 | L21: 2500000 | M21: 2500000 | N21: 2500000 | O21: =SUM(C21:N21) -> 46547204
B22: Gastos de Operaciones | C22: 26362481 | D22: 14384193 | E22: 12000000 | F22: 7000000 | G22: 7000000 | H22: 7000000 | I22: 7000000 | J22: 7000000 | K22: 7000000 | L22: 7000000 | M22: 7000000 | N22: 7000000 | O22: =SUM(C22:N22) -> 1.1574667e+08
B23: Gastos de Importacion | O23: =SUM(C23:N23) -> 0
B24: Siga Sonriendo | C24: 1450000 | D24: =+C24 -> 1450000 | E24: =+D24 -> 1450000 | F24: =+E24 -> 1450000 | G24: =+F24 -> 1450000 | H24: =+G24 -> 1450000 | I24: =+H24 -> 1450000 | J24: =+I24 -> 1450000 | K24: =+J24 -> 1450000 | ... N24: =+M24 -> 1450000 | O24: =SUM(C24:N24) -> 17400000
B25: Gastos Financieros | C25: 1249537 | D25: 1061503 | E25: 1000000 | F25: 1000000 | G25: 1000000 | H25: 1000000 | I25: 1000000 | J25: 1000000 | K25: 1000000 | L25: 1000000 | M25: 1000000 | N25: 1000000 | O25: =SUM(C25:N25) -> 12311040
B26: Gastos de Personal | C26: 46032254 | D26: 31313984 | E26: 40000000 | F26: 32000000 | G26: 32000000 | H26: 32000000 | I26: 32000000 | J26: 32000000 | K26: 32000000 | L26: 32000000 | M26: 32000000 | N26: 32000000 | O26: =SUM(C26:N26) -> 4.0534624e+08
B27: Gastos Extras | C27: 38000000 | D27: =+C27 -> 38000000 | E27: =+D27 -> 38000000 | F27: =+E27 -> 38000000 | G27: =+F27 -> 38000000 | H27: =+G27 -> 38000000 | I27: =+H27 -> 38000000 | J27: =+I27 -> 38000000 | K27: =+J27 -> 38000000 | ... N27: =+M27 -> 38000000 | O27: =SUM(C27:N27) -> 456000000
B28: Gasto Tax Ingenieria | C28: 8000374 | D28: 566837 | E28: 1000000 | F28: 1000000 | G28: 1000000 | H28: 1000000 | I28: 1000000 | J28: 1000000 | K28: 1000000 | L28: 1000000 | M28: 1000000 | N28: 1000000 | O28: =SUM(C28:N28) -> 18567211
C30: =SUM(C21:C29) -> 1.2759667e+08 | D30: =SUM(D21:D28) -> 91321694 | E30: =SUM(E21:E28) -> 99450000 | F30: =SUM(F21:F28) -> 86450000 | G30: =SUM(G21:G28) -> 86450000 | H30: =SUM(H21:H28) -> 82950000 | I30: =SUM(I21:I28) -> 82950000 | J30: =SUM(J21:J28) -> 82950000 | K30: =SUM(K21:K28) -> 82950000 | ... N30: =SUM(N21:N28) -> 82950000
B33: Gastos Generales Insumos Medicos | C33: =SUM(C34:C38) -> 12800000 | D33: =SUM(D34:D38) -> 23800500 | E33: =SUM(E34:E38) -> 12801000 | F33: =SUM(F34:F38) -> 12801501 | G33: =SUM(G34:G38) -> 23802002 | H33: =SUM(H34:H38) -> 12802503 | I33: =SUM(I34:I38) -> 12803004 | J33: =SUM(J34:J38) -> 23803505 | ... N33: =SUM(N34:N38) -> 12805514 | O33: =SUM(C33:N33) -> 1.9763306e+08
B34: Gastos de Oficina | C34: 800000 | D34: 800000 | E34: 800000 | F34: 800000 | G34: 800000 | H34: 800000 | I34: 800000 | J34: 800000 | K34: 800000 | L34: 800000 | M34: 800000 | N34: 800000
B35: Gastos Operacionales | C35: 1500000 | D35: 1500000 | E35: 1500000 | F35: 1500000 | G35: 1500000 | H35: 1500000 | I35: 1500000 | J35: 1500000 | K35: 1500000 | L35: 1500000 | M35: 1500000 | N35: 1500000
B36: Gastos de Viajes | C36: 1000000 | D36: =+C36*1.0005 -> 1000500 | E36: =+D36*1.0005 -> 1001000.2 | F36: =+E36*1.0005 -> 1001500.8 | G36: =+F36*1.0005 -> 1002001.5 | H36: =+G36*1.0005 -> 1002502.5 | I36: =+H36*1.0005 -> 1003003.8 | J36: =+I36*1.0005 -> 1003505.3 | K36: =+J36*1.0005 -> 1004007 | ... N36: =+M36*1.0005 -> 1005513.8
B37: Gastos extras | D37: 11000000 | G37: 11000000 | J37: 11000000 | L37: 11000000
B38: Gastos de Personal | C38: 9500000 | D38: 9500000 | E38: 9500000 | F38: 9500000 | G38: 9500000 | H38: 9500000 | I38: 9500000 | J38: 9500000 | K38: 9500000 | L38: 9500000 | M38: 9500000 | N38: 9500000

Sheet Reporte 
C6: Reporte Mensual Rendiciones
C7: CL
C8: julio | E8: junio
B9: Rendiciones | C9: Neto | D9: Exento | E9: Neto | F9: Exento
B10: Air Heca | C10: 156941 | D10: 2852629 | E10: 250924 | F10: 5380655.7
B11: Operacionales | C11: 156941 | D11: 2852629 | E11: 250924 | F11: 5380655.7
B12: Total general | C12: 156941 | D12: 2852629 | E12: 250924 | F12: 5380655.7

Sheet Dashboard
B1: Fecha | C1: (Todas)
B3: Suma de Total
C4: julio | D4: junio | E4: Total general
B6: Operacionales | C6: 560250.17 | D6: 5324975.7 | E6: 5885225.9
B7: Bencina | D7: 118401 | E7: 118401
B8: Comidas y Bebidas | C8: 40369.6 | D8: 941620 | E8: 981989.6
B9: Envíos y encomiendas | C9: 24876.57 | D9: 91666 | E9: 116542.57
B10: Gastos de Viajes | C10: 495004 | E10: 495004
B11: Gastos Varios | D11: 44471.46 | E11: 44471.46
B12: Hospedaje | D12: 2340839 | E12: 2340839
B13: Peajes / Estacionamientos | D13: 125373 | E13: 125373
B14: Taxi - Uber | D14: 44261 | E14: 44261
B15: Gastos de Vehiculo | D15: 1618344.2 | E15: 1618344.2
B16: Total general | C16: 560250.17 | D16: 5324975.7 | E16: 5885225.9

Sheet Bancos 
B3: Reporte bancos HGI
B4: Bancos | C4: Rendiciones
C5: 2026 | M5: Total 2026 | N5: Total general
C6: ene | D6: feb | E6: mar | F6: abr | G6: may | H6: jun | I6: jul | J6: ago | K6: sept | L6: oct
B7: Chile
B8: Banco Internacional HGI | C8: 5599945.8 | D8: 2493217.6 | E8: 2449369.4 | F8: 2794773.7 | G8: 4614671.1 | H8: 1025796.6 | I8: 4329942.4 | J8: 1243366.3 | K8: 347577 | L8: 136520 | M8: 25035180 | N8: 25035180
B9: Adolfo Quintana | E9: 9157 | M9: 9157 | N9: 9157
B10: Alejandra Olivares | C10: 98560 | D10: 73464 | M10: 172024 | N10: 172024
B11: Brigitte Moran Mesa | C11: 400000 | G11: 443203.83 | I11: 900000 | M11: 1743203.8 | N11: 1743203.8
B12: Dailin Arellano | C12: 85348 | D12: 1246866 | F12: 535856.26 | G12: 1176889.4 | M12: 3044959.6 | N12: 3044959.6
B13: David Herce | C13: 2776652.4 | D13: 204639.42 | E13: 1509451.3 | F13: 420684.72 | G13: 49308 | H13: 354529 | I13: 140778 | J13: 70388.92 | M13: 5526431.8 | N13: 5526431.8
B14: Davis Torres | D14: 52286 | E14: 133629.1 | G14: 40019.95 | J14: 127195.53 | M14: 353130.58 | N14: 353130.58
B15: Javier Salazar | C15: 602683.18 | D15: 287717.01 | M15: 890400.19 | N15: 890400.19
B16: Manuel Guajardo | D16: 57343.17 | M16: 57343.17 | N16: 57343.17
B17: Mariangel Veloz | D17: 169414 | E17: 30393 | F17: 673690.91 | G17: 38990 | H17: 437147.92 | I17: 171201.14 | J17: 16759.96 | M17: 1537596.9 | N17: 1537596.9
B18: Raul Diaz | C18: 300000 | D18: 375320 | E18: 161732.72 | F18: 598791.36 | G18: 471274.93 | H18: 195970.71 | I18: 309838.64 | J18: 321274 | K18: 347577 | L18: 136520 | M18: 3218299.4 | N18: 3218299.4
B19: Tomas Castro | C19: 1298352 | D19: 26168 | E19: 50000 | F19: 26471 | G19: 604080 | H19: 20000 | I19: 1686739 | J19: 24516 | M19: 3736326 | N19: 3736326
B20: Deisy Sierra | F20: 103357.45 | I20: 211298.78 | J20: 529691.91 | M20: 844348.14 | N20: 844348.14
B21: Edgar hernandez | C21: 38350.19 | M21: 38350.19 | N21: 38350.19
B22: Abel Kottwitz | E22: 555006.3 | F22: 435922 | G22: 1790905 | H22: 18149 | I22: 785086.83 | J22: 149340 | M22: 3734409.1 | N22: 3734409.1
B23: Pia Cotronea | I23: 125000 | M23: 125000 | N23: 125000
B24: (en blanco) | I24: 125000 | M24: 125000 | N24: 125000
B25: Yohana Morillo | J25: 4200 | M25: 4200 | N25: 4200
B26: Scotianbank CLP | C26: 1933058.1 | E26: 790277 | H26: 3208366.4 | I26: 9573297.2 | J26: 2572787.6 | M26: 18077786 | N26: 18077786
B27: Alejandra Olivares | C27: 38711 | M27: 38711 | N27: 38711
B28: Brigitte Moran Mesa | C28: 402023 | H28: 850000 | I28: 454931.94 | M28: 1706954.9 | N28: 1706954.9
B29: Dailin Arellano | E29: 790277 | H29: 222315 | I29: 512688.77 | M29: 1525280.8 | N29: 1525280.8
B30: David Herce | H30: 148778.38 | J30: 775838.4 | M30: 924616.78 | N30: 924616.78
B31: Mariangel Veloz | J31: 545740 | M31: 545740 | N31: 545740
B32: Raul Diaz | H32: 91070.42 | I32: 241312 | J32: 331825.08 | M32: 664207.5 | N32: 664207.5
B33: Tomas Castro | C33: 1243599 | H33: 57871 | M33: 1301470 | N33: 1301470
B34: Edgar hernandez | C34: 248725.07 | M34: 248725.07 | N34: 248725.07
B35: Abel Kottwitz | H35: 1484052 | J35: 419384.14 | M35: 1903436.1 | N35: 1903436.1
B36: Rodrigo Ibañez | H36: 354279.56 | I36: 8364364.5 | M36: 8718644.1 | N36: 8718644.1
B37: 1 | H37: 354279.56 | M37: 354279.56 | N37: 354279.56
B38: 2 | I38: 2479139 | M38: 2479139 | N38: 2479139
B39: 3 | I39: 5885225.5 | M39: 5885225.5 | N39: 5885225.5
B40: Edynar Monsalbe | J40: 500000 | M40: 500000 | N40: 500000
B41: 1 | J41: 500000 | M41: 500000 | N41: 500000
B42: Total general | C42: 7533003.8 | D42: 2493217.6 | E42: 3239646.4 | F42: 2794773.7 | G42: 4614671.1 | H42: 4234163 | I42: 13903240 | J42: 3816153.9 | K42: 347577 | L42: 136520 | M42: 43112966 | N42: 43112966

Sheet HGI
C6: Reporte Mensual Rendiciones
B7: Insumos medicos | C7: CL
B8: Rendiciones | C8: octubre | D8: enero | E8: febrero | F8: marzo | G8: abril | H8: mayo | I8: junio | J8: julio | K8: agosto | L8: Total general
B9: Adolfo Quintana | F9: 9157 | L9: 9157
B10: Alejandra Olivares | D10: 137271 | E10: 73464 | L10: 210735
B11: Brigitte Moran Mesa | D11: 769022.02 | H11: 476204.81 | I11: 951730.92 | J11: 1044741.7 | K11: 279646.91 | L11: 3521346.3
B12: Dailin Arellano | E12: 1118303 | F12: 1004188 | G12: 535856.26 | H12: 1174049.4 | I12: 320700 | J12: 380152.77 | L12: 4533249.4
B13: David Herce | D13: 2776652.4 | E13: 204639.42 | F13: 1509451.3 | G13: 420684.72 | H13: 49308 | I13: 503307.38 | J13: 140778 | K13: 846227.32 | L13: 6451048.5
B14: Davis Torres | E14: 52286 | F14: 133629.1 | H14: 370311.59 | I14: 30928.1 | J14: 21949.55 | K14: 144026.24 | L14: 753130.58
B15: Javier Salazar | D15: 602683.18 | E15: 287717.01 | L15: 890400.19
B16: Manuel Guajardo | E16: 57343.17 | L16: 57343.17
B17: Mariangel Veloz | E17: 169414 | F17: 30393 | G17: 670690.91 | H17: 38990 | I17: 465222.92 | J17: 171201.14 | K17: 562499.96 | L17: 2108411.9
B18: Raul Diaz | C18: 119300.42 | D18: 279475.74 | E18: 295844.02 | F18: 261732.96 | G18: 598791.36 | H18: 379054.93 | I18: 353823.07 | J18: 484368.21 | K18: 653099.01 | L18: 3425489.7
B19: Tomas Castro | D19: 2541951 | E19: 26168 | F19: 50000 | G19: 26471 | H19: 604080 | I19: 77871 | J19: 1686739 | K19: 213496 | L19: 5226776
B20: Deisy Sierra | G20: 103357.45 | J20: 211298.78 | K20: 529691.91 | L20: 844348.14
B21: Edgar hernandez | D21: 287075.26 | L21: 287075.26
B22: Abel Kottwitz | E22: 130755.15 | F22: 441251.15 | G22: 470590.62 | H22: 1852319.6 | I22: 2024147.3 | J22: 1009225.3 | K22: 721769.93 | L22: 6650059.1
B23: Rodrigo Ibañez | I23: 5679255.3 | J23: 3039388.8 | L23: 8718644.1
B24: Pia Cotronea | I24: 96032 | J24: 34040 | L24: 130072
B25: Yohana Morillo | K25: 4200 | L25: 4200
B26: Edynar Monsalbe | K26: 762889.96 | L26: 762889.96
B27: Total general | C27: 119300.42 | D27: 7394130.6 | E27: 2415933.8 | F27: 3439802.5 | G27: 2826442.3 | H27: 4944318.3 | I27: 10503018 | J27: 8223883.2 | K27: 4717547.2 | L27: 44584376
N32: 1635285
N33: 1299644.6 | P33: =+N32*P34 -> 1105869.4
N34: =+N33/N32 -> 0.79475113 | P34: 0.6762548
N36: 314049 | P36: =+N36 -> 314049
N37: =+N36/N32 -> 0.19204542
N39: 21591.41 | P39: =+N32-P33-P36 -> 215366.68
N40: =+N39/N32 -> 0.013203454 | P40: =+P39/N32 -> 0.13169978

Sheet Rendiciones
B3: =Rendiciones[[#Totals],[Saldo Fondo ]] -> 14185.203 | AA3: =30000/1.19 -> 25210.084
B4: Nombre Solicitante | C4: Nro Rend. | D4: Fecha | E4: Semana | F4: Mes | G4: C.C. | H4: Cuenta | I4: Detalle | J4: Concepto | K4: Tipo Doc | L4: Monto Neto | M4: Monto Exento | N4: Iva | O4: Total | P4: Pagado por | Q4: Fecha de Pago | R4: Monto | S4: Saldo Fondo | T4: Columna1
B5: Brigitte Moran Mesa | D5: 46031 | E5: Del 05 al 09 | F5: =IF(Rendiciones[[#This Row],[Fecha ]]<>"",TEXT(Rendiciones[[#This Row],[Fecha ]],"MMMM"),"") -> enero | G5: HGI. | N5: =Rendiciones[[#This Row],[Monto Neto ]]*19% -> 0 | O5: =+Rendiciones[[#This Row],[Monto Neto ]]+Rendiciones[[#This Row],[Monto Exento ]]+Rendiciones[[#This Row],[Iva]] -> 0 | P5: Banco Internacional HGI | Q5: 46031 | R5: 400000 | S5: =Rendiciones[[#This Row],[Total ]]-Rendiciones[[#This Row],[Monto ]] -> -400000
B6: Raul Diaz | D6: 46035 | E6: Del 12 al 16 | F6: =IF(Rendiciones[[#This Row],[Fecha ]]<>"",TEXT(Rendiciones[[#This Row],[Fecha ]],"MMMM"),"") -> enero | N6: =Rendiciones[[#This Row],[Monto Neto ]]*19% -> 0 | O6: =+Rendiciones[[#This Row],[Monto Neto ]]+Rendiciones[[#This Row],[Monto Exento ]]+Rendiciones[[#This Row],[Iva]] -> 0 | P6: Banco Internacional HGI | Q6: 46035 | R6: 300000 | S6: =Rendiciones[[#This Row],[Total ]]-Rendiciones[[#This Row],[Monto ]] -> -300000
B7: Alejandra Olivares | C7: 1 | D7: 46030 | E7: Del 05 al 09 | F7: =IF(Rendiciones[[#This Row],[Fecha ]]<>"",TEXT(Rendiciones[[#This Row],[Fecha ]],"MMMM"),"") -> enero | G7: HG | H7: Oficina | I7: Miscelaneos Administracion | M7: 35899 | N7: =Rendiciones[[#This Row],[Monto Neto ]]*19% -> 0 | O7: =+Rendiciones[[#This Row],[Monto Neto ]]+Rendiciones[[#This Row],[Monto Exento ]]+Rendiciones[[#This Row],[Iva]] -> 35899 | S7: =Rendiciones[[#This Row],[Total ]]-Rendiciones[[#This Row],[Monto ]] -> 35899
B8: Alejandra Olivares | C8: 1 | D8: 46030 | E8: Del 05 al 09 | F8: =IF(Rendiciones[[#This Row],[Fecha ]]<>"",TEXT(Rendiciones[[#This Row],[Fecha ]],"MMMM"),"") -> enero | G8: HG | H8: Oficina | I8: Artículos de Oficina | M8: 12620 | N8: =Rendiciones[[#This Row],[Monto Neto ]]*19% -> 0 | O8: =+Rendiciones[[#This Row],[Monto Neto ]]+Rendiciones[[#This Row],[Monto Exento ]]+Rendiciones[[#This Row],[Iva]] -> 12620 | P8: Banco Internacional HGI | Q8: 46031 | R8: 48519 | S8: =Rendiciones[[#This Row],[Total ]]-Rendiciones[[#This Row],[Monto ]] -> -35899
B9: Javier Salazar | C9: 1 | D9: 46030 | E9: Del 05 al 09 | F9: =IF(Rendiciones[[#This Row],[Fecha ]]<>"",TEXT(Rendiciones[[#This Row],[Fecha ]],"MMMM"),"") -> enero | G9: HGI. | H9: Operacionales | I9: Bodega | K9: Factura | L9: 12580 | N9: =Rendiciones[[#This Row],[Monto Neto ]]*19% -> 2390.2 | O9: =+Rendiciones[[#This Row],[Monto Neto ]]+Rendiciones[[#This Row],[Monto Exento ]]+Rendiciones[[#This Row],[Iva]] -> 14970.2 | S9: =Rendiciones[[#This Row],[Total ]]-Rendiciones[[#This Row],[Monto ]] -> 14970.2
B10: Javier Salazar | C10: 1 | D10: 46030 | E10: Del 05 al 09 | F10: =IF(Rendiciones[[#This Row],[Fecha ]]<>"",TEXT(Rendiciones[[#This Row],[Fecha ]],"MMMM"),"") -> enero | G10: HGI. | H10: Operacionales | I10: Bodega | K10: Factura | L10: 49588 | N10: =Rendiciones[[#This Row],[Monto Neto ]]*19% -> 9421.72 | O10: =+Rendiciones[[#This Row],[Monto Neto ]]+Rendiciones[[#This Row],[Monto Exento ]]+Rendiciones[[#This Row],[Iva]] -> 59009.72 | S10: =Rendiciones[[#This Row],[Total ]]-Rendiciones[[#This Row],[Monto ]] -> 59009.72
B11: Javier Salazar | C11: 1 | D11: 46030 | E11: Del 05 al 09 | F11: =IF(Rendiciones[[#This Row],[Fecha ]]<>"",TEXT(Rendiciones[[#This Row],[Fecha ]],"MMMM"),"") -> enero | G11: HGI. | H11: Operacionales | I11: Peajes / Estacionamientos | M11: 750 | N11: =Rendiciones[[#This Row],[Monto Neto ]]*19% -> 0 | O11: =+Rendiciones[[#This Row],[Monto Neto ]]+Rendiciones[[#This Row],[Monto Exento ]]+Rendiciones[[#This Row],[Iva]] -> 750 | S11: =Rendiciones[[#This Row],[Total ]]-Rendiciones[[#This Row],[Monto ]] -> 750
B12: Javier Salazar | C12: 1 | D12: 46030 | E12: Del 05 al 09 | F12: =IF(Rendiciones[[#This Row],[Fecha ]]<>"",TEXT(Rendiciones[[#This Row],[Fecha ]],"MMMM"),"") -> enero | G12: HGI. | H12: Operacionales | I12: Comidas y Bebidas | M12: 10000 | N12: =Rendiciones[[#This Row],[Monto Neto ]]*19% -> 0 | O12: =+Rendiciones[[#This Row],[Monto Neto ]]+Rendiciones[[#This Row],[Monto Exento ]]+Rendiciones[[#This Row],[Iva]] -> 10000 | P12: Banco Internacional HGI | Q12: 46031 | R12: 84729.92 | S12: =Rendiciones[[#This Row],[Total ]]-Rendiciones[[#This Row],[Monto ]] -> -74729.92
B13: David Herce | C13: 1 | D13: 46034 | E13: Del 12 al 16 | F13: =IF(Rendiciones[[#This Row],[Fecha ]]<>"",TEXT(Rendiciones[[#This Row],[Fecha ]],"MMMM"),"") -> enero | G13: O. PAÍS | H13: Activo fijo | I13: Equipos Electronicos y de Computacion | K13: Factura | L13: 588227 | N13: =Rendiciones[[#This Row],[Monto Neto ]]*19% -> 111763.13 | O13: =+Rendiciones[[#This Row],[Monto Neto ]]+Rendiciones[[#This Row],[Monto Exento ]]+Rendiciones[[#This Row],[Iva]] -> 699990.13 | P13: Banco Internacional HGI | Q13: 46037 | R13: 699990 | S13: =Rendiciones[[#This Row],[Total ]]-Rendiciones[[#This Row],[Monto ]] -> 0.13
B14: Alejandra Olivares | C14: 2 | D14: 46037 | E14: Del 12 al 16 | F14: =IF(Rendiciones[[#This Row],[Fecha ]]<>"",TEXT(Rendiciones[[#This Row],[Fecha ]],"MMMM"),"") -> enero | G14: HG | H14: Oficina | I14: Miscelaneos Administracion | M14: =22131+6990 -> 29121 | N14: =Rendiciones[[#This Row],[Monto Neto ]]*19% -> 0 | O14: =+Rendiciones[[#This Row],[Monto Neto ]]+Rendiciones[[#This Row],[Monto Exento ]]+Rendiciones[[#This Row],[Iva]] -> 29121 | S14: =Rendiciones[[#This Row],[Total ]]-Rendiciones[[#This Row],[Monto ]] -> 29121
B15: Alejandra Olivares | C15: 2 | D15: 46037 | E15: Del 12 al 16 | F15: =IF(Rendiciones[[#This Row],[Fecha ]]<>"",TEXT(Rendiciones[[#This Row],[Fecha ]],"MMMM"),"") -> enero | G15: HG | H15: Oficina | I15: Artículos de Aseo | M15: =5340+2590+12990 -> 20920 | N15: =Rendiciones[[#This Row],[Monto Neto ]]*19% -> 0 | O15: =+Rendiciones[[#This Row],[Monto Neto ]]+Rendiciones[[#This Row],[Monto Exento ]]+Rendiciones[[#This Row],[Iva]] -> 20920 | P15: Banco Internacional HGI | Q15: 46037 | R15: 50041 | S15: =Rendiciones[[#This Row],[Total ]]-Rendiciones[[#This Row],[Monto ]] -> -29121
B16: Javier Salazar | C16: 2 | D16: 46037 | E16: Del 12 al 16 | F16: =IF(Rendiciones[[#This Row],[Fecha ]]<>"",TEXT(Rendiciones[[#This Row],[Fecha ]],"MMMM"),"") -> enero | G16: HGI. | H16: Operacionales | I16: Bencina | K16: Factura | L16: 32318 | M16: =5236+4701+300 -> 10237 | N16: =Rendiciones[[#This Row],[Monto Neto ]]*19% -> 6140.42 | O16: =+Rendiciones[[#This Row],[Monto Neto ]]+Rendiciones[[#This Row],[Monto Exento ]]+Rendiciones[[#This Row],[Iva]] -> 48695.42 | S16: =Rendiciones[[#This Row],[Total ]]-Rendiciones[[#This Row],[Monto ]] -> 48695.42
B17: Javier Salazar | C17: 2 | D17: 46037 | E17: Del 12 al 16 | F17: =IF(Rendiciones[[#This Row],[Fecha ]]<>"",TEXT(Rendiciones[[#This Row],[Fecha ]],"MMMM"),"") -> enero | G17: HGI. | H17: Operacionales | I17: Reparaciones y remodelaciones | K17: Factura | L17: 230728 | N17: =Rendiciones[[#This Row],[Monto Neto ]]*19% -> 43838.32 | O17: =+Rendiciones[[#This Row],[Monto Neto ]]+Rendiciones[[#This Row],[Monto Exento ]]+Rendiciones[[#This Row],[Iva]] -> 274566.32 | S17: =Rendiciones[[#This Row],[Total ]]-Rendiciones[[#This Row],[Monto ]] -> 274566.32
B18: Javier Salazar | C18: 2 | D18: 46037 | E18: Del 12 al 16 | F18: =IF(Rendiciones[[#This Row],[Fecha ]]<>"",TEXT(Rendiciones[[#This Row],[Fecha ]],"MMMM"),"") -> enero | G18: HGI. | H18: Operacionales | I18: Reparaciones y remodelaciones | K18: Factura | L18: -95003.6 | N18: =Rendiciones[[#This Row],[Monto Neto ]]*19% -> -18050.684 | O18: =+Rendiciones[[#This Row],[Monto Neto ]]+Rendiciones[[#This Row],[Monto Exento ]]+Rendiciones[[#This Row],[Iva]] -> -113054.28 | S18: =Rendiciones[[#This Row],[Total ]]-Rendiciones[[#This Row],[Monto ]] -> -113054.28
B19: Javier Salazar | C19: 2 | D19: 46037 | E19: Del 12 al 16 | F19: =IF(Rendiciones[[#This Row],[Fecha ]]<>"",TEXT(Rendiciones[[#This Row],[Fecha ]],"MMMM"),"") -> enero | G19: HGI. | H19: Operacionales | I19: Peajes / Estacionamientos | M19: =1600+1350 -> 2950 | N19: =Rendiciones[[#This Row],[Monto Neto ]]*19% -> 0 | O19: =+Rendiciones[[#This Row],[Monto Neto ]]+Rendiciones[[#This Row],[Monto Exento ]]+Rendiciones[[#This Row],[Iva]] -> 2950 | S19: =Rendiciones[[#This Row],[Total ]]-Rendiciones[[#This Row],[Monto ]] -> 2950
B20: Javier Salazar | C20: 2 | D20: 46037 | E20: Del 12 al 16 | F20: =IF(Rendiciones[[#This Row],[Fecha ]]<>"",TEXT(Rendiciones[[#This Row],[Fecha ]],"MMMM"),"") -> enero | G20: HGI. | H20: Operacionales | I20: Comidas y Bebidas | M20: 15950 | N20: =Rendiciones[[#This Row],[Monto Neto ]]*19% -> 0 | O20: =+Rendiciones[[#This Row],[Monto Neto ]]+Rendiciones[[#This Row],[Monto Exento ]]+Rendiciones[[#This Row],[Iva]] -> 15950 | S20: =Rendiciones[[#This Row],[Total ]]-Rendiciones[[#This Row],[Monto ]] -> 15950
B21: Javier Salazar | C21: 2 | D21: 46037 | E21: Del 12 al 16 | F21: =IF(Rendiciones[[#This Row],[Fecha ]]<>"",TEXT(Rendiciones[[#This Row],[Fecha ]],"MMMM"),"") -> enero | G21: HGI. | H21: Operacionales | I21: Otros | M21: 1200 | N21: =Rendiciones[[#This Row],[Monto Neto ]]*19% -> 0 | O21: =+Rendiciones[[#This Row],[Monto Neto ]]+Rendiciones[[#This Row],[Monto Exento ]]+Rendiciones[[#This Row],[Iva]] -> 1200 | P21: Banco Internacional HGI | Q21: 46038 | R21: 343361 | S21: =Rendiciones[[#This Row],[Total ]]-Rendiciones[[#This Row],[Monto ]] -> -342161
B22: David Herce | C22: 2 | D22: 46038 | E22: Del 12 al 16 | F22: =IF(Rendiciones[[#This Row],[Fecha ]]<>"",TEXT(Rendiciones[[#This Row],[Fecha ]],"MMMM"),"") -> enero | G22: O. PAÍS | H22: Activo fijo | I22: Equipos Electronicos y de Computacion | K22: Factura | L22: 129395 | N22: =Rendiciones[[#This Row],[Monto Neto ]]*19% -> 24585.05 | O22: =+Rendiciones[[#This Row],[Monto Neto ]]+Rendiciones[[#This Row],[Monto Exento ]]+Rendiciones[[#This Row],[Iva]] -> 153980.05 | S22: =Rendiciones[[#This Row],[Total ]]-Rendiciones[[#This Row],[Monto ]] -> 153980.05
B23: David Herce | C23: 3 | D23: 46038 | E23: Del 12 al 16 | F23: =IF(Rendiciones[[#This Row],[Fecha ]]<>"",TEXT(Rendiciones[[#This Row],[Fecha ]],"MMMM"),"") -> enero | G23: HG | H23: Operacionales | I23: Bencina | K23: Factura | M23: 20000 | N23: =Rendiciones[[#This Row],[Monto Neto ]]*19% -> 0 | O23: =+Rendiciones[[#This Row],[Monto Neto ]]+Rendiciones[[#This Row],[Monto Exento ]]+Rendiciones[[#This Row],[Iva]] -> 20000 | S23: =Rendiciones[[#This Row],[Total ]]-Rendiciones[[#This Row],[Monto ]] -> 20000
B24: David Herce | C24: 3 | D24: 46038 | E24: Del 12 al 16 | F24: =IF(Rendiciones[[#This Row],[Fecha ]]<>"",TEXT(Rendiciones[[#This Row],[Fecha ]],"MMMM"),"") -> enero | G24: HG | H24: Operacionales | I24: Taxi - Uber | M24: 22722 | N24: =Rendiciones[[#This Row],[Monto Neto ]]*19% -> 0 | O24: =+Rendiciones[[#This Row],[Monto Neto ]]+Rendiciones[[#This Row],[Monto Exento ]]+Rendiciones[[#This Row],[Iva]] -> 22722 | S24: =Rendiciones[[#This Row],[Total ]]-Rendiciones[[#This Row],[Monto ]] -> 22722
B25: David Herce | C25: 4 | D25: 46038 | E25: Del 12 al 16 | F25: =IF(Rendiciones[[#This Row],[Fecha ]]<>"",TEXT(Rendiciones[[#This Row],[Fecha ]],"MMMM"),"") -> enero | G25: O. PAÍS | H25: Activo fijo | I25: Equipos Electronicos y de Computacion | K25: Factura | L25: 1428555 | N25: =Rendiciones[[#This Row],[Monto Neto ]]*19% -> 271425.45 | O25: =+Rendiciones[[#This Row],[Monto Neto ]]+Rendiciones[[#This Row],[Monto Exento ]]+Rendiciones[[#This Row],[Iva]] -> 1699980.4 | S25: =Rendiciones[[#This Row],[Total ]]-Rendiciones[[#This Row],[Monto ]] -> 1699980.4
B26: David Herce | C26: 4 | D26: 46038 | E26: Del 12 al 16 | F26: =IF(Rendiciones[[#This Row],[Fecha ]]<>"",TEXT(Rendiciones[[#This Row],[Fecha ]],"MMMM"),"") -> enero | G26: O. PAÍS | H26: Activo fijo | I26: Equipos Electronicos y de Computacion | K26: Factura | L26: 151243.5 | N26: =Rendiciones[[#This Row],[Monto Neto ]]*19% -> 28736.265 | O26: =+Rendiciones[[#This Row],[Monto Neto ]]+Rendiciones[[#This Row],[Monto Exento ]]+Rendiciones[[#This Row],[Iva]] -> 179979.77 | P26: Banco Internacional HGI | Q26: 46041 | R26: 2076662.4 | S26: =Rendiciones[[#This Row],[Total ]]-Rendiciones[[#This Row],[Monto ]] -> -1896682.6
B27: Raul Diaz | C27: 1 | D27: 46038 | E27: Del 12 al 16 | F27: =IF(Rendiciones[[#This Row],[Fecha ]]<>"",TEXT(Rendiciones[[#This Row],[Fecha ]],"MMMM"),"") -> enero | G27: HG | H27: Operacionales | I27: Bencina | K27: Factura | L27: 33915 | M27: =5439+4209 -> 9648 | N27: =Rendiciones[[#This Row],[Monto Neto ]]*19% -> 6443.85 | O27: =+Rendiciones[[#This Row],[Monto Neto ]]+Rendiciones[[#This Row],[Monto Exento ]]+Rendiciones[[#This Row],[Iva]] -> 50006.85 | S27: =Rendiciones[[#This Row],[Total ]]-Rendiciones[[#This Row],[Monto ]] -> 50006.85
B28: Raul Diaz | C28: 1 | D28: 46038 | E28: Del 12 al 16 | F28: =IF(Rendiciones[[#This Row],[Fecha ]]<>"",TEXT(Rendiciones[[#This Row],[Fecha ]],"MMMM"),"") -> enero | G28: HG | H28: Operacionales | I28: Bodega | K28: Factura | L28: 184831 | N28: =Rendiciones[[#This Row],[Monto Neto ]]*19% -> 35117.89 | O28: =+Rendiciones[[#This Row],[Monto Neto ]]+Rendiciones[[#This Row],[Monto Exento ]]+Rendiciones[[#This Row],[Iva]] -> 219948.89 | S28: =Rendiciones[[#This Row],[Total ]]-Rendiciones[[#This Row],[Monto ]] -> 219948.89
B29: Raul Diaz | C29: 1 | D29: 46038 | E29: Del 12 al 16 | F29: =IF(Rendiciones[[#This Row],[Fecha ]]<>"",TEXT(Rendiciones[[#This Row],[Fecha ]],"MMMM"),"") -> enero | G29: HG | H29: Operacionales | I29: Peajes / Estacionamientos | M29: =2950+400+470 -> 3820 | N29: =Rendiciones[[#This Row],[Monto Neto ]]*19% -> 0 | O29: =+Rendiciones[[#This Row],[Monto Neto ]]+Rendiciones[[#This Row],[Monto Exento ]]+Rendiciones[[#This Row],[Iva]] -> 3820 | S29: =Rendiciones[[#This Row],[Total ]]-Rendiciones[[#This Row],[Monto ]] -> 3820
B30: Raul Diaz | C30: 1 | D30: 46038 | E30: Del 12 al 16 | F30: =IF(Rendiciones[[#This Row],[Fecha ]]<>"",TEXT(Rendiciones[[#This Row],[Fecha ]],"MMMM"),"") -> enero | G30: HG | H30: Operacionales | I30: Otros | M30: =2700+3000 -> 5700 | N30: =Rendiciones[[#This Row],[Monto Neto ]]*19% -> 0 | O30: =+Rendiciones[[#This Row],[Monto Neto ]]+Rendiciones[[#This Row],[Monto Exento ]]+Rendiciones[[#This Row],[Iva]] -> 5700 | P30: No Genera Pago | S30: =Rendiciones[[#This Row],[Total ]]-Rendiciones[[#This Row],[Monto ]] -> 5700
B31: Javier Salazar | C31: 2 | D31: 46045 | E31: Del 19 al 23 | F31: =IF(Rendiciones[[#This Row],[Fecha ]]<>"",TEXT(Rendiciones[[#This Row],[Fecha ]],"MMMM"),"") -> enero | G31: HGI. | N31: =Rendiciones[[#This Row],[Monto Neto ]]*19% -> 0 | O31: =+Rendiciones[[#This Row],[Monto Neto ]]+Rendiciones[[#This Row],[Monto Exento ]]+Rendiciones[[#This Row],[Iva]] -> 0 | P31: Banco Internacional HGI | Q31: 46045 | R31: -113053.54 | S31: =Rendiciones[[#This Row],[Total ]]-Rendiciones[[#This Row],[Monto ]] -> 113053.54
B32: Alejandra Olivares | C32: 3 | D32: 46044 | E32: Del 19 al 23 | F32: =IF(Rendiciones[[#This Row],[Fecha ]]<>"",TEXT(Rendiciones[[#This Row],[Fecha ]],"MMMM"),"") -> enero | G32: HG | H32: Oficina | I32: Miscelaneos Administracion | M32: 27009 | N32: =Rendiciones[[#This Row],[Monto Neto ]]*19% -> 0 | O32: =+Rendiciones[[#This Row],[Monto Neto ]]+Rendiciones[[#This Row],[Monto Exento ]]+Rendiciones[[#This Row],[Iva]] -> 27009 | S32: =Rendiciones[[#This Row],[Total ]]-Rendiciones[[#This Row],[Monto ]] -> 27009
B33: Alejandra Olivares | C33: 3 | D33: 46044 | E33: Del 19 al 23 | F33: =IF(Rendiciones[[#This Row],[Fecha ]]<>"",TEXT(Rendiciones[[#This Row],[Fecha ]],"MMMM"),"") -> enero | G33: HG | H33: Oficina | I33: Envíos y encomiendas | M33: 11702 | N33: =Rendiciones[[#This Row],[Monto Neto ]]*19% -> 0 | O33: =+Rendiciones[[#This Row],[Monto Neto ]]+Rendiciones[[#This Row],[Monto Exento ]]+Rendiciones[[#This Row],[Iva]] -> 11702 | P33: Scotianbank CLP | Q33: 46045 | R33: 38711 | S33: =Rendiciones[[#This Row],[Total ]]-Rendiciones[[#This Row],[Monto ]] -> -27009
B34: Tomas Castro | C34: 1 | D34: 46043 | E34: Del 19 al 23 | F34: =IF(Rendiciones[[#This Row],[Fecha ]]<>"",TEXT(Rendiciones[[#This Row],[Fecha ]],"MMMM"),"") -> enero | G34: HG | H34: Operacionales | I34: Patente | M34: 1291352 | N34: =Rendiciones[[#This Row],[Monto Neto ]]*19% -> 0 | O34: =+Rendiciones[[#This Row],[Monto Neto ]]+Rendiciones[[#This Row],[Monto Exento ]]+Rendiciones[[#This Row],[Iva]] -> 1291352 | P34: Banco Internacional HGI | Q34: 46043 | R34: 1291352 | S34: =Rendiciones[[#This Row],[Total ]]-Rendiciones[[#This Row],[Monto ]] -> 0
B35: Tomas Castro | C35: 1 | D35: 46043 | E35: Del 19 al 23 | F35: =IF(Rendiciones[[#This Row],[Fecha ]]<>"",TEXT(Rendiciones[[#This Row],[Fecha ]],"MMMM"),"") -> enero | G35: HG | H35: Operacionales | I35: Patente | M35: 1243599 | N35: =Rendiciones[[#This Row],[Monto Neto ]]*19% -> 0 | O35: =+Rendiciones[[#This Row],[Monto Neto ]]+Rendiciones[[#This Row],[Monto Exento ]]+Rendiciones[[#This Row],[Iva]] -> 1243599 | P35: Scotianbank CLP | Q35: 46045 | R35: 500000 | S35: =Rendiciones[[#This Row],[Total ]]-Rendiciones[[#This Row],[Monto ]] -> 743599
B36: Edgar hernandez | C36: 1 | D36: 46041 | E36: Del 19 al 23 | F36: =IF(Rendiciones[[#This Row],[Fecha ]]<>"",TEXT(Rendiciones[[#This Row],[Fecha ]],"MMMM"),"") -> enero | G36: HG | H36: Extras | I36: Bencina | K36: Factura | L36: 13544 | M36: =2189+1694 -> 3883 | N36: =Rendiciones[[#This Row],[Monto Neto ]]*19% -> 2573.36 | O36: =+Rendiciones[[#This Row],[Monto Neto ]]+Rendiciones[[#This Row],[Monto Exento ]]+Rendiciones[[#This Row],[Iva]] -> 20000.36 | S36: =Rendiciones[[#This Row],[Total ]]-Rendiciones[[#This Row],[Monto ]] -> 20000.36
B37: Edgar hernandez | C37: 1 | D37: 46041 | E37: Del 19 al 23 | F37: =IF(Rendiciones[[#This Row],[Fecha ]]<>"",TEXT(Rendiciones[[#This Row],[Fecha ]],"MMMM"),"") -> enero | G37: HG | H37: Extras | I37: Bencina | K37: Factura | L37: 28029 | M37: =4489+3474 -> 7963 | N37: =Rendiciones[[#This Row],[Monto Neto ]]*19% -> 5325.51 | O37: =+Rendiciones[[#This Row],[Monto Neto ]]+Rendiciones[[#This Row],[Monto Exento ]]+Rendiciones[[#This Row],[Iva]] -> 41317.51 | S37: =Rendiciones[[#This Row],[Total ]]-Rendiciones[[#This Row],[Monto ]] -> 41317.51
B38: Edgar hernandez | C38: 1 | D38: 46041 | E38: Del 19 al 23 | F38: =IF(Rendiciones[[#This Row],[Fecha ]]<>"",TEXT(Rendiciones[[#This Row],[Fecha ]],"MMMM"),"") -> enero | G38: HG | H38: Extras | I38: Bencina | K38: Factura | L38: 24329 | M38: =3973+3075+500 -> 7548 | N38: =Rendiciones[[#This Row],[Monto Neto ]]*19% -> 4622.51 | O38: =+Rendiciones[[#This Row],[Monto Neto ]]+Rendiciones[[#This Row],[Monto Exento ]]+Rendiciones[[#This Row],[Iva]] -> 36499.51 | S38: =Rendiciones[[#This Row],[Total ]]-Rendiciones[[#This Row],[Monto ]] -> 36499.51
B39: Edgar hernandez | C39: 1 | D39: 46041 | E39: Del 19 al 23 | F39: =IF(Rendiciones[[#This Row],[Fecha ]]<>"",TEXT(Rendiciones[[#This Row],[Fecha ]],"MMMM"),"") -> enero | G39: HG | H39: Extras | I39: Bencina | K39: Factura | L39: 22588 | M39: =3753+3369+500 -> 7622 | N39: =Rendiciones[[#This Row],[Monto Neto ]]*19% -> 4291.72 | O39: =+Rendiciones[[#This Row],[Monto Neto ]]+Rendiciones[[#This Row],[Monto Exento ]]+Rendiciones[[#This Row],[Iva]] -> 34501.72 | S39: =Rendiciones[[#This Row],[Total ]]-Rendiciones[[#This Row],[Monto ]] -> 34501.72
B40: Edgar hernandez | C40: 1 | D40: 46041 | E40: Del 19 al 23 | F40: =IF(Rendiciones[[#This Row],[Fecha ]]<>"",TEXT(Rendiciones[[#This Row],[Fecha ]],"MMMM"),"") -> enero | G40: HG | H40: Extras | I40: Bencina | K40: Factura | L40: 23930 | M40: =3975+3569+500 -> 8044 | N40: =Rendiciones[[#This Row],[Monto Neto ]]*19% -> 4546.7 | O40: =+Rendiciones[[#This Row],[Monto Neto ]]+Rendiciones[[#This Row],[Monto Exento ]]+Rendiciones[[#This Row],[Iva]] -> 36520.7 | S40: =Rendiciones[[#This Row],[Total ]]-Rendiciones[[#This Row],[Monto ]] -> 36520.7
B41: Edgar hernandez | C41: 1 | D41: 46041 | E41: Del 19 al 23 | F41: =IF(Rendiciones[[#This Row],[Fecha ]]<>"",TEXT(Rendiciones[[#This Row],[Fecha ]],"MMMM"),"") -> enero | G41: HG | H41: Oficina | I41: Artículos de Oficina | M41: 9819 | N41: =Rendiciones[[#This Row],[Monto Neto ]]*19% -> 0 | O41: =+Rendiciones[[#This Row],[Monto Neto ]]+Rendiciones[[#This Row],[Monto Exento ]]+Rendiciones[[#This Row],[Iva]] -> 9819 | S41: =Rendiciones[[#This Row],[Total ]]-Rendiciones[[#This Row],[Monto ]] -> 9819
B42: Edgar hernandez | C42: 1 | D42: 46041 | E42: Del 19 al 23 | F42: =IF(Rendiciones[[#This Row],[Fecha ]]<>"",TEXT(Rendiciones[[#This Row],[Fecha ]],"MMMM"),"") -> enero | G42: HG | H42: Extras | I42: Comidas y Bebidas | M42: =5500+6069+2740+3800+4605+5340.4 -> 28054.4 | N42: =Rendiciones[[#This Row],[Monto Neto ]]*19% -> 0 | O42: =+Rendiciones[[#This Row],[Monto Neto ]]+Rendiciones[[#This Row],[Monto Exento ]]+Rendiciones[[#This Row],[Iva]] -> 28054.4 | S42: =Rendiciones[[#This Row],[Total ]]-Rendiciones[[#This Row],[Monto ]] -> 28054.4
B43: Edgar hernandez | C43: 1 | D43: 46041 | E43: Del 19 al 23 | F43: =IF(Rendiciones[[#This Row],[Fecha ]]<>"",TEXT(Rendiciones[[#This Row],[Fecha ]],"MMMM"),"") -> enero | G43: HG | H43: Extras | I43: Peajes / Estacionamientos | M43: 3900.4 | N43: =Rendiciones[[#This Row],[Monto Neto ]]*19% -> 0 | O43: =+Rendiciones[[#This Row],[Monto Neto ]]+Rendiciones[[#This Row],[Monto Exento ]]+Rendiciones[[#This Row],[Iva]] -> 3900.4 | P43: Scotianbank CLP | Q43: 46045 | R43: 210613.6 | S43: =Rendiciones[[#This Row],[Total ]]-Rendiciones[[#This Row],[Monto ]] -> -206713.2
B44: Edgar hernandez | C44: 2 | D44: 46050 | E44: Del 26 al 30 | F44: =IF(Rendiciones[[#This Row],[Fecha ]]<>"",TEXT(Rendiciones[[#This Row],[Fecha ]],"MMMM"),"") -> enero | G44: HG | H44: Extras | I44: Bencina | K44: Factura | L44: 19313 | M44: =3091+1938+500 -> 5529 | N44: =Rendiciones[[#This Row],[Monto Neto ]]*19% -> 3669.47 | O44: =+Rendiciones[[#This Row],[Monto Neto ]]+Rendiciones[[#This Row],[Monto Exento ]]+Rendiciones[[#This Row],[Iva]] -> 28511.47 | S44: =Rendiciones[[#This Row],[Total ]]-Rendiciones[[#This Row],[Monto ]] -> 28511.47
B45: Edgar hernandez | C45: 2 | D45: 46050 | E45: Del 26 al 30 | F45: =IF(Rendiciones[[#This Row],[Fecha ]]<>"",TEXT(Rendiciones[[#This Row],[Fecha ]],"MMMM"),"") -> enero | G45: HG | H45: Extras | I45: Comidas y Bebidas | M45: =4400+5200 -> 9600 | N45: =Rendiciones[[#This Row],[Monto Neto ]]*19% -> 0 | O45: =+Rendiciones[[#This Row],[Monto Neto ]]+Rendiciones[[#This Row],[Monto Exento ]]+Rendiciones[[#This Row],[Iva]] -> 9600 | P45: Scotianbank CLP | Q45: 46052 | R45: 38111.47 | S45: =Rendiciones[[#This Row],[Total ]]-Rendiciones[[#This Row],[Monto ]] -> -28511.47
B46: Brigitte Moran Mesa | C46: 1 | D46: 46038 | E46: Del 12 al 16 | F46: =IF(Rendiciones[[#This Row],[Fecha ]]<>"",TEXT(Rendiciones[[#This Row],[Fecha ]],"MMMM"),"") -> enero | G46: HGI. | H46: Operacionales | I46: Hospedaje | K46: Factura | M46: 315000 | N46: =Rendiciones[[#This Row],[Monto Neto ]]*19% -> 0 | O46: =+Rendiciones[[#This Row],[Monto Neto ]]+Rendiciones[[#This Row],[Monto Exento ]]+Rendiciones[[#This Row],[Iva]] -> 315000 | S46: =Rendiciones[[#This Row],[Total ]]-Rendiciones[[#This Row],[Monto ]] -> 315000
B47: Brigitte Moran Mesa | C47: 1 | D47: 46038 | E47: Del 12 al 16 | F47: =IF(Rendiciones[[#This Row],[Fecha ]]<>"",TEXT(Rendiciones[[#This Row],[Fecha ]],"MMMM"),"") -> enero | G47: HGI. | H47: Operacionales | I47: Café / Doctores Colación | K47: Factura | L47: 49664 | M47: 5910 | N47: =Rendiciones[[#This Row],[Monto Neto ]]*19% -> 9436.16 | O47: =+Rendiciones[[#This Row],[Monto Neto ]]+Rendiciones[[#This Row],[Monto Exento ]]+Rendiciones[[#This Row],[Iva]] -> 65010.16 | S47: =Rendiciones[[#This Row],[Total ]]-Rendiciones[[#This Row],[Monto ]] -> 65010.16
B48: Brigitte Moran Mesa | C48: 1 | D48: 46038 | E48: Del 12 al 16 | F48: =IF(Rendiciones[[#This Row],[Fecha ]]<>"",TEXT(Rendiciones[[#This Row],[Fecha ]],"MMMM"),"") -> enero | G48: HGI. | H48: Operacionales | I48: Café / Doctores Colación | K48: Factura | L48: 23487 | M48: 2795 | N48: =Rendiciones[[#This Row],[Monto Neto ]]*19% -> 4462.53 | O48: =+Rendiciones[[#This Row],[Monto Neto ]]+Rendiciones[[#This Row],[Monto Exento ]]+Rendiciones[[#This Row],[Iva]] -> 30744.53 | S48: =Rendiciones[[#This Row],[Total ]]-Rendiciones[[#This Row],[Monto ]] -> 30744.53
B49: Brigitte Moran Mesa | C49: 1 | D49: 46038 | E49: Del 12 al 16 | F49: =IF(Rendiciones[[#This Row],[Fecha ]]<>"",TEXT(Rendiciones[[#This Row],[Fecha ]],"MMMM"),"") -> enero | G49: HGI. | H49: Operacionales | I49: Taxi - Uber | M49: =25000+5000+2744+6193+2784+6228+5282+6000+4000+4000+5000+6000+6332+4479+6000+6000+6000+25000 -> 132042 | N49: =Rendiciones[[#This Row],[Monto Neto ]]*19% -> 0 | O49: =+Rendiciones[[#This Row],[Monto Neto ]]+Rendiciones[[#This Row],[Monto Exento ]]+Rendiciones[[#This Row],[Iva]] -> 132042 | S49: =Rendiciones[[#This Row],[Total ]]-Rendiciones[[#This Row],[Monto ]] -> 132042
B50: Brigitte Moran Mesa | C50: 1 | D50: 46038 | E50: Del 12 al 16 | F50: =IF(Rendiciones[[#This Row],[Fecha ]]<>"",TEXT(Rendiciones[[#This Row],[Fecha ]],"MMMM"),"") -> enero | G50: HGI. | H50: Operacionales | I50: Comidas y Bebidas | M50: =15600+27160+29700+8140 -> 80600 | N50: =Rendiciones[[#This Row],[Monto Neto ]]*19% -> 0 | O50: =+Rendiciones[[#This Row],[Monto Neto ]]+Rendiciones[[#This Row],[Monto Exento ]]+Rendiciones[[#This Row],[Iva]] -> 80600 | S50: =Rendiciones[[#This Row],[Total ]]-Rendiciones[[#This Row],[Monto ]] -> 80600
B51: Brigitte Moran Mesa | C51: 2 | D51: 46038 | E51: Del 12 al 16 | F51: =IF(Rendiciones[[#This Row],[Fecha ]]<>"",TEXT(Rendiciones[[#This Row],[Fecha ]],"MMMM"),"") -> enero | G51: HGI. | H51: Operacionales | I51: Comidas y Bebidas | K51: Factura | L51: 48067 | N51: =Rendiciones[[#This Row],[Monto Neto ]]*19% -> 9132.73 | O51: =+Rendiciones[[#This Row],[Monto Neto ]]+Rendiciones[[#This Row],[Monto Exento ]]+Rendiciones[[#This Row],[Iva]] -> 57199.73 | S51: =Rendiciones[[#This Row],[Total ]]-Rendiciones[[#This Row],[Monto ]] -> 57199.73
B52: Brigitte Moran Mesa | C52: 2 | D52: 46038 | E52: Del 12 al 16 | F52: =IF(Rendiciones[[#This Row],[Fecha ]]<>"",TEXT(Rendiciones[[#This Row],[Fecha ]],"MMMM"),"") -> enero | G52: HGI. | H52: Operacionales | I52: Bencina | K52: Factura | L52: 12490 | M52: 10137 | N52: =Rendiciones[[#This Row],[Monto Neto ]]*19% -> 2373.1 | O52: =+Rendiciones[[#This Row],[Monto Neto ]]+Rendiciones[[#This Row],[Monto Exento ]]+Rendiciones[[#This Row],[Iva]] -> 25000.1 | S52: =Rendiciones[[#This Row],[Total ]]-Rendiciones[[#This Row],[Monto ]] -> 25000.1
B53: Brigitte Moran Mesa | C53: 2 | D53: 46038 | E53: Del 12 al 16 | F53: =IF(Rendiciones[[#This Row],[Fecha ]]<>"",TEXT(Rendiciones[[#This Row],[Fecha ]],"MMMM"),"") -> enero | G53: HGI. | H53: Operacionales | I53: Bencina | K53: Factura | L53: 23750 | M53: 21103 | N53: =Rendiciones[[#This Row],[Monto Neto ]]*19% -> 4512.5 | O53: =+Rendiciones[[#This Row],[Monto Neto ]]+Rendiciones[[#This Row],[Monto Exento ]]+Rendiciones[[#This Row],[Iva]] -> 49365.5 | S53: =Rendiciones[[#This Row],[Total ]]-Rendiciones[[#This Row],[Monto ]] -> 49365.5
B54: Brigitte Moran Mesa | C54: 2 | D54: 46038 | E54: Del 12 al 16 | F54: =IF(Rendiciones[[#This Row],[Fecha ]]<>"",TEXT(Rendiciones[[#This Row],[Fecha ]],"MMMM"),"") -> enero | G54: HGI. | H54: Operacionales | I54: Estacionamiento | M54: =7560+6500 -> 14060 | N54: =Rendiciones[[#This Row],[Monto Neto ]]*19% -> 0 | O54: =+Rendiciones[[#This Row],[Monto Neto ]]+Rendiciones[[#This Row],[Monto Exento ]]+Rendiciones[[#This Row],[Iva]] -> 14060 | P54: Scotianbank CLP | Q54: 46052 | R54: 402023 | S54: =Rendiciones[[#This Row],[Total ]]-Rendiciones[[#This Row],[Monto ]] -> -387963
B55: Alejandra Olivares | C55: 4 | D55: 46058 | E55: Del 02 al 06 | F55: =IF(Rendiciones[[#This Row],[Fecha ]]<>"",TEXT(Rendiciones[[#This Row],[Fecha ]],"MMMM"),"") -> febrero | G55: HG | H55: Oficina | I55: Miscelaneos Administracion | M55: 54023 | N55: =Rendiciones[[#This Row],[Monto Neto ]]*19% -> 0 | O55: =+Rendiciones[[#This Row],[Monto Neto ]]+Rendiciones[[#This Row],[Monto Exento ]]+Rendiciones[[#This Row],[Iva]] -> 54023 | P55: Banco Internacional HGI | Q55: 46059 | R55: 54023 | S55: =Rendiciones[[#This Row],[Total ]]-Rendiciones[[#This Row],[Monto ]] -> 0
B56: Davis Torres | C56: 1 | D56: 46055 | E56: Del 02 al 06 | F56: =IF(Rendiciones[[#This Row],[Fecha ]]<>"",TEXT(Rendiciones[[#This Row],[Fecha ]],"MMMM"),"") -> febrero | G56: HGI. | H56: Oficina | I56: Otros Gastos de Oficina | M56: 30928 | N56: =Rendiciones[[#This Row],[Monto Neto ]]*19% -> 0 | O56: =+Rendiciones[[#This Row],[Monto Neto ]]+Rendiciones[[#This Row],[Monto Exento ]]+Rendiciones[[#This Row],[Iva]] -> 30928 | P56: Banco Internacional HGI | Q56: 46059 | R56: 30928 | S56: =Rendiciones[[#This Row],[Total ]]-Rendiciones[[#This Row],[Monto ]] -> 0
B57: Edgar hernandez | C57: 3 | D57: 46052 | E57: Del 26 al 30 | F57: =IF(Rendiciones[[#This Row],[Fecha ]]<>"",TEXT(Rendiciones[[#This Row],[Fecha ]],"MMMM"),"") -> enero | G57: HG | H57: Operacionales | I57: Gastos Auto | K57: Factura | L57: 17101 | N57: =Rendiciones[[#This Row],[Monto Neto ]]*19% -> 3249.19 | O57: =+Rendiciones[[#This Row],[Monto Neto ]]+Rendiciones[[#This Row],[Monto Exento ]]+Rendiciones[[#This Row],[Iva]] -> 20350.19 | S57: =Rendiciones[[#This Row],[Total ]]-Rendiciones[[#This Row],[Monto ]] -> 20350.19
B58: Edgar hernandez | C58: 3 | D58: 46052 | E58: Del 26 al 30 | F58: =IF(Rendiciones[[#This Row],[Fecha ]]<>"",TEXT(Rendiciones[[#This Row],[Fecha ]],"MMMM"),"") -> enero | G58: HG | H58: Operacionales | I58: Gastos Auto | M58: 18000 | N58: =Rendiciones[[#This Row],[Monto Neto ]]*19% -> 0 | O58: =+Rendiciones[[#This Row],[Monto Neto ]]+Rendiciones[[#This Row],[Monto Exento ]]+Rendiciones[[#This Row],[Iva]] -> 18000 | P58: Banco Internacional HGI | Q58: 46059 | R58: 38350.19 | S58: =Rendiciones[[#This Row],[Total ]]-Rendiciones[[#This Row],[Monto ]] -> -20350.19
B59: Tomas Castro | D59: 46048 | E59: Del 26 al 30 | F59: =IF(Rendiciones[[#This Row],[Fecha ]]<>"",TEXT(Rendiciones[[#This Row],[Fecha ]],"MMMM"),"") -> enero | G59: HG | N59: =Rendiciones[[#This Row],[Monto Neto ]]*19% -> 0 | O59: =+Rendiciones[[#This Row],[Monto Neto ]]+Rendiciones[[#This Row],[Monto Exento ]]+Rendiciones[[#This Row],[Iva]] -> 0 | P59: Scotianbank CLP | Q59: 46048 | R59: 743599 | S59: =Rendiciones[[#This Row],[Total ]]-Rendiciones[[#This Row],[Monto ]] -> -743599
B60: Tomas Castro | C60: 2 | D60: 46052 | E60: Del 26 al 30 | F60: =IF(Rendiciones[[#This Row],[Fecha ]]<>"",TEXT(Rendiciones[[#This Row],[Fecha ]],"MMMM"),"") -> enero | G60: HGI. | H60: Operacionales | I60: Honorarios | K60: Boleta de honorarios | M60: 7000 | N60: =Rendiciones[[#This Row],[Monto Neto ]]*19% -> 0 | O60: =+Rendiciones[[#This Row],[Monto Neto ]]+Rendiciones[[#This Row],[Monto Exento ]]+Rendiciones[[#This Row],[Iva]] -> 7000 | P60: Banco Internacional HGI | Q60: 46059 | R60: 7000 | S60: =Rendiciones[[#This Row],[Total ]]-Rendiciones[[#This Row],[Monto ]] -> 0
B61: Javier Salazar | C61: 3 | D61: 46050 | E61: Del 26 al 30 | F61: =IF(Rendiciones[[#This Row],[Fecha ]]<>"",TEXT(Rendiciones[[#This Row],[Fecha ]],"MMMM"),"") -> enero | G61: HG | H61: Operacionales | I61: Bencina | K61: Factura | L61: 28488 | M61: =4554+2855+300 -> 7709 | N61: =Rendiciones[[#This Row],[Monto Neto ]]*19% -> 5412.72 | O61: =+Rendiciones[[#This Row],[Monto Neto ]]+Rendiciones[[#This Row],[Monto Exento ]]+Rendiciones[[#This Row],[Iva]] -> 41609.72 | S61: =Rendiciones[[#This Row],[Total ]]-Rendiciones[[#This Row],[Monto ]] -> 41609.72
B62: Javier Salazar | C62: 3 | D62: 46050 | E62: Del 26 al 30 | F62: =IF(Rendiciones[[#This Row],[Fecha ]]<>"",TEXT(Rendiciones[[#This Row],[Fecha ]],"MMMM"),"") -> enero | G62: HG | H62: Operacionales | I62: Reparaciones y remodelaciones | K62: Factura | L62: 10151 | N62: =Rendiciones[[#This Row],[Monto Neto ]]*19% -> 1928.69 | O62: =+Rendiciones[[#This Row],[Monto Neto ]]+Rendiciones[[#This Row],[Monto Exento ]]+Rendiciones[[#This Row],[Iva]] -> 12079.69 | S62: =Rendiciones[[#This Row],[Total ]]-Rendiciones[[#This Row],[Monto ]] -> 12079.69
B63: Javier Salazar | C63: 3 | D63: 46050 | E63: Del 26 al 30 | F63: =IF(Rendiciones[[#This Row],[Fecha ]]<>"",TEXT(Rendiciones[[#This Row],[Fecha ]],"MMMM"),"") -> enero | G63: HG | H63: Operacionales | I63: Gastos Furgón | K63: Factura | L63: 15126 | N63: =Rendiciones[[#This Row],[Monto Neto ]]*19% -> 2873.94 | O63: =+Rendiciones[[#This Row],[Monto Neto ]]+Rendiciones[[#This Row],[Monto Exento ]]+Rendiciones[[#This Row],[Iva]] -> 17999.94 | S63: =Rendiciones[[#This Row],[Total ]]-Rendiciones[[#This Row],[Monto ]] -> 17999.94
B64: Javier Salazar | C64: 3 | D64: 46050 | E64: Del 26 al 30 | F64: =IF(Rendiciones[[#This Row],[Fecha ]]<>"",TEXT(Rendiciones[[#This Row],[Fecha ]],"MMMM"),"") -> enero | G64: HG | H64: Operacionales | I64: Bencina | K64: Factura | L64: 28460 | M64: =4550+2852+500 -> 7902 | N64: =Rendiciones[[#This Row],[Monto Neto ]]*19% -> 5407.4 | O64: =+Rendiciones[[#This Row],[Monto Neto ]]+Rendiciones[[#This Row],[Monto Exento ]]+Rendiciones[[#This Row],[Iva]] -> 41769.4 | S64: =Rendiciones[[#This Row],[Total ]]-Rendiciones[[#This Row],[Monto ]] -> 41769.4
B65: Javier Salazar | C65: 3 | D65: 46050 | E65: Del 26 al 30 | F65: =IF(Rendiciones[[#This Row],[Fecha ]]<>"",TEXT(Rendiciones[[#This Row],[Fecha ]],"MMMM"),"") -> enero | G65: HG | H65: Operacionales | I65: Reparaciones y remodelaciones | K65: Factura | L65: 32200 | N65: =Rendiciones[[#This Row],[Monto Neto ]]*19% -> 6118 | O65: =+Rendiciones[[#This Row],[Monto Neto ]]+Rendiciones[[#This Row],[Monto Exento ]]+Rendiciones[[#This Row],[Iva]] -> 38318 | S65: =Rendiciones[[#This Row],[Total ]]-Rendiciones[[#This Row],[Monto ]] -> 38318
B66: Javier Salazar | C66: 3 | D66: 46050 | E66: Del 26 al 30 | F66: =IF(Rendiciones[[#This Row],[Fecha ]]<>"",TEXT(Rendiciones[[#This Row],[Fecha ]],"MMMM"),"") -> enero | G66: HG | H66: Operacionales | I66: Reparaciones y remodelaciones | K66: Factura | L66: 30869 | N66: =Rendiciones[[#This Row],[Monto Neto ]]*19% -> 5865.11 | O66: =+Rendiciones[[#This Row],[Monto Neto ]]+Rendiciones[[#This Row],[Monto Exento ]]+Rendiciones[[#This Row],[Iva]] -> 36734.11 | S66: =Rendiciones[[#This Row],[Total ]]-Rendiciones[[#This Row],[Monto ]] -> 36734.11
B67: Javier Salazar | C67: 3 | D67: 46050 | E67: Del 26 al 30 | F67: =IF(Rendiciones[[#This Row],[Fecha ]]<>"",TEXT(Rendiciones[[#This Row],[Fecha ]],"MMMM"),"") -> enero | G67: HG | H67: Operacionales | I67: Reparaciones y remodelaciones | K67: Factura | L67: 30252 | N67: =Rendiciones[[#This Row],[Monto Neto ]]*19% -> 5747.88 | O67: =+Rendiciones[[#This Row],[Monto Neto ]]+Rendiciones[[#This Row],[Monto Exento ]]+Rendiciones[[#This Row],[Iva]] -> 35999.88 | S67: =Rendiciones[[#This Row],[Total ]]-Rendiciones[[#This Row],[Monto ]] -> 35999.88
B68: Javier Salazar | C68: 3 | D68: 46050 | E68: Del 26 al 30 | F68: =IF(Rendiciones[[#This Row],[Fecha ]]<>"",TEXT(Rendiciones[[#This Row],[Fecha ]],"MMMM"),"") -> enero | G68: HG | H68: Operacionales | I68: Reparaciones y remodelaciones | K68: Factura | L68: 5874 | N68: =Rendiciones[[#This Row],[Monto Neto ]]*19% -> 1116.06 | O68: =+Rendiciones[[#This Row],[Monto Neto ]]+Rendiciones[[#This Row],[Monto Exento ]]+Rendiciones[[#This Row],[Iva]] -> 6990.06 | S68: =Rendiciones[[#This Row],[Total ]]-Rendiciones[[#This Row],[Monto ]] -> 6990.06
B69: Javier Salazar | C69: 3 | D69: 46050 | E69: Del 26 al 30 | F69: =IF(Rendiciones[[#This Row],[Fecha ]]<>"",TEXT(Rendiciones[[#This Row],[Fecha ]],"MMMM"),"") -> enero | G69: HG | H69: Operacionales | I69: Peajes / Estacionamientos | M69: =1200+700+300+400 -> 2600 | N69: =Rendiciones[[#This Row],[Monto Neto ]]*19% -> 0 | O69: =+Rendiciones[[#This Row],[Monto Neto ]]+Rendiciones[[#This Row],[Monto Exento ]]+Rendiciones[[#This Row],[Iva]] -> 2600 | S69: =Rendiciones[[#This Row],[Total ]]-Rendiciones[[#This Row],[Monto ]] -> 2600
B70: Javier Salazar | C70: 3 | D70: 46050 | E70: Del 26 al 30 | F70: =IF(Rendiciones[[#This Row],[Fecha ]]<>"",TEXT(Rendiciones[[#This Row],[Fecha ]],"MMMM"),"") -> enero | G70: HG | H70: Operacionales | I70: Taxi - Uber | M70: 2865 | N70: =Rendiciones[[#This Row],[Monto Neto ]]*19% -> 0 | O70: =+Rendiciones[[#This Row],[Monto Neto ]]+Rendiciones[[#This Row],[Monto Exento ]]+Rendiciones[[#This Row],[Iva]] -> 2865 | S70: =Rendiciones[[#This Row],[Total ]]-Rendiciones[[#This Row],[Monto ]] -> 2865
B71: Javier Salazar | C71: 3 | D71: 46050 | E71: Del 26 al 30 | F71: =IF(Rendiciones[[#This Row],[Fecha ]]<>"",TEXT(Rendiciones[[#This Row],[Fecha ]],"MMMM"),"") -> enero | G71: HG | H71: Operacionales | I71: Comidas y Bebidas | M71: =7400+7990 -> 15390 | N71: =Rendiciones[[#This Row],[Monto Neto ]]*19% -> 0 | O71: =+Rendiciones[[#This Row],[Monto Neto ]]+Rendiciones[[#This Row],[Monto Exento ]]+Rendiciones[[#This Row],[Iva]] -> 15390 | S71: =Rendiciones[[#This Row],[Total ]]-Rendiciones[[#This Row],[Monto ]] -> 15390
B72: Javier Salazar | C72: 3 | D72: 46050 | E72: Del 26 al 30 | F72: =IF(Rendiciones[[#This Row],[Fecha ]]<>"",TEXT(Rendiciones[[#This Row],[Fecha ]],"MMMM"),"") -> enero | G72: HG | H72: Operacionales | I72: Reparaciones y remodelaciones | M72: =30000+5290 -> 35290 | N72: =Rendiciones[[#This Row],[Monto Neto ]]*19% -> 0 | O72: =+Rendiciones[[#This Row],[Monto Neto ]]+Rendiciones[[#This Row],[Monto Exento ]]+Rendiciones[[#This Row],[Iva]] -> 35290 | P72: Banco Internacional HGI | Q72: 46057 | R72: 287645.8 | S72: =Rendiciones[[#This Row],[Total ]]-Rendiciones[[#This Row],[Monto ]] -> -252355.8
B73: Javier Salazar | C73: 4 | D73: 46062 | E73: Del 09 al 13 | F73: =IF(Rendiciones[[#This Row],[Fecha ]]<>"",TEXT(Rendiciones[[#This Row],[Fecha ]],"MMMM"),"") -> febrero | G73: HG | H73: Operacionales | I73: Bencina | K73: Factura | L73: 30926 | M73: =4898+1926 -> 6824 | N73: =Rendiciones[[#This Row],[Monto Neto ]]*19% -> 5875.94 | O73: =+Rendiciones[[#This Row],[Monto Neto ]]+Rendiciones[[#This Row],[Monto Exento ]]+Rendiciones[[#This Row],[Iva]] -> 43625.94 | S73: =Rendiciones[[#This Row],[Total ]]-Rendiciones[[#This Row],[Monto ]] -> 43625.94
B74: Javier Salazar | C74: 4 | D74: 46062 | E74: Del 09 al 13 | F74: =IF(Rendiciones[[#This Row],[Fecha ]]<>"",TEXT(Rendiciones[[#This Row],[Fecha ]],"MMMM"),"") -> febrero | G74: HG | H74: Operacionales | I74: Gastos Furgón | K74: Factura | L74: 8403 | N74: =Rendiciones[[#This Row],[Monto Neto ]]*19% -> 1596.57 | O74: =+Rendiciones[[#This Row],[Monto Neto ]]+Rendiciones[[#This Row],[Monto Exento ]]+Rendiciones[[#This Row],[Iva]] -> 9999.57 | S74: =Rendiciones[[#This Row],[Total ]]-Rendiciones[[#This Row],[Monto ]] -> 9999.57
B75: Javier Salazar | C75: 4 | D75: 46062 | E75: Del 09 al 13 | F75: =IF(Rendiciones[[#This Row],[Fecha ]]<>"",TEXT(Rendiciones[[#This Row],[Fecha ]],"MMMM"),"") -> febrero | G75: HG | H75: Operacionales | I75: Peajes / Estacionamientos | M75: =630+1461 -> 2091 | N75: =Rendiciones[[#This Row],[Monto Neto ]]*19% -> 0 | O75: =+Rendiciones[[#This Row],[Monto Neto ]]+Rendiciones[[#This Row],[Monto Exento ]]+Rendiciones[[#This Row],[Iva]] -> 2091 | P75: Banco Internacional HGI | Q75: 46066 | R75: 55716.506 | S75: =Rendiciones[[#This Row],[Total ]]-Rendiciones[[#This Row],[Monto ]] -> -53625.506
B76: Raul Diaz | C76: 2 | D76: 46062 | E76: Del 09 al 13 | F76: =IF(Rendiciones[[#This Row],[Fecha ]]<>"",TEXT(Rendiciones[[#This Row],[Fecha ]],"MMMM"),"") -> febrero | G76: HGI. | H76: Operacionales | I76: Bencina | K76: Factura | L76: 25365 | M76: =3851+965 -> 4816 | N76: =Rendiciones[[#This Row],[Monto Neto ]]*19% -> 4819.35 | O76: =+Rendiciones[[#This Row],[Monto Neto ]]+Rendiciones[[#This Row],[Monto Exento ]]+Rendiciones[[#This Row],[Iva]] -> 35000.35 | S76: =Rendiciones[[#This Row],[Total ]]-Rendiciones[[#This Row],[Monto ]] -> 35000.35
B77: Raul Diaz | C77: 2 | D77: 46062 | E77: Del 09 al 13 | F77: =IF(Rendiciones[[#This Row],[Fecha ]]<>"",TEXT(Rendiciones[[#This Row],[Fecha ]],"MMMM"),"") -> febrero | G77: HGI. | H77: Operacionales | I77: Estacionamiento | M77: 760 | N77: =Rendiciones[[#This Row],[Monto Neto ]]*19% -> 0 | O77: =+Rendiciones[[#This Row],[Monto Neto ]]+Rendiciones[[#This Row],[Monto Exento ]]+Rendiciones[[#This Row],[Iva]] -> 760 | S77: =Rendiciones[[#This Row],[Total ]]-Rendiciones[[#This Row],[Monto ]] -> 760
B78: Raul Diaz | C78: 2 | D78: 46062 | E78: Del 09 al 13 | F78: =IF(Rendiciones[[#This Row],[Fecha ]]<>"",TEXT(Rendiciones[[#This Row],[Fecha ]],"MMMM"),"") -> febrero | G78: HGI. | H78: Operacionales | I78: Comidas y Bebidas | M78: 4500 | N78: =Rendiciones[[#This Row],[Monto Neto ]]*19% -> 0 | O78: =+Rendiciones[[#This Row],[Monto Neto ]]+Rendiciones[[#This Row],[Monto Exento ]]+Rendiciones[[#This Row],[Iva]] -> 4500 | S78: =Rendiciones[[#This Row],[Total ]]-Rendiciones[[#This Row],[Monto ]] -> 4500
B79: David Herce | C79: 5 | D79: 46063 | E79: Del 09 al 13 | F79: =IF(Rendiciones[[#This Row],[Fecha ]]<>"",TEXT(Rendiciones[[#This Row],[Fecha ]],"MMMM"),"") -> febrero | G79: HGI. | H79: Operacionales | I79: Gastos Furgón | K79: Factura | L79: 142017 | N79: =Rendiciones[[#This Row],[Monto Neto ]]*19% -> 26983.23 | O79: =+Rendiciones[[#This Row],[Monto Neto ]]+Rendiciones[[#This Row],[Monto Exento ]]+Rendiciones[[#This Row],[Iva]] -> 169000.23 | P79: Banco Internacional HGI | Q79: 46066 | R79: 169000 | S79: =Rendiciones[[#This Row],[Total ]]-Rendiciones[[#This Row],[Monto ]] -> 0.23
B80: David Herce | C80: 6 | D80: 46065 | E80: Del 09 al 13 | F80: =IF(Rendiciones[[#This Row],[Fecha ]]<>"",TEXT(Rendiciones[[#This Row],[Fecha ]],"MMMM"),"") -> febrero | G80: HG | H80: Oficina | I80: Reparaciones y remodelaciones | K80: Factura | L80: 29948.9 | N80: =Rendiciones[[#This Row],[Monto Neto ]]*19% -> 5690.291 | O80: =+Rendiciones[[#This Row],[Monto Neto ]]+Rendiciones[[#This Row],[Monto Exento ]]+Rendiciones[[#This Row],[Iva]] -> 35639.191 | P80: Banco Internacional HGI | Q80: 46073 | R80: 35639.421 | S80: =Rendiciones[[#This Row],[Total ]]-Rendiciones[[#This Row],[Monto ]] -> -0.23
B81: Raul Diaz | C81: 3 | D81: 46070 | E81: Del 16 al 20 | F81: =IF(Rendiciones[[#This Row],[Fecha ]]<>"",TEXT(Rendiciones[[#This Row],[Fecha ]],"MMMM"),"") -> febrero | G81: HGI. | H81: Operacionales | I81: Bencina | K81: Factura | L81: 36470 | M81: 5365 | N81: =Rendiciones[[#This Row],[Monto Neto ]]*19% -> 6929.3 | O81: =+Rendiciones[[#This Row],[Monto Neto ]]+Rendiciones[[#This Row],[Monto Exento ]]+Rendiciones[[#This Row],[Iva]] -> 48764.3 | S81: =Rendiciones[[#This Row],[Total ]]-Rendiciones[[#This Row],[Monto ]] -> 48764.3
B82: Raul Diaz | C82: 3 | D82: 46070 | E82: Del 16 al 20 | F82: =IF(Rendiciones[[#This Row],[Fecha ]]<>"",TEXT(Rendiciones[[#This Row],[Fecha ]],"MMMM"),"") -> febrero | G82: HGI. | H82: Operacionales | I82: Gastos Furgón | K82: Factura | L82: 6008 | N82: =Rendiciones[[#This Row],[Monto Neto ]]*19% -> 1141.52 | O82: =+Rendiciones[[#This Row],[Monto Neto ]]+Rendiciones[[#This Row],[Monto Exento ]]+Rendiciones[[#This Row],[Iva]] -> 7149.52 | S82: =Rendiciones[[#This Row],[Total ]]-Rendiciones[[#This Row],[Monto ]] -> 7149.52
B83: Raul Diaz | C83: 3 | D83: 46070 | E83: Del 16 al 20 | F83: =IF(Rendiciones[[#This Row],[Fecha ]]<>"",TEXT(Rendiciones[[#This Row],[Fecha ]],"MMMM"),"") -> febrero | G83: HGI. | H83: Operacionales | I83: Estacionamiento | M83: 2030 | N83: =Rendiciones[[#This Row],[Monto Neto ]]*19% -> 0 | O83: =+Rendiciones[[#This Row],[Monto Neto ]]+Rendiciones[[#This Row],[Monto Exento ]]+Rendiciones[[#This Row],[Iva]] -> 2030 | S83: =Rendiciones[[#This Row],[Total ]]-Rendiciones[[#This Row],[Monto ]] -> 2030
B84: Raul Diaz | C84: 3 | D84: 46070 | E84: Del 16 al 20 | F84: =IF(Rendiciones[[#This Row],[Fecha ]]<>"",TEXT(Rendiciones[[#This Row],[Fecha ]],"MMMM"),"") -> febrero | G84: HGI. | H84: Operacionales | I84: Comidas y Bebidas | M84: =7000+5850 -> 12850 | N84: =Rendiciones[[#This Row],[Monto Neto ]]*19% -> 0 | O84: =+Rendiciones[[#This Row],[Monto Neto ]]+Rendiciones[[#This Row],[Monto Exento ]]+Rendiciones[[#This Row],[Iva]] -> 12850 | P84: Banco Internacional HGI | Q84: 46066 | R84: 119736 | S84: =Rendiciones[[#This Row],[Total ]]-Rendiciones[[#This Row],[Monto ]] -> -106886
B85: Dailin Arellano | C85: 0 | D85: 46023 | E85: Del 01 al 02 | F85: =IF(Rendiciones[[#This Row],[Fecha ]]<>"",TEXT(Rendiciones[[#This Row],[Fecha ]],"MMMM"),"") -> enero | G85: HGI. | N85: =Rendiciones[[#This Row],[Monto Neto ]]*19% -> 0 | O85: =+Rendiciones[[#This Row],[Monto Neto ]]+Rendiciones[[#This Row],[Monto Exento ]]+Rendiciones[[#This Row],[Iva]] -> 0 | P85: Banco Internacional HGI | Q85: 46022 | R85: 85348 | S85: =Rendiciones[[#This Row],[Total ]]-Rendiciones[[#This Row],[Monto ]] -> -85348
B86: Dailin Arellano | C86: 1 | D86: 46065 | E86: Del 12 al 16 | F86: =IF(Rendiciones[[#This Row],[Fecha ]]<>"",TEXT(Rendiciones[[#This Row],[Fecha ]],"MMMM"),"") -> febrero | G86: HGI. | H86: Viajes | I86: Pasajes Bus - Aéreos | K86: Factura | M86: 121386 | N86: =Rendiciones[[#This Row],[Monto Neto ]]*19% -> 0 | O86: =+Rendiciones[[#This Row],[Monto Neto ]]+Rendiciones[[#This Row],[Monto Exento ]]+Rendiciones[[#This Row],[Iva]] -> 121386 | S86: =Rendiciones[[#This Row],[Total ]]-Rendiciones[[#This Row],[Monto ]] -> 121386
B87: Dailin Arellano | C87: 1 | D87: 46065 | E87: Del 12 al 16 | F87: =IF(Rendiciones[[#This Row],[Fecha ]]<>"",TEXT(Rendiciones[[#This Row],[Fecha ]],"MMMM"),"") -> febrero | G87: HGI. | H87: Viajes | I87: Pasajes Bus - Aéreos | M87: =3000+3000+42400+110732+14000+15800+3000+3000+145804+4000+3000 -> 347736 | N87: =Rendiciones[[#This Row],[Monto Neto ]]*19% -> 0 | O87: =+Rendiciones[[#This Row],[Monto Neto ]]+Rendiciones[[#This Row],[Monto Exento ]]+Rendiciones[[#This Row],[Iva]] -> 347736 | S87: =Rendiciones[[#This Row],[Total ]]-Rendiciones[[#This Row],[Monto ]] -> 347736
B88: Dailin Arellano | C88: 1 | D88: 46065 | E88: Del 12 al 16 | F88: =IF(Rendiciones[[#This Row],[Fecha ]]<>"",TEXT(Rendiciones[[#This Row],[Fecha ]],"MMMM"),"") -> febrero | G88: HGI. | H88: Viajes | I88: Taxi - Uber | M88: =2996+3194+7010+6144+8990+9293+7937+2058+3711+4048+7597+2595+3598+5098+4099+13307+12992+2663+3076+5326+2359+3698+3098+3400+7050+3300+3395 -> 142032 | N88: =Rendiciones[[#This Row],[Monto Neto ]]*19% -> 0 | O88: =+Rendiciones[[#This Row],[Monto Neto ]]+Rendiciones[[#This Row],[Monto Exento ]]+Rendiciones[[#This Row],[Iva]] -> 142032 | S88: =Rendiciones[[#This Row],[Total ]]-Rendiciones[[#This Row],[Monto ]] -> 142032
B89: Dailin Arellano | C89: 1 | D89: 46065 | E89: Del 12 al 16 | F89: =IF(Rendiciones[[#This Row],[Fecha ]]<>"",TEXT(Rendiciones[[#This Row],[Fecha ]],"MMMM"),"") -> febrero | G89: HGI. | H89: Viajes | I89: Comidas y Bebidas | M89: =4400+13500+5000+12600+17490+6500+2200+10840+19470+30140+5390+21670+9990 -> 159190 | N89: =Rendiciones[[#This Row],[Monto Neto ]]*19% -> 0 | O89: =+Rendiciones[[#This Row],[Monto Neto ]]+Rendiciones[[#This Row],[Monto Exento ]]+Rendiciones[[#This Row],[Iva]] -> 159190 | S89: =Rendiciones[[#This Row],[Total ]]-Rendiciones[[#This Row],[Monto ]] -> 159190
B90: Dailin Arellano | C90: 1 | D90: 46065 | E90: Del 12 al 16 | F90: =IF(Rendiciones[[#This Row],[Fecha ]]<>"",TEXT(Rendiciones[[#This Row],[Fecha ]],"MMMM"),"") -> febrero | G90: HGI. | H90: Viajes | I90: Hospedaje | M90: 53500 | N90: =Rendiciones[[#This Row],[Monto Neto ]]*19% -> 0 | O90: =+Rendiciones[[#This Row],[Monto Neto ]]+Rendiciones[[#This Row],[Monto Exento ]]+Rendiciones[[#This Row],[Iva]] -> 53500 | S90: =Rendiciones[[#This Row],[Total ]]-Rendiciones[[#This Row],[Monto ]] -> 53500
B91: Dailin Arellano | C91: 1 | D91: 46065 | E91: Del 12 al 16 | F91: =IF(Rendiciones[[#This Row],[Fecha ]]<>"",TEXT(Rendiciones[[#This Row],[Fecha ]],"MMMM"),"") -> febrero | G91: HGI. | H91: Viajes | I91: Pasajes Bus - Aéreos | M91: 29000 | N91: =Rendiciones[[#This Row],[Monto Neto ]]*19% -> 0 | O91: =+Rendiciones[[#This Row],[Monto Neto ]]+Rendiciones[[#This Row],[Monto Exento ]]+Rendiciones[[#This Row],[Iva]] -> 29000 | S91: =Rendiciones[[#This Row],[Total ]]-Rendiciones[[#This Row],[Monto ]] -> 29000
B92: Dailin Arellano | C92: 1 | D92: 46065 | E92: Del 12 al 16 | F92: =IF(Rendiciones[[#This Row],[Fecha ]]<>"",TEXT(Rendiciones[[#This Row],[Fecha ]],"MMMM"),"") -> febrero | G92: HGI. | H92: Viajes | I92: Café / Doctores Colación | M92: 8162 | N92: =Rendiciones[[#This Row],[Monto Neto ]]*19% -> 0 | O92: =+Rendiciones[[#This Row],[Monto Neto ]]+Rendiciones[[#This Row],[Monto Exento ]]+Rendiciones[[#This Row],[Iva]] -> 8162 | P92: Banco Internacional HGI | Q92: 46073 | R92: 775658 | S92: =Rendiciones[[#This Row],[Total ]]-Rendiciones[[#This Row],[Monto ]] -> -767496
B93: Raul Diaz | D93: 46073 | E93: Del 16 al 20 | F93: =IF(Rendiciones[[#This Row],[Fecha ]]<>"",TEXT(Rendiciones[[#This Row],[Fecha ]],"MMMM"),"") -> febrero | N93: =Rendiciones[[#This Row],[Monto Neto ]]*19% -> 0 | O93: =+Rendiciones[[#This Row],[Monto Neto ]]+Rendiciones[[#This Row],[Monto Exento ]]+Rendiciones[[#This Row],[Iva]] -> 0 | P93: Banco Internacional HGI | Q93: 45708 | R93: 70794 | S93: =Rendiciones[[#This Row],[Total ]]-Rendiciones[[#This Row],[Monto ]] -> -70794
B94: Raul Diaz | C94: 4 | D94: 46076 | E94: Del 23 al 27 | F94: =IF(Rendiciones[[#This Row],[Fecha ]]<>"",TEXT(Rendiciones[[#This Row],[Fecha ]],"MMMM"),"") -> febrero | G94: HGI. | H94: Operacionales | I94: Artículos de Oficina | K94: Factura | L94: 73916 | N94: =Rendiciones[[#This Row],[Monto Neto ]]*19% -> 14044.04 | O94: =+Rendiciones[[#This Row],[Monto Neto ]]+Rendiciones[[#This Row],[Monto Exento ]]+Rendiciones[[#This Row],[Iva]] -> 87960.04 | S94: =Rendiciones[[#This Row],[Total ]]-Rendiciones[[#This Row],[Monto ]] -> 87960.04
B95: Raul Diaz | C95: 4 | D95: 46076 | E95: Del 23 al 27 | F95: =IF(Rendiciones[[#This Row],[Fecha ]]<>"",TEXT(Rendiciones[[#This Row],[Fecha ]],"MMMM"),"") -> febrero | G95: HGI. | H95: Operacionales | I95: Peajes / Estacionamientos | M95: 1780 | N95: =Rendiciones[[#This Row],[Monto Neto ]]*19% -> 0 | O95: =+Rendiciones[[#This Row],[Monto Neto ]]+Rendiciones[[#This Row],[Monto Exento ]]+Rendiciones[[#This Row],[Iva]] -> 1780 | P95: Banco Internacional HGI | Q95: 46078 | R95: 89740 | S95: =Rendiciones[[#This Row],[Total ]]-Rendiciones[[#This Row],[Monto ]] -> -87960
B96: Dailin Arellano | C96: 2 | D96: 46072 | E96: Del 16 al 20 | F96: =IF(Rendiciones[[#This Row],[Fecha ]]<>"",TEXT(Rendiciones[[#This Row],[Fecha ]],"MMMM"),"") -> febrero | G96: HGI. | H96: Operacionales | I96: Taxi - Uber | M96: =13328+3798+4082 -> 21208 | N96: =Rendiciones[[#This Row],[Monto Neto ]]*19% -> 0 | O96: =+Rendiciones[[#This Row],[Monto Neto ]]+Rendiciones[[#This Row],[Monto Exento ]]+Rendiciones[[#This Row],[Iva]] -> 21208 | S96: =Rendiciones[[#This Row],[Total ]]-Rendiciones[[#This Row],[Monto ]] -> 21208
B97: Dailin Arellano | C97: 2 | D97: 46072 | E97: Del 16 al 20 | F97: =IF(Rendiciones[[#This Row],[Fecha ]]<>"",TEXT(Rendiciones[[#This Row],[Fecha ]],"MMMM"),"") -> febrero | G97: HGI. | H97: Extras | I97: Honorarios | M97: 200000 | N97: =Rendiciones[[#This Row],[Monto Neto ]]*19% -> 0 | O97: =+Rendiciones[[#This Row],[Monto Neto ]]+Rendiciones[[#This Row],[Monto Exento ]]+Rendiciones[[#This Row],[Iva]] -> 200000 | P97: Banco Internacional HGI | Q97: 46092 | R97: 221208 | S97: =Rendiciones[[#This Row],[Total ]]-Rendiciones[[#This Row],[Monto ]] -> -21208
B98: Raul Diaz | C98: 5 | D98: 46080 | E98: Del 23 al 27 | F98: =IF(Rendiciones[[#This Row],[Fecha ]]<>"",TEXT(Rendiciones[[#This Row],[Fecha ]],"MMMM"),"") -> febrero | G98: HGI. | H98: Operacionales | I98: Bencina | K98: Factura | L98: 17103 | M98: =2563+84.5 -> 2647.5 | N98: =Rendiciones[[#This Row],[Monto Neto ]]*19% -> 3249.57 | O98: =+Rendiciones[[#This Row],[Monto Neto ]]+Rendiciones[[#This Row],[Monto Exento ]]+Rendiciones[[#This Row],[Iva]] -> 23000.07 | S98: =Rendiciones[[#This Row],[Total ]]-Rendiciones[[#This Row],[Monto ]] -> 23000.07
B99: Raul Diaz | C99: 5 | D99: 46080 | E99: Del 23 al 27 | F99: =IF(Rendiciones[[#This Row],[Fecha ]]<>"",TEXT(Rendiciones[[#This Row],[Fecha ]],"MMMM"),"") -> febrero | G99: HGI. | H99: Operacionales | I99: Artículos de Oficina | K99: Factura | L99: 60546 | N99: =Rendiciones[[#This Row],[Monto Neto ]]*19% -> 11503.74 | O99: =+Rendiciones[[#This Row],[Monto Neto ]]+Rendiciones[[#This Row],[Monto Exento ]]+Rendiciones[[#This Row],[Iva]] -> 72049.74 | P99: Banco Internacional HGI | Q99: 46083 | R99: 95050 | S99: =Rendiciones[[#This Row],[Total ]]-Rendiciones[[#This Row],[Monto ]] -> -23000.26
B100: Javier Salazar | C100: 5 | D100: 46076 | E100: Del 23 al 27 | F100: =IF(Rendiciones[[#This Row],[Fecha ]]<>"",TEXT(Rendiciones[[#This Row],[Fecha ]],"MMMM"),"") -> febrero | G100: HGI. | H100: Operacionales | I100: Bencina | K100: Factura | L100: 18225 | M100: =2833+710+500.02 -> 4043.02 | N100: =Rendiciones[[#This Row],[Monto Neto ]]*19% -> 3462.75 | O100: =+Rendiciones[[#This Row],[Monto Neto ]]+Rendiciones[[#This Row],[Monto Exento ]]+Rendiciones[[#This Row],[Iva]] -> 25730.77 | S100: =Rendiciones[[#This Row],[Total ]]-Rendiciones[[#This Row],[Monto ]] -> 25730.77
B101: Javier Salazar | C101: 5 | D101: 46076 | E101: Del 23 al 27 | F101: =IF(Rendiciones[[#This Row],[Fecha ]]<>"",TEXT(Rendiciones[[#This Row],[Fecha ]],"MMMM"),"") -> febrero | G101: HGI. | H101: Oficina | I101: Artículos de Oficina | K101: Factura | L101: 6688 | N101: =Rendiciones[[#This Row],[Monto Neto ]]*19% -> 1270.72 | O101: =+Rendiciones[[#This Row],[Monto Neto ]]+Rendiciones[[#This Row],[Monto Exento ]]+Rendiciones[[#This Row],[Iva]] -> 7958.72 | S101: =Rendiciones[[#This Row],[Total ]]-Rendiciones[[#This Row],[Monto ]] -> 7958.72
B102: Javier Salazar | C102: 5 | D102: 46076 | E102: Del 23 al 27 | F102: =IF(Rendiciones[[#This Row],[Fecha ]]<>"",TEXT(Rendiciones[[#This Row],[Fecha ]],"MMMM"),"") -> febrero | G102: HGI. | H102: Operacionales | I102: Bencina | K102: Factura | L102: 24687 | M102: =3693+500 -> 4193 | N102: =Rendiciones[[#This Row],[Monto Neto ]]*19% -> 4690.53 | O102: =+Rendiciones[[#This Row],[Monto Neto ]]+Rendiciones[[#This Row],[Monto Exento ]]+Rendiciones[[#This Row],[Iva]] -> 33570.53 | S102: =Rendiciones[[#This Row],[Total ]]-Rendiciones[[#This Row],[Monto ]] -> 33570.53
...

Sheet Listas
K2: Q1 23 | L2: Q2 23 | M2: Q3 23 | N2: Q4 23
B3: Nombre del Solicitante | D3: C.C. | E3: Cuentas | F3: Subcuentas | G3: Rut Empresa | H3: Empresa | I3: Pagado Por
B4: David Herce | D4: HG | E4: Oficina | F4: Notario y Legal | G4: 76723245-4 | H4: Heca Global SPA | I4: Banco Estado HGI
B5: Manuel Guajardo | D5: HC | E5: Operacionales | F5: Miscelaneos Administracion | G5: 76886693-7 | H5: Hecaglobal Instruments SPA | I5: Banco Internacional HGI | P5: Gastos de Oficina
B6: Tomas Castro | D6: HGI. | E6: Siga Sonriendo | F6: Equipos de Protección personal | G6: 77422425-4 | H6: Siga Sonriendo SPA | I6: No Genera Pago | P6: Gastos Operacionales
B7: Alvaro Martínez | D7: SS | E7: Viajes | F7: Otros Gastos de Oficina | G7: 77219167-7 | H7: Sonrie Pro Financial SPA | I7: Cash USD | P7: Gastos de Viaje
B8: Adolfo Quintana | D8: CS | E8: Extras | F8: Reparaciones y remodelaciones | I8: Cash CLP | P8: Siga Sonriendo
B9: Alejandra Olivares | D9: MIXTO | E9: Otros | F9: Artículos de Aseo | I9: Scotianbank CLP | P9: Gastos Financieros
B10: Davis Torres | D10: O. PAÍS | E10: Marketing | F10: Artículos de Oficina | P10: Gastos de Personal
B11: David Herce | D11: C. ORDEN | E11: Gastos de Personal | F11: Bencina | P11: Gastos de Marketing y Publicidad
B12: Rodrigo Letelier | D12: Air Heca | E12: Importaciones / Export. | F12: Estacionamiento | P12: Gastos Extras
B13: Fernando Stange | E13: Activo fijo | F13: TAG | P13: Gastos Tax Ingenieria
B14: Dailin Arellano | E14: Impuestos | F14: Bus- Peaje
B15: ALG | F15: Taxi - Uber
B16: Teresa Espinoza | F16: Metro - tarjeta Bip
B17: Mariangel Veloz | F17: Comidas y Bebidas
B18: Raul Diaz | F18: Gastos Furgón
B19: Javier Salazar | F19: Gastos Auto
B20: Brigitte Moran Mesa | F20: Gastos Varios
B21: Ana Jocelyn Schnell | F21: Maletas Pelican
B22: Arleen Cedeño | F22: Peoneta - Yale
B23: Deisy Sierra | F23: Comisiones Bancarias
B24: Nicolas Gonzalez | F24: Teléfono celular
B25: Edgar hernandez | F25: Estacionamiento Ofic. 25
B26: Abel Kottwitz | F26: Envíos y encomiendas
... B30: Edynar Monsalbe | F30: Gastos de Ambulancia
F31: Peajes / Estacionamientos
F32: Hospedaje
F33: Combustible
F34: Pasajes Bus - Aéreos
F35: Gastos Argentina
F36: Pagos Cristóbal
F37: Gastos Otros Países - Chile
F38: Autopistas CS / Heca SA
F39: Pasajes Aéreos CS
F40: Otros
F41: Almacenaje Importaciones
F42: DIN Importaciones
... F65: Gastos de Vehiculo

Sheet 2024 & 2023 & 2022
B2: COMPARATIVO DE GASTOS
B3: HECA - CHILE
B7: Variacion 2024 | C7: =+C19/GETPIVOTDATA("Cuarter 1 ",$B$25)-1 -> #REF! | D7: =+D19/GETPIVOTDATA("Cuarter 2 ",$B$25)-1 -> #REF! | E7: =+E19/GETPIVOTDATA("Cuarter 3 ",$B$25)-1 -> #REF! | F7: =+F19/GETPIVOTDATA("Cuarter 4 ",$B$25)-1 -> #REF!
B8: 2024
B9: Chile 2024 | C9: Cuarter 1 | D9: Cuarter 2 | E9: Cuarter 3 | F9: Cuarter 4 | I9: Chile | J9: Cuarter 1 | K9: Cuarter 2 | L9: Cuarter 3 | M9: Cuarter 4 | N9: total
B10: Gastos de Oficina | C10: =+GETPIVOTDATA("Monto ",'[1]TD Cuarter'!$B$5,"Cuenta","Gastos de Oficina ") -> #REF! | D10: =+GETPIVOTDATA("Monto ",'[1]TD Cuarter'!$S$5,"Cuenta","Gastos de Oficina ") -> #REF! | E10: =+GETPIVOTDATA("Monto ",'[1]TD Cuarter'!$AG$5,"Cuenta","Gastos de Oficina ") -> #REF! | F10: =+GETPIVOTDATA("Monto ",'[1]TD Cuarter'!$AN$5,"Cuenta","Gastos de Oficina ") -> #REF! | I10: 2024 | J10: =+C19 -> #REF! | K10: =+D19 -> #REF! | L10: =+E19 -> #REF! | M10: =+F19 -> #REF! | N10: =SUM(J10:M10) -> #REF! | O10: =+N10/N11-1 -> #REF! | P10: =+N10/N12-1 -> #REF!
B11: Gastos Operacionales | C11: =+GETPIVOTDATA("Monto ",'[1]TD Cuarter'!$B$5,"Cuenta","Gastos Operacionales ") -> #REF! | D11: =+GETPIVOTDATA("Monto ",'[1]TD Cuarter'!$S$5,"Cuenta","Gastos Operacionales ") -> #REF! | E11: =+GETPIVOTDATA("Monto ",'[1]TD Cuarter'!$AG$5,"Cuenta","Gastos Operacionales ") -> #REF! | F11: =+GETPIVOTDATA("Monto ",'[1]TD Cuarter'!$AN$5,"Cuenta","Gastos Operacionales ") -> #REF! | I11: 2023 | J11: =+GETPIVOTDATA("Cuarter 1 ",$B$25) -> 2.9372403e+08 | K11: =+GETPIVOTDATA("Cuarter 2 ",$B$25) -> 3.2537824e+08 | L11: =+GETPIVOTDATA("Cuarter 3 ",$B$25) -> 3.1624304e+08 | M11: =+GETPIVOTDATA("Cuarter 4 ",$B$25) -> 3.069793e+08 | N11: =SUM(J11:M11) -> 1.2423246e+09 | O11: =+N11/N12-1 -> 0.072363845
B12: Gastos de Viaje | C12: 0 | D12: =+GETPIVOTDATA("Monto ",'[1]TD Cuarter'!$S$5,"Cuenta","Gastos de Viaje ") -> #REF! | E12: =+GETPIVOTDATA("Monto ",'[1]TD Cuarter'!$AG$5,"Cuenta","Gastos de Viaje ") -> #REF! | F12: 0 | I12: 2022 | J12: =+GETPIVOTDATA("Cuarter 1 ",$B$40) -> 2.6838081e+08 | K12: =+GETPIVOTDATA("Cuarter 2 ",$B$40) -> 3.1617478e+08 | L12: =+GETPIVOTDATA("Cuarter 3 ",$B$40) -> 2.392393e+08 | M12: =+GETPIVOTDATA(" cuarter 4",$B$40) -> 3.3469682e+08 | N12: =SUM(J12:M12) -> 1.1584917e+09
B13: Siga Sonriendo | C13: =+GETPIVOTDATA("Monto ",'[1]TD Cuarter'!$B$5,"Cuenta","Siga Sonriendo ") -> #REF! | D13: =+GETPIVOTDATA("Monto ",'[1]TD Cuarter'!$S$5,"Cuenta","Siga Sonriendo ") -> #REF! | E13: =+GETPIVOTDATA("Monto ",'[1]TD Cuarter'!$AG$5,"Cuenta","Siga Sonriendo ") -> #REF! | F13: =+GETPIVOTDATA("Monto ",'[1]TD Cuarter'!$AN$5,"Cuenta","Siga Sonriendo ") -> #REF!
B14: Gastos Financieros | C14: =+GETPIVOTDATA("Monto ",'[1]TD Cuarter'!$B$5,"Cuenta","Gastos Financieros") -> #REF! | D14: =+GETPIVOTDATA("Monto ",'[1]TD Cuarter'!$S$5,"Cuenta","Gastos Financieros") -> #REF! | E14: =+GETPIVOTDATA("Monto ",'[1]TD Cuarter'!$AG$5,"Cuenta","Gastos Financieros") -> #REF! | F14: =+GETPIVOTDATA("Monto ",'[1]TD Cuarter'!$AN$5,"Cuenta","Gastos Financieros") -> #REF!
B15: Gastos de Personal | C15: =+GETPIVOTDATA("Monto ",'[1]TD Cuarter'!$B$5,"Cuenta","Gastos de Personal ") -> #REF! | D15: =+GETPIVOTDATA("Monto ",'[1]TD Cuarter'!$S$5,"Cuenta","Gastos de Personal ") -> #REF! | E15: =+GETPIVOTDATA("Monto ",'[1]TD Cuarter'!$AG$5,"Cuenta","Gastos de Personal ") -> #REF! | F15: =+GETPIVOTDATA("Monto ",'[1]TD Cuarter'!$AN$5,"Cuenta","Gastos de Personal ") -> #REF!
B16: Gastos de Marketing y Publicidad | C16: =+GETPIVOTDATA("Monto ",'[1]TD Cuarter'!$B$5,"Cuenta","Gastos de Marketing y Publicidad ") -> #REF! | D16: =+GETPIVOTDATA("Monto ",'[1]TD Cuarter'!$S$5,"Cuenta","Gastos de Marketing y Publicidad ") -> #REF! | E16: =+GETPIVOTDATA("Monto ",'[1]TD Cuarter'!$AG$5,"Cuenta","Gastos de Marketing y Publicidad ") -> #REF! | F16: 0 | I16: Realizando un analisis comparativo de gastos del año 2024 con 2023, hubo una disminucion del
B17: Gastos Extras | I17: =+O10 -> #REF! | J17: en el periodo
B18: Gastos Tax Ingenieria | C18: =+GETPIVOTDATA("Monto ",'[1]TD Cuarter'!$B$5,"Cuenta","Gastos Tax Ingenieria ") -> #REF! | D18: =+GETPIVOTDATA("Monto ",'[1]TD Cuarter'!$S$5,"Cuenta","Gastos Tax Ingenieria ") -> #REF! | E18: =+GETPIVOTDATA("Monto ",'[1]TD Cuarter'!$AG$5,"Cuenta","Gastos Tax Ingenieria ") -> #REF! | F18: =+GETPIVOTDATA("Monto ",'[1]TD Cuarter'!$AN$5,"Cuenta","Gastos Tax Ingenieria ") -> #REF!
B19: Total general | C19: =SUM(C10:C18) -> #REF! | D19: =SUM(D10:D18) -> #REF! | E19: =SUM(E10:E18) -> #REF! | F19: =SUM(F10:F18) -> #REF! | I19: De igual forma, el 2024 con respecto al 2022 tuvo un crecimiento en los gastos del
I20: =+P10 -> #REF! | J20: en el mismo periodo.
B21: Variacion trimestral | C21: =+C19/GETPIVOTDATA("Cuarter 4 ",$B$25)-1 -> #REF! | D21: =+D19/C19-1 -> #REF! | E21: =+E19/D19-1 -> #REF! | F21: =+F19/E19-1 -> #REF!
B24: 2023
B25: Chile 2023 | C25: Cuarter 1 | D25: Cuarter 2 | E25: Cuarter 3 | F25: Cuarter 4
B26: Gastos de Oficina | C26: 25923832 | D26: 31550235 | E26: 37764132 | F26: 34622950
B27: Gastos de Operaciones | C27: 57771765 | D27: 60692034 | E27: 58744192 | F27: 47009437
B28: Gastos de Viaje | C28: 557138 | D28: 3849235 | E28: 1447983 | F28: 548602
B29: Siga Sonriendo | C29: 9799265 | D29: 4404905 | E29: 4094372 | F29: 4415570
B30: Gastos Financieros | C30: 58632692 | D30: 74596765 | E30: 69111531 | F30: 76094471
B31: Gastos de Personal | C31: 1.0576383e+08 | D31: 1.0843186e+08 | E31: 1.0484164e+08 | F31: 1.0202148e+08
B32: Gasto Tax Ingenieria | C32: 35275515 | D32: 41853206 | E32: 40239181 | F32: 42266791
B33: Total general | C33: 2.9372403e+08 | D33: 3.2537824e+08 | E33: 3.1624304e+08 | F33: 3.069793e+08
B36: Variacion trimestral | C36: =GETPIVOTDATA("Cuarter 1 ",$B$25)/GETPIVOTDATA(" cuarter 4",$B$40)-1 -> -0.12241761 | D36: =GETPIVOTDATA("Cuarter 2 ",$B$25)/GETPIVOTDATA("Cuarter 1 ",$B$25)-1 -> 0.10776854 | E36: =GETPIVOTDATA("Cuarter 3 ",$B$25)/GETPIVOTDATA("Cuarter 2 ",$B$25)-1 -> -0.028075653 | F36: =GETPIVOTDATA("Cuarter 4 ",$B$25)/GETPIVOTDATA("Cuarter 3 ",$B$25)-1 -> -0.029293085
B39: 2022
B40: Chile 2022 | C40: Cuarter 1 | D40: Cuarter 2 | E40: Cuarter 3 | F40: cuarter 4
B41: Gastos de Oficina | C41: 31878058 | D41: 41617780 | E41: 28667274 | F41: 32296786
B42: Gastos de Operaciones | C42: 18498122 | D42: 32614841 | E42: 31407638 | F42: 41457713
B43: Gastos de Viaje | C43: 589436 | D43: 911167 | E43: 668827 | F43: 247775
B44: Siga Sonriendo | C44: 46073406 | D44: 59560197 | E44: 36824033 | F44: 40349454
B45: Gastos Financieros | C45: 41949615 | D45: 53043142 | E45: 45504378 | F45: 70146271
B46: Gastos de Personal | C46: 91520005 | D46: 85141216 | E46: 66117646 | F46: 1.0775891e+08
B47: Gasto Tax Ingenieria | C47: 37872163 | D47: 43286435 | E47: 30049505 | F47: 42439903
B48: Total general | C48: 2.6838081e+08 | D48: 3.1617478e+08 | E48: 2.392393e+08 | F48: 3.3469682e+08
B51: Variacion trimestral | D51: =GETPIVOTDATA("Cuarter 2 ",$B$40)/GETPIVOTDATA("Cuarter 1 ",$B$40)-1 -> 0.17808267 | E51: =+GETPIVOTDATA("Cuarter 3 ",$B$40)/GETPIVOTDATA("Cuarter 2 ",$B$40)-1 -> -0.24333211 | F51: =GETPIVOTDATA(" cuarter 4",$B$40)/GETPIVOTDATA("Cuarter 3 ",$B$40)-1 -> 0.39900432
B53: ****No incluyen los gastos Extras

Sheet 2024&2023& 2022 G. Extra
B2: COMPARATIVO DE GASTOS
B3: HECA - CHILE
I4: Chile | J4: Cuarter 1 | K4: Cuarter 2 | L4: Cuarter 3 | M4: Cuarter 4 | N4: total
I5: 2025 | J5: =+C18 -> 39542991 | K5: =+D18 -> 59196948 | L5: =+E18 -> 63513736 | M5: =+F18 -> 0 | N5: =SUM(J5:K5) -> 98739939
B6: Variacion 2025 | C6: =+C18/C34-1 -> -0.91731827 | D6: =+D18/D34-1 -> -0.88214896 | E6: =+E18/E34-1 -> -0.83120136 | F6: =+F18/F34-1 -> -1 | I6: 2024 | J6: =+C34 -> 4.7825548e+08 | K6: =+D34 -> 5.0230314e+08 | L6: =+E34 -> 3.7626924e+08 | M6: =+F34 -> 5.5667411e+08 | N6: =SUM(J6:K6) -> 9.8055862e+08 | O6: =+N5/N6-1 -> -0.89930236
B7: 2025 | I7: 2023 | J7: =+GETPIVOTDATA("Cuarter 1 ",$B$40) -> 6.1428645e+08 | K7: =+GETPIVOTDATA("Cuarter 2 ",$B$40) -> 5.8766595e+08 | L7: =+GETPIVOTDATA("Cuarter 3 ",$B$40) -> 5.9067415e+08 | M7: =+GETPIVOTDATA("Cuarter 4 ",$B$40) -> 6.3477983e+08 | N7: =SUM(J7:K7) -> 1.2019524e+09 | O7: =+N5/N7-1 -> -0.91785037
B8: Chile 2024 | C8: Cuarter 1 | D8: Cuarter 2 | E8: Cuarter 3 | F8: Cuarter 4 | I8: 2022 | J8: =+GETPIVOTDATA("Cuarter 1 ",$B$55) -> 4.1405747e+08 | K8: =+GETPIVOTDATA("Cuarter 2 ",$B$55) -> 4.6008915e+08 | L8: =+GETPIVOTDATA("Cuarter 3 ",$B$55) -> 3.5225972e+08 | M8: =+GETPIVOTDATA(" cuarter 4",$B$55) -> 5.5706748e+08 | N8: =SUM(J8:K8) -> 8.7414662e+08 | O8: =+N5/N8-1 -> -0.88704419
B9: Gastos de Oficina | C9: =SUM([2]TD!$C$8:$E$8) -> 39542991 | D9: =SUM([2]TD!$F$8:$H$8) -> 59196948 | E9: =SUM([2]TD!$I$8:$K$8) -> 63513736
B10: Gastos Operacionales | C10: =SUM([2]TD!$C$24:$E$24) -> 0 | D10: =SUM([2]TD!$F$24:$H$24) -> 0 | E10: =SUM([2]TD!$I$24:$K$24) -> 0 | I10: Realizando un analisis comparativo de gastos del año 2025 con años anteriores, hubo una disminucion del
B11: Gastos de Viaje | I11: =+O6 -> -0.89930236 | J11: durante el 1er semestre del año
B12: Siga Sonriendo | C12: =SUM([2]TD!$C$37:$E$37) -> 0 | D12: =SUM([2]TD!$F$37:$H$37) -> 0 | E12: =SUM([2]TD!$I$37:$K$37) -> 0
B13: Gastos Financieros | C13: =SUM([2]TD!$C$83:$E$83) -> 0 | D13: =SUM([2]TD!$F$83:$H$83) -> 0 | E13: =SUM([2]TD!$I$83:$K$83) -> 0
B14: Gastos de Personal | C14: =SUM([2]TD!$C$77:$E$77) -> 0 | D14: =SUM([2]TD!$F$77:$H$77) -> 0
B15: Gastos de Marketing y Publicidad
B16: Gastos Extras | C16: =SUM([2]TD!$C$65:$E$65,[2]TD!$C$45:$E$45) -> 0 | D16: =SUM([2]TD!$F$45:$H$45,[2]TD!$F$65:$H$65) -> 0
B17: Gastos Tax Ingenieria | C17: =SUM([2]TD!$C$95:$E$95) -> 0 | D17: =SUM([2]TD!$F$95:$H$95) -> 0
B18: Total general | C18: =SUM(C9:C17) -> 39542991 | D18: =SUM(D9:D17) -> 59196948 | E18: =SUM(E9:E17) -> 63513736 | F18: =SUM(F9:F17) -> 0
B20: Variacion trimestral | C20: =+C18/C34-1 -> -0.91731827 | D20: =+D18/D34/-1 -> -0.11785104 | E20: =+E18/E34/-1 -> -0.16879864 | F20: =+F18/F34/-1 -> 0
B23: 2024
B24: Chile 2024 | C24: Cuarter 1 | D24: Cuarter 2 | E24: Cuarter 3 | F24: Cuarter 4
B25: Gastos de Oficina | C25: 27503870 | D25: 27152063 | E25: 22234572 | F25: 23639180
B26: Gastos Operacionales | C26: 38326905 | D26: 35888514 | E26: 35582526 | F26: 36454116
B27: Gastos de Viaje | C27: 0 | D27: 275428 | E27: 12000 | F27: 0
B28: Siga Sonriendo | C28: 4359326 | D28: 4318237 | E28: 4346056 | F28: 4463227
B29: Gastos Financieros | C29: 53158374 | D29: 54585023 | E29: 43700189 | F29: 39983421
B30: Gastos de Personal | C30: 96773224 | D30: 1.0199314e+08 | E30: 1.1486347e+08 | F30: 1.0210948e+08
B31: Gastos de Marketing y Publicidad | C31: 10326030 | D31: 375000 | E31: 1088820 | F31: 0
B32: Gastos Extras | C32: 2.2236596e+08 | D32: 2.629553e+08 | E32: 1.4469883e+08 | F32: 3.4451789e+08
B33: Gastos Tax Ingenieria | C33: 25441796 | D33: 14760439 | E33: 9742776 | F33: 5506789
B34: Total general | C34: =SUM(C25:C33) -> 4.7825548e+08 | D34: =SUM(D25:D33) -> 5.0230314e+08 | E34: =SUM(E25:E33) -> 3.7626924e+08 | F34: =SUM(F25:F33) -> 5.5667411e+08
B36: Variacion trimestral | C36: =+C34/GETPIVOTDATA("Cuarter 4 ",$B$40)-1 -> -0.24658053 | D36: =+D34/C34-1 -> 0.050282027 | E36: =+E34/D34-1 -> -0.25091202 | F36: =+F34/E34-1 -> 0.47945686
B39: 2023
B40: Chile 2023 | C40: Cuarter 1 | D40: Cuarter 2 | E40: Cuarter 3 | F40: Cuarter 4
B41: Gastos de Oficina | C41: 25923832 | D41: 31550235 | E41: 37764132 | F41: 34622950
B42: Gastos de Operaciones | C42: 57771765 | D42: 60692034 | E42: 58744192 | F42: 47009437
B43: Gastos de Viaje | C43: 557138 | D43: 3849235 | E43: 1447983 | F43: 548602
B44: Siga Sonriendo | C44: 9799265 | D44: 4404905 | E44: 4094372 | F44: 4415570
B45: Gastos Financieros | C45: 58632692 | D45: 74596765 | E45: 69111531 | F45: 76094471
B46: Gastos de Personal | C46: 1.0576383e+08 | D46: 1.0843186e+08 | E46: 1.0484164e+08 | F46: 1.0202148e+08
B47: Gastos Extras | C47: 3.2056242e+08 | D47: 2.6228771e+08 | E47: 2.7443112e+08 | F47: 3.2780053e+08
B48: Gasto Tax Ingenieria | C48: 35275515 | D48: 41853206 | E48: 40239181 | F48: 42266791
B49: Total general | C49: 6.1428645e+08 | D49: 5.8766595e+08 | E49: 5.9067415e+08 | F49: 6.3477983e+08
B51: Variacion trimestral | C51: =GETPIVOTDATA("Cuarter 1 ",$B$40)/GETPIVOTDATA(" cuarter 4",$B$55)-1 -> 0.1027146 | D51: =GETPIVOTDATA("Cuarter 2 ",$B$40)/GETPIVOTDATA("Cuarter 1 ",$B$40)-1 -> -0.043335648 | E51: =GETPIVOTDATA("Cuarter 3 ",$B$40)/GETPIVOTDATA("Cuarter 2 ",$B$40)-1 -> 0.005118899 | F51: =GETPIVOTDATA("Cuarter 4 ",$B$40)/GETPIVOTDATA("Cuarter 3 ",$B$40)-1 -> 0.074670068
B54: 2022
B55: Chile 2022 | C55: Cuarter 1 | D55: Cuarter 2 | E55: Cuarter 3 | F55: cuarter 4
B56: Gastos de Oficina | C56: 31878058 | D56: 41617780 | E56: 28667274 | F56: 32296786
B57: Gastos de Operaciones | C57: 18498122 | D57: 32614841 | E57: 31407638 | F57: 41457713
B58: Gastos de Viaje | C58: 589436 | D58: 911167 | E58: 668827 | F58: 247775
B59: Siga Sonriendo | C59: 46073406 | D59: 59560197 | E59: 36824033 | F59: 40349454
B60: Gastos Financieros | C60: 41949615 | D60: 53043142 | E60: 45504378 | F60: 70146271
B61: Gastos de Personal | C61: 91520005 | D61: 85141216 | E61: 66117646 | F61: 1.0775891e+08
B62: Gastos Extras | C62: 1.4567666e+08 | D62: 1.4391437e+08 | E62: 1.1302042e+08 | F62: 2.2237067e+08
B63: Gasto Tax Ingenieria | C63: 37872163 | D63: 43286435 | E63: 30049505 | F63: 42439903
B64: Total general | C64: 4.1405747e+08 | D64: 4.6008915e+08 | E64: 3.5225972e+08 | F64: 5.5706748e+08
B66: Variacion trimestral | D66: =GETPIVOTDATA("Cuarter 2 ",$B$55)/GETPIVOTDATA("Cuarter 1 ",$B$55)-1 -> 0.1111722 | E66: =+GETPIVOTDATA("Cuarter 3 ",$B$55)/GETPIVOTDATA("Cuarter 2 ",$B$55)-1 -> -0.23436638 | F66: =GETPIVOTDATA(" cuarter 4",$B$55)/GETPIVOTDATA("Cuarter 3 ",$B$55)-1 -> 0.58141125

Sheet Detalle anual Gastos 
B2: Detalle trimestral de Gastos
B3: 2022-2025 | N3: Datos Acumulados
N4: Año | O4: Detalle | P4: Monto | Q4: Cuarter
A5: Tipo de gastos | N5: 2022 | O5: Gastos de Oficina | P5: 31878058 | Q5: Cuarter 1
A6: Gastos Operacionales | N6: 2022 | O6: Gastos Operacionales | P6: 18498122 | Q6: Cuarter 1
N7: 2022 | O7: Gastos de Viaje | P7: 589436 | Q7: Cuarter 1
B8: Chile | C8: Cuarter 1 | E8: Cuarter 2 | G8: Cuarter 3 | I8: Cuarter 4 | K8: total | L8: Parcial | N8: 2022 | O8: Siga Sonriendo | P8: 46073406 | Q8: Cuarter 1 | Y8: Suma de Monto | Z8: Etiquetas de columna
B9: 2025 | C9: =SUMIFS(P5:P122,O5:O122,A6,Q5:Q122,"Cuarter 1",Tabla4[Año],"2025") -> 0 | D9: =+C9/C10-1 -> -1 | E9: =SUMIFS(P5:P122,O5:O122,A6,Q5:Q122,"Cuarter 2",Tabla4[Año],"2025") -> 0 | F9: =+E9/E10-1 -> -1 | G9: =SUMIFS(P5:P122,O5:O122,A6,Q5:Q122,"Cuarter 3",Tabla4[Año],"2025") -> 0 | I9: =SUMIFS(P6:P123,O5:O122,A6,Q5:Q122,"Cuarter 4",Tabla4[Año],"2025") -> 0 | K9: =SUM(C9,E9,G9,I9) -> 0 | L9: =SUM(C9,E9) -> 0 | M9: =+L9/L10-1 -> -1 | N9: 2022 | O9: Gastos Financieros | P9: 41949615 | Q9: Cuarter 1 | Z9: Gastos Financieros | AD9: Total Gastos Financieros | AE9: Total general
B10: 2024 | C10: =SUMIFS(P5:P122,O5:O122,A6,Q5:Q122,"Cuarter 1",Tabla4[Año],"2024") -> 38326905 | E10: =SUMIFS(P5:P122,O5:O122,A6,Q5:Q122,"Cuarter 2",Tabla4[Año],"2024") -> 35888514 | G10: =SUMIFS(P5:P122,O5:O122,A6,Q5:Q122,"Cuarter 3",Tabla4[Año],"2024") -> 35582526 | I10: =SUMIFS(P5:P122,O5:O122,A6,Q5:Q122,"Cuarter 4",Tabla4[Año],"2024") -> 36454116 | K10: =SUM(C10,E10,G10,I10) -> 1.4625206e+08 | L10: =SUM(C10,E10) -> 74215418 | N10: 2022 | O10: Gastos de Personal | P10: 91520005 | Q10: Cuarter 1 | Y10: Etiquetas de fila | Z10: 2022 | AA10: 2023 | AB10: 2024 | AC10: 2025
B11: 2023 | C11: =SUMIFS(P5:P122,O5:O122,A6,Q5:Q122,"Cuarter 1",Tabla4[Año],"2023") -> 57771765 | D11: =+C10/C11-1 -> -0.33658069 | E11: =SUMIFS(P5:P122,O5:O122,A6,Q5:Q122,"Cuarter 2",Tabla4[Año],"2023") -> 60692034 | F11: =+E10/E11-1 -> -0.40867835 | G11: =SUMIFS(P5:P122,O5:O122,A6,Q5:Q122,"Cuarter 3",Tabla4[Año],"2023") -> 58744192 | H11: =+G10/G11-1 -> -0.3942801 | I11: =SUMIFS(P5:P122,O5:O122,A6,Q5:Q122,"Cuarter 4",Tabla4[Año],"2023") -> 47009437 | J11: =+I10/I11-1 -> -0.22453621 | K11: =SUM(C11,E11,G11,I11) -> 2.2421743e+08 | L11: =SUM(C11,E11) -> 118463799 | M11: =+L10/L11-1 -> -0.37351817 | N11: 2022 | O11: Gastos Extras | P11: 1.4567666e+08 | Q11: Cuarter 1 | Y11: Cuarter 1 | Z11: 41949615 | AA11: 58632692 | AB11: 53158374 | AC11: 0 | AD11: 153740681 | AE11: 153740681
B12: 2022 | C12: =SUMIFS(P5:P122,O5:O122,A6,Q5:Q122,"Cuarter 1",Tabla4[Año],"2022") -> 18498122 | E12: =SUMIFS(P5:P122,O5:O122,A6,Q5:Q122,"Cuarter 2",Tabla4[Año],"2022") -> 32614841 | G12: =SUMIFS(P5:P122,O5:O122,A6,Q5:Q122,"Cuarter 3",Tabla4[Año],"2022") -> 31407638 | I12: =SUMIFS(P5:P122,O5:O122,A6,Q5:Q122,"Cuarter 4",Tabla4[Año],"2022") -> 41457713 | K12: =SUM(C12,E12,G12,I12) -> 123978314 | L12: =SUM(C12,E12) -> 51112963 | N12: 2022 | O12: Gastos Tax Ingenieria | Q12: Cuarter 1 | Y12: Cuarter 2 | Z12: 53043142 | AA12: 74596765 | AB12: 54585023 | AC12: 0 | AD12: 182224930 | AE12: 182224930
N13: 2022 | O13: Gastos de Oficina | P13: 41617780 | Q13: Cuarter 2 | Y13: Cuarter 3 | Z13: 45504378 | AA13: 69111531 | AB13: 43700189 | AD13: 158316098 | AE13: 158316098
N14: 2022 | O14: Gastos Operacionales | P14: 32614841 | Q14: Cuarter 2 | Y14: Cuarter 4 | Z14: 70146271 | AA14: 76094471 | AB14: 39983421 | AD14: 186224163 | AE14: 186224163
N15: 2022 | O15: Gastos de Viaje | P15: 911167 | Q15: Cuarter 2 | Y15: Total general | Z15: 210643406 | AA15: 278435459 | AB15: 191427007 | AC15: 0 | AD15: 680505872 | AE15: 680505872
N16: 2022 | O16: Siga Sonriendo | P16: 59560197 | Q16: Cuarter 2
N17: 2022 | O17: Gastos Financieros | P17: 53043142 | Q17: Cuarter 2
N18: 2022 | O18: Gastos de Personal | P18: 85141216 | Q18: Cuarter 2
N19: 2022 | O19: Gastos Extras | P19: 1.4391437e+08 | Q19: Cuarter 2
N20: 2022 | O20: Gastos Tax Ingenieria | P20: 43286435 | Q20: Cuarter 2
N21: 2022 | O21: Gastos de Oficina | P21: 28667274 | Q21: Cuarter 3
N22: 2022 | O22: Gastos Operacionales | P22: 31407638 | Q22: Cuarter 3
N23: 2022 | O23: Gastos de Viaje | P23: 668827 | Q23: Cuarter 3
N24: 2022 | O24: Siga Sonriendo | P24: 36824033 | Q24: Cuarter 3
N25: 2022 | O25: Gastos Financieros | P25: 45504378 | Q25: Cuarter 3
N26: 2022 | O26: Gastos de Personal | P26: 66117646 | Q26: Cuarter 3
N27: 2022 | O27: Gastos Extras | P27: 1.1302042e+08 | Q27: Cuarter 3
... N104: 2024 | O104: Gastos Tax Ingenieria | P104: 5506789 | Q104: Cuarter 4
N105: 2025 | O105: Gastos de Oficina | P105: =+'2024&2023& 2022 G. Extra'!C9 -> 39542991 | Q105: Cuarter 1
N106: 2025 | O106: Gastos Operacionales | P106: =+'2024&2023& 2022 G. Extra'!C10 -> 0 | Q106: Cuarter 1
N107: 2025 | O107: Gastos de Viaje | P107: =+'2024&2023& 2022 G. Extra'!C11 -> 0 | Q107: Cuarter 1
N108: 2025 | O108: Siga Sonriendo | P108: =+'2024&2023& 2022 G. Extra'!C12 -> 0 | Q108: Cuarter 1
N109: 2025 | O109: Gastos Financieros | P109: =+'2024&2023& 2022 G. Extra'!C13 -> 0 | Q109: Cuarter 1
N110: 2025 | O110: Gastos de Personal | P110: =+'2024&2023& 2022 G. Extra'!C14 -> 0 | Q110: Cuarter 1
N111: 2025 | O111: Gastos de Marketing y Publicidad | P111: =+'2024&2023& 2022 G. Extra'!C15 -> 0 | Q111: Cuarter 1
N112: 2025 | O112: Gastos Extras | P112: =+'2024&2023& 2022 G. Extra'!C16 -> 0 | Q112: Cuarter 1
N113: 2025 | O113: Gastos Tax Ingenieria | P113: =+'2024&2023& 2022 G. Extra'!C17 -> 0 | Q113: Cuarter 1
N114: 2025 | O114: Gastos de Oficina | P114: =+'2024&2023& 2022 G. Extra'!D9 -> 59196948 | Q114: Cuarter 2
N115: 2025 | O115: Gastos Operacionales | P115: =+'2024&2023& 2022 G. Extra'!D10 -> 0 | Q115: Cuarter 2
N116: 2025 | O116: Gastos de Viaje | P116: =+'2024&2023& 2022 G. Extra'!D11 -> 0 | Q116: Cuarter 2
N117: 2025 | O117: Siga Sonriendo | P117: =+'2024&2023& 2022 G. Extra'!D12 -> 0 | Q117: Cuarter 2
N118: 2025 | O118: Gastos Financieros | P118: =+'2024&2023& 2022 G. Extra'!D13 -> 0 | Q118: Cuarter 2
N119: 2025 | O119: Gastos de Personal | P119: =+'2024&2023& 2022 G. Extra'!D14 -> 0 | Q119: Cuarter 2
N120: 2025 | O120: Gastos de Marketing y Publicidad | P120: =+'2024&2023& 2022 G. Extra'!D15 -> 0 | Q120: Cuarter 2
N121: 2025 | O121: Gastos Extras | P121: =+'2024&2023& 2022 G. Extra'!D16 -> 0 | Q121: Cuarter 2
N122: 2025 | O122: Gastos Tax Ingenieria | P122: =+'2024&2023& 2022 G. Extra'!D17 -> 0 | Q122: Cuarter 2

Sheet Gastos Generales
B5: Cuenta | C5: Subcuenta | D5: january | E5: february | F5: march | G5: cuarter 1 | H5: april | I5: may | J5: june | K5: cuarter 2 | L5: july | M5: august | N5: september | O5: cuarter 3 | P5: october | Q5: november | R5: december | S5: cuarter 4 | T5: Total
B6: Gastos de Oficina | C6: EMPRESA RECICLADORA PLANETA LIMPIO | D6: =_xlfn.XLOOKUP(C6,[3]Gastos!$B:$B,[3]Gastos!$G:$G) -> 0 | E6: =_xlfn.XLOOKUP(C6,[3]Gastos!$B:$B,[3]Gastos!$L:$L) -> 0 | F6: =_xlfn.XLOOKUP(C6,[3]Gastos!$B:$B,[3]Gastos!$Q:$Q) -> 0 | G6: =SUM(Tabla1[[#This Row],[january]:[march]]) -> 0 | H6: =_xlfn.XLOOKUP(C6,[3]Gastos!$B:$B,[3]Gastos!$V:$V) -> 119540 | I6: =_xlfn.XLOOKUP(C6,[3]Gastos!$B:$B,[3]Gastos!$AA:$AA) -> 215654 | J6: =_xlfn.XLOOKUP(C6,[3]Gastos!$B:$B,[3]Gastos!$AF:$AF) -> 107327 | K6: =SUM(Tabla1[[#This Row],[april]:[june]]) -> 442521 | L6: =_xlfn.XLOOKUP(C6,[3]Gastos!$B:$B,[3]Gastos!$AK:$AK) -> 214680 | M6: =_xlfn.XLOOKUP(C6,[3]Gastos!$B:$B,[3]Gastos!$AP:$AP) -> 107198 | N6: =_xlfn.XLOOKUP(Tabla1[[#This Row],[Subcuenta]],[3]Gastos!$B:$B,[3]Gastos!$AU:$AU) -> 311506 | O6: =SUM(Tabla1[[#This Row],[july]:[september]]) -> 633384 | P6: =_xlfn.XLOOKUP(Tabla1[[#This Row],[Subcuenta]],[3]Gastos!$B:$B,[3]Gastos!$AZ:$AZ) -> 203427 | Q6: =_xlfn.XLOOKUP(Tabla1[[#This Row],[Subcuenta]],[3]Gastos!$B:$B,[3]Gastos!$BE:$BE) -> 222773 | R6: =_xlfn.XLOOKUP(Tabla1[[#This Row],[Subcuenta]],[3]Gastos!$B:$B,[3]Gastos!$BJ:$BJ) -> 299822 | S6: =SUM(Tabla1[[#This Row],[october]:[december]]) -> 726022 | T6: =SUM(G6,K6,O6,S6) -> 1801927
B7: Gastos de Oficina | C7: Equipos de protección al Personal | D7: =_xlfn.XLOOKUP(C7,[3]Gastos!$B:$B,[3]Gastos!$G:$G) -> 0 | E7: =_xlfn.XLOOKUP(C7,[3]Gastos!$B:$B,[3]Gastos!$L:$L) -> 0 | F7: =_xlfn.XLOOKUP(C7,[3]Gastos!$B:$B,[3]Gastos!$Q:$Q) -> 0 | G7: =SUM(Tabla1[[#This Row],[january]:[march]]) -> 0 | H7: =_xlfn.XLOOKUP(C7,[3]Gastos!$B:$B,[3]Gastos!$V:$V) -> 0 | I7: =_xlfn.XLOOKUP(C7,[3]Gastos!$B:$B,[3]Gastos!$AA:$AA) -> 0 | J7: =_xlfn.XLOOKUP(C7,[3]Gastos!$B:$B,[3]Gastos!$AF:$AF) -> 0 | K7: =SUM(Tabla1[[#This Row],[april]:[june]]) -> 0 | L7: =_xlfn.XLOOKUP(C7,[3]Gastos!$B:$B,[3]Gastos!$AK:$AK) -> 0 | M7: =_xlfn.XLOOKUP(C7,[3]Gastos!$B:$B,[3]Gastos!$AP:$AP) -> 0 | N7: =_xlfn.XLOOKUP(Tabla1[[#This Row],[Subcuenta]],[3]Gastos!$B:$B,[3]Gastos!$AU:$AU) -> 1107520 | O7: =SUM(Tabla1[[#This Row],[july]:[september]]) -> 1107520 | P7: =_xlfn.XLOOKUP(Tabla1[[#This Row],[Subcuenta]],[3]Gastos!$B:$B,[3]Gastos!$AZ:$AZ) -> 5523028 | Q7: =_xlfn.XLOOKUP(Tabla1[[#This Row],[Subcuenta]],[3]Gastos!$B:$B,[3]Gastos!$BE:$BE) -> 195200 | R7: =_xlfn.XLOOKUP(Tabla1[[#This Row],[Subcuenta]],[3]Gastos!$B:$B,[3]Gastos!$BJ:$BJ) -> 1787475 | S7: =SUM(Tabla1[[#This Row],[october]:[december]]) -> 7505703 | T7: =SUM(G7,K7,O7,S7) -> 8613223
B8: Gastos de Oficina | C8: Articulos de OFICINA (Dimerc, TodoToner) | D8: =_xlfn.XLOOKUP(C8,[3]Gastos!$B:$B,[3]Gastos!$G:$G) -> 486440 | E8: =_xlfn.XLOOKUP(C8,[3]Gastos!$B:$B,[3]Gastos!$L:$L) -> 643380 | F8: =_xlfn.XLOOKUP(C8,[3]Gastos!$B:$B,[3]Gastos!$Q:$Q) -> 782873 | G8: =SUM(Tabla1[[#This Row],[january]:[march]]) -> 1912693 | H8: =_xlfn.XLOOKUP(C8,[3]Gastos!$B:$B,[3]Gastos!$V:$V) -> 499369 | I8: =_xlfn.XLOOKUP(C8,[3]Gastos!$B:$B,[3]Gastos!$AA:$AA) -> 475469 | J8: =_xlfn.XLOOKUP(C8,[3]Gastos!$B:$B,[3]Gastos!$AF:$AF) -> 439479 | K8: =SUM(Tabla1[[#This Row],[april]:[june]]) -> 1414317 | L8: =_xlfn.XLOOKUP(C8,[3]Gastos!$B:$B,[3]Gastos!$AK:$AK) -> 302827 | M8: =_xlfn.XLOOKUP(C8,[3]Gastos!$B:$B,[3]Gastos!$AP:$AP) -> 754895 | N8: =_xlfn.XLOOKUP(Tabla1[[#This Row],[Subcuenta]],[3]Gastos!$B:$B,[3]Gastos!$AU:$AU) -> 490595 | O8: =SUM(Tabla1[[#This Row],[july]:[september]]) -> 1548317 | P8: =_xlfn.XLOOKUP(Tabla1[[#This Row],[Subcuenta]],[3]Gastos!$B:$B,[3]Gastos!$AZ:$AZ) -> 616738 | Q8: =_xlfn.XLOOKUP(Tabla1[[#This Row],[Subcuenta]],[3]Gastos!$B:$B,[3]Gastos!$BE:$BE) -> 405348 | R8: =_xlfn.XLOOKUP(Tabla1[[#This Row],[Subcuenta]],[3]Gastos!$B:$B,[3]Gastos!$BJ:$BJ) -> 0 | S8: =SUM(Tabla1[[#This Row],[october]:[december]]) -> 1022086 | T8: =SUM(G8,K8,O8,S8) -> 5897413
B9: Gastos de Oficina | C9: AGUA MINERAL | D9: =_xlfn.XLOOKUP(C9,[3]Gastos!$B:$B,[3]Gastos!$G:$G) -> 60000 | E9: =_xlfn.XLOOKUP(C9,[3]Gastos!$B:$B,[3]Gastos!$L:$L) -> 75000 | F9: =_xlfn.XLOOKUP(C9,[3]Gastos!$B:$B,[3]Gastos!$Q:$Q) -> 108000 | G9: =SUM(Tabla1[[#This Row],[january]:[march]]) -> 243000 | H9: =_xlfn.XLOOKUP(C9,[3]Gastos!$B:$B,[3]Gastos!$V:$V) -> 0 | I9: =_xlfn.XLOOKUP(C9,[3]Gastos!$B:$B,[3]Gastos!$AA:$AA) -> 123000 | J9: =_xlfn.XLOOKUP(C9,[3]Gastos!$B:$B,[3]Gastos!$AF:$AF) -> 0 | K9: =SUM(Tabla1[[#This Row],[april]:[june]]) -> 123000 | L9: =_xlfn.XLOOKUP(C9,[3]Gastos!$B:$B,[3]Gastos!$AK:$AK) -> 54000 | M9: =_xlfn.XLOOKUP(C9,[3]Gastos!$B:$B,[3]Gastos!$AP:$AP) -> 48000 | N9: =_xlfn.XLOOKUP(Tabla1[[#This Row],[Subcuenta]],[3]Gastos!$B:$B,[3]Gastos!$AU:$AU) -> 120000 | O9: =SUM(Tabla1[[#This Row],[july]:[september]]) -> 222000 | P9: =_xlfn.XLOOKUP(Tabla1[[#This Row],[Subcuenta]],[3]Gastos!$B:$B,[3]Gastos!$AZ:$AZ) -> 72000 | Q9: =_xlfn.XLOOKUP(Tabla1[[#This Row],[Subcuenta]],[3]Gastos!$B:$B,[3]Gastos!$BE:$BE) -> 0 | R9: =_xlfn.XLOOKUP(Tabla1[[#This Row],[Subcuenta]],[3]Gastos!$B:$B,[3]Gastos!$BJ:$BJ) -> 57000 | S9: =SUM(Tabla1[[#This Row],[october]:[december]]) -> 129000 | T9: =SUM(G9,K9,O9,S9) -> 717000
B10: Gastos de Oficina | C10: Mantencion de Aires Acondicionados / Impresoras/ GEOVICTORIA | D10: =_xlfn.XLOOKUP(C10,[3]Gastos!$B:$B,[3]Gastos!$G:$G) -> 0 | E10: =_xlfn.XLOOKUP(C10,[3]Gastos!$B:$B,[3]Gastos!$L:$L) -> 0 | F10: =_xlfn.XLOOKUP(C10,[3]Gastos!$B:$B,[3]Gastos!$Q:$Q) -> 0 | G10: =SUM(Tabla1[[#This Row],[january]:[march]]) -> 0 | H10: =_xlfn.XLOOKUP(C10,[3]Gastos!$B:$B,[3]Gastos!$V:$V) -> 890788 | I10: =_xlfn.XLOOKUP(C10,[3]Gastos!$B:$B,[3]Gastos!$AA:$AA) -> 0 | J10: =_xlfn.XLOOKUP(C10,[3]Gastos!$B:$B,[3]Gastos!$AF:$AF) -> 14064 | K10: =SUM(Tabla1[[#This Row],[april]:[june]]) -> 904852 | L10: =_xlfn.XLOOKUP(C10,[3]Gastos!$B:$B,[3]Gastos!$AK:$AK) -> 0 | M10: =_xlfn.XLOOKUP(C10,[3]Gastos!$B:$B,[3]Gastos!$AP:$AP) -> 294565 | N10: =_xlfn.XLOOKUP(Tabla1[[#This Row],[Subcuenta]],[3]Gastos!$B:$B,[3]Gastos!$AU:$AU) -> 0 | O10: =SUM(Tabla1[[#This Row],[july]:[september]]) -> 294565 | P10: =_xlfn.XLOOKUP(Tabla1[[#This Row],[Subcuenta]],[3]Gastos!$B:$B,[3]Gastos!$AZ:$AZ) -> 0 | Q10: =_xlfn.XLOOKUP(Tabla1[[#This Row],[Subcuenta]],[3]Gastos!$B:$B,[3]Gastos!$BE:$BE) -> 0 | R10: =_xlfn.XLOOKUP(Tabla1[[#This Row],[Subcuenta]],[3]Gastos!$B:$B,[3]Gastos!$BJ:$BJ) -> 0 | S10: =SUM(Tabla1[[#This Row],[october]:[december]]) -> 0 | T10: =SUM(G10,K10,O10,S10) -> 1199417
B11: Gastos de Oficina | C11: INTERNET CLARO / ENTEL CELULARES | D11: =_xlfn.XLOOKUP(C11,[3]Gastos!$B:$B,[3]Gastos!$G:$G) -> 181690 | E11: =_xlfn.XLOOKUP(C11,[3]Gastos!$B:$B,[3]Gastos!$L:$L) -> 220051 | F11: =_xlfn.XLOOKUP(C11,[3]Gastos!$B:$B,[3]Gastos!$Q:$Q) -> 229864 | G11: =SUM(Tabla1[[#This Row],[january]:[march]]) -> 631605 | H11: =_xlfn.XLOOKUP(C11,[3]Gastos!$B:$B,[3]Gastos!$V:$V) -> 203690 | I11: =_xlfn.XLOOKUP(C11,[3]Gastos!$B:$B,[3]Gastos!$AA:$AA) -> 216310 | J11: =_xlfn.XLOOKUP(C11,[3]Gastos!$B:$B,[3]Gastos!$AF:$AF) -> 217106 | K11: =SUM(Tabla1[[#This Row],[april]:[june]]) -> 637106 | L11: =_xlfn.XLOOKUP(C11,[3]Gastos!$B:$B,[3]Gastos!$AK:$AK) -> 189969 | M11: =_xlfn.XLOOKUP(C11,[3]Gastos!$B:$B,[3]Gastos!$AP:$AP) -> 219821 | N11: =_xlfn.XLOOKUP(Tabla1[[#This Row],[Subcuenta]],[3]Gastos!$B:$B,[3]Gastos!$AU:$AU) -> 188717 | O11: =SUM(Tabla1[[#This Row],[july]:[september]]) -> 598507 | P11: =_xlfn.XLOOKUP(Tabla1[[#This Row],[Subcuenta]],[3]Gastos!$B:$B,[3]Gastos!$AZ:$AZ) -> 194279 | Q11: =_xlfn.XLOOKUP(Tabla1[[#This Row],[Subcuenta]],[3]Gastos!$B:$B,[3]Gastos!$BE:$BE) -> 184313 | R11: =_xlfn.XLOOKUP(Tabla1[[#This Row],[Subcuenta]],[3]Gastos!$B:$B,[3]Gastos!$BJ:$BJ) -> 196693 | S11: =SUM(Tabla1[[#This Row],[october]:[december]]) -> 575285 | T11: =SUM(G11,K11,O11,S11) -> 2442503
B12: Gastos de Oficina | C12: OFICINA 450-455-460 GASTOS ENTRE HECAGLOBAL / HGI | D12: =_xlfn.XLOOKUP(C12,[3]Gastos!$B:$B,[3]Gastos!$G:$G) -> 0 | E12: =_xlfn.XLOOKUP(C12,[3]Gastos!$B:$B,[3]Gastos!$L:$L) -> 0 | F12: =_xlfn.XLOOKUP(C12,[3]Gastos!$B:$B,[3]Gastos!$Q:$Q) -> 0 | G12: =SUM(Tabla1[[#This Row],[january]:[march]]) -> 0 | H12: =_xlfn.XLOOKUP(C12,[3]Gastos!$B:$B,[3]Gastos!$V:$V) -> 0 | I12: =_xlfn.XLOOKUP(C12,[3]Gastos!$B:$B,[3]Gastos!$AA:$AA) -> 0 | J12: =_xlfn.XLOOKUP(C12,[3]Gastos!$B:$B,[3]Gastos!$AF:$AF) -> 0 | K12: =SUM(Tabla1[[#This Row],[april]:[june]]) -> 0 | L12: =_xlfn.XLOOKUP(C12,[3]Gastos!$B:$B,[3]Gastos!$AK:$AK) -> 0 | M12: =_xlfn.XLOOKUP(C12,[3]Gastos!$B:$B,[3]Gastos!$AP:$AP) -> 0 | N12: =_xlfn.XLOOKUP(Tabla1[[#This Row],[Subcuenta]],[3]Gastos!$B:$B,[3]Gastos!$AU:$AU) -> 0 | O12: =SUM(Tabla1[[#This Row],[july]:[september]]) -> 0 | P12: =_xlfn.XLOOKUP(Tabla1[[#This Row],[Subcuenta]],[3]Gastos!$B:$B,[3]Gastos!$AZ:$AZ) -> 0 | Q12: =_xlfn.XLOOKUP(Tabla1[[#This Row],[Subcuenta]],[3]Gastos!$B:$B,[3]Gastos!$BE:$BE) -> 0 | R12: =_xlfn.XLOOKUP(Tabla1[[#This Row],[Subcuenta]],[3]Gastos!$B:$B,[3]Gastos!$BJ:$BJ) -> 0 | S12: =SUM(Tabla1[[#This Row],[october]:[december]]) -> 0 | T12: =SUM(G12,K12,O12,S12) -> 0
B13: Gastos de Oficina | C13: OFICINA 455 EGAÑA - ARRIENDO / VERISURE / ENTEL INTERNET | D13: =_xlfn.XLOOKUP(C13,[3]Gastos!$B:$B,[3]Gastos!$G:$G) -> 304940.5 | E13: =_xlfn.XLOOKUP(C13,[3]Gastos!$B:$B,[3]Gastos!$L:$L) -> 305179.5 | F13: =_xlfn.XLOOKUP(C13,[3]Gastos!$B:$B,[3]Gastos!$Q:$Q) -> 305580.5 | G13: =SUM(Tabla1[[#This Row],[january]:[march]]) -> 915700.5 | H13: =_xlfn.XLOOKUP(C13,[3]Gastos!$B:$B,[3]Gastos!$V:$V) -> 305411.5 | I13: =_xlfn.XLOOKUP(C13,[3]Gastos!$B:$B,[3]Gastos!$AA:$AA) -> 867011.97 | J13: =_xlfn.XLOOKUP(C13,[3]Gastos!$B:$B,[3]Gastos!$AF:$AF) -> 358929 | K13: =SUM(Tabla1[[#This Row],[april]:[june]]) -> 1531352.5 | L13: =_xlfn.XLOOKUP(C13,[3]Gastos!$B:$B,[3]Gastos!$AK:$AK) -> 359015.5 | M13: =_xlfn.XLOOKUP(C13,[3]Gastos!$B:$B,[3]Gastos!$AP:$AP) -> 369230 | N13: =_xlfn.XLOOKUP(Tabla1[[#This Row],[Subcuenta]],[3]Gastos!$B:$B,[3]Gastos!$AU:$AU) -> 369402.5 | O13: =SUM(Tabla1[[#This Row],[july]:[september]]) -> 1097648 | P13: =_xlfn.XLOOKUP(Tabla1[[#This Row],[Subcuenta]],[3]Gastos!$B:$B,[3]Gastos!$AZ:$AZ) -> 359184.5 | Q13: =_xlfn.XLOOKUP(Tabla1[[#This Row],[Subcuenta]],[3]Gastos!$B:$B,[3]Gastos!$BE:$BE) -> 369877.5 | R13: =_xlfn.XLOOKUP(Tabla1[[#This Row],[Subcuenta]],[3]Gastos!$B:$B,[3]Gastos!$BJ:$BJ) -> 359760 | S13: =SUM(Tabla1[[#This Row],[october]:[december]]) -> 1088822 | T13: =SUM(G13,K13,O13,S13) -> 4633523
B14: Gastos de Oficina | C14: OFICINA 450-455-460 EGAÑA Gasto Comun | D14: =_xlfn.XLOOKUP(C14,[3]Gastos!$B:$B,[3]Gastos!$G:$G) -> 224021 | E14: =_xlfn.XLOOKUP(C14,[3]Gastos!$B:$B,[3]Gastos!$L:$L) -> 205183 | F14: =_xlfn.XLOOKUP(C14,[3]Gastos!$B:$B,[3]Gastos!$Q:$Q) -> 214506 | G14: =SUM(Tabla1[[#This Row],[january]:[march]]) -> 643710 | H14: =_xlfn.XLOOKUP(C14,[3]Gastos!$B:$B,[3]Gastos!$V:$V) -> 216110.5 | I14: =_xlfn.XLOOKUP(C14,[3]Gastos!$B:$B,[3]Gastos!$AA:$AA) -> 223958.5 | J14: =_xlfn.XLOOKUP(C14,[3]Gastos!$B:$B,[3]Gastos!$AF:$AF) -> 228407.5 | K14: =SUM(Tabla1[[#This Row],[april]:[june]]) -> 668476.5 | L14: =_xlfn.XLOOKUP(C14,[3]Gastos!$B:$B,[3]Gastos!$AK:$AK) -> 232310 | M14: =_xlfn.XLOOKUP(C14,[3]Gastos!$B:$B,[3]Gastos!$AP:$AP) -> 241576 | N14: =_xlfn.XLOOKUP(Tabla1[[#This Row],[Subcuenta]],[3]Gastos!$B:$B,[3]Gastos!$AU:$AU) -> 248480.5 | O14: =SUM(Tabla1[[#This Row],[july]:[september]]) -> 722366.5 | P14: =_xlfn.XLOOKUP(Tabla1[[#This Row],[Subcuenta]],[3]Gastos!$B:$B,[3]Gastos!$AZ:$AZ) -> 252650 | Q14: =_xlfn.XLOOKUP(Tabla1[[#This Row],[Subcuenta]],[3]Gastos!$B:$B,[3]Gastos!$BE:$BE) -> 249075.5 | R14: =_xlfn.XLOOKUP(Tabla1[[#This Row],[Subcuenta]],[3]Gastos!$B:$B,[3]Gastos!$BJ:$BJ) -> 249075.5 | S14: =SUM(Tabla1[[#This Row],[october]:[december]]) -> 750801 | T14: =SUM(G14,K14,O14,S14) -> 2785354
B15: Gastos de Oficina | C15: OFICINA 450-455-460 EGAÑA - AGUAS ANDINAS | D15: =_xlfn.XLOOKUP(C15,[3]Gastos!$B:$B,[3]Gastos!$G:$G) -> 2960 | E15: =_xlfn.XLOOKUP(C15,[3]Gastos!$B:$B,[3]Gastos!$L:$L) -> 3605 | F15: =_xlfn.XLOOKUP(C15,[3]Gastos!$B:$B,[3]Gastos!$Q:$Q) -> 3665 | G15: =SUM(Tabla1[[#This Row],[january]:[march]]) -> 10230 | H15: =_xlfn.XLOOKUP(C15,[3]Gastos!$B:$B,[3]Gastos!$V:$V) -> 1810 | I15: =_xlfn.XLOOKUP(C15,[3]Gastos!$B:$B,[3]Gastos!$AA:$AA) -> 3090 | J15: =_xlfn.XLOOKUP(C15,[3]Gastos!$B:$B,[3]Gastos!$AF:$AF) -> 2475 | K15: =SUM(Tabla1[[#This Row],[april]:[june]]) -> 7375 | L15: =_xlfn.XLOOKUP(C15,[3]Gastos!$B:$B,[3]Gastos!$AK:$AK) -> 3740 | M15: =_xlfn.XLOOKUP(C15,[3]Gastos!$B:$B,[3]Gastos!$AP:$AP) -> 2474 | N15: =_xlfn.XLOOKUP(Tabla1[[#This Row],[Subcuenta]],[3]Gastos!$B:$B,[3]Gastos!$AU:$AU) -> 3635 | O15: =SUM(Tabla1[[#This Row],[july]:[september]]) -> 9849 | P15: =_xlfn.XLOOKUP(Tabla1[[#This Row],[Subcuenta]],[3]Gastos!$B:$B,[3]Gastos!$AZ:$AZ) -> 2615 | Q15: =_xlfn.XLOOKUP(Tabla1[[#This Row],[Subcuenta]],[3]Gastos!$B:$B,[3]Gastos!$BE:$BE) -> 3150 | R15: =_xlfn.XLOOKUP(Tabla1[[#This Row],[Subcuenta]],[3]Gastos!$B:$B,[3]Gastos!$BJ:$BJ) -> 5090.5 | S15: =SUM(Tabla1[[#This Row],[october]:[december]]) -> 10855.5 | T15: =SUM(G15,K15,O15,S15) -> 38309.5
B16: Gastos de Oficina | C16: OFICINA 450-455-460 EGAÑA - ENEL | D16: =_xlfn.XLOOKUP(C16,[3]Gastos!$B:$B,[3]Gastos!$G:$G) -> 0 | E16: =_xlfn.XLOOKUP(C16,[3]Gastos!$B:$B,[3]Gastos!$L:$L) -> 65307 | F16: =_xlfn.XLOOKUP(C16,[3]Gastos!$B:$B,[3]Gastos!$Q:$Q) -> 22831.5 | G16: =SUM(Tabla1[[#This Row],[january]:[march]]) -> 88138.5 | H16: =_xlfn.XLOOKUP(C16,[3]Gastos!$B:$B,[3]Gastos!$V:$V) -> 28688.5 | I16: =_xlfn.XLOOKUP(C16,[3]Gastos!$B:$B,[3]Gastos!$AA:$AA) -> 27180.5 | J16: =_xlfn.XLOOKUP(C16,[3]Gastos!$B:$B,[3]Gastos!$AF:$AF) -> 43173 | K16: =SUM(Tabla1[[#This Row],[april]:[june]]) -> 99042 | L16: =_xlfn.XLOOKUP(C16,[3]Gastos!$B:$B,[3]Gastos!$AK:$AK) -> 142513.5 | M16: =_xlfn.XLOOKUP(C16,[3]Gastos!$B:$B,[3]Gastos!$AP:$AP) -> 89998 | N16: =_xlfn.XLOOKUP(Tabla1[[#This Row],[Subcuenta]],[3]Gastos!$B:$B,[3]Gastos!$AU:$AU) -> 71590.5 | O16: =SUM(Tabla1[[#This Row],[july]:[september]]) -> 304102 | P16: =_xlfn.XLOOKUP(Tabla1[[#This Row],[Subcuenta]],[3]Gastos!$B:$B,[3]Gastos!$AZ:$AZ) -> 67317 | Q16: =_xlfn.XLOOKUP(Tabla1[[#This Row],[Subcuenta]],[3]Gastos!$B:$B,[3]Gastos!$BE:$BE) -> 46239 | R16: =_xlfn.XLOOKUP(Tabla1[[#This Row],[Subcuenta]],[3]Gastos!$B:$B,[3]Gastos!$BJ:$BJ) -> 11741 | S16: =SUM(Tabla1[[#This Row],[october]:[december]]) -> 125297 | T16: =SUM(G16,K16,O16,S16) -> 616579.5
B17: Gastos de Oficina | C17: OFICINA 520-525-530 - ARRIENDO / VERISURE / ENTEL INTERNET / ENTEL TELEFONIA | D17: =_xlfn.XLOOKUP(C17,[3]Gastos!$B:$B,[3]Gastos!$G:$G) -> 3241786 | E17: =_xlfn.XLOOKUP(C17,[3]Gastos!$B:$B,[3]Gastos!$L:$L) -> 3255357 | F17: =_xlfn.XLOOKUP(C17,[3]Gastos!$B:$B,[3]Gastos!$Q:$Q) -> 3277365 | G17: =SUM(Tabla1[[#This Row],[january]:[march]]) -> 9774508 | H17: =_xlfn.XLOOKUP(C17,[3]Gastos!$B:$B,[3]Gastos!$V:$V) -> 3280847 | I17: =_xlfn.XLOOKUP(C17,[3]Gastos!$B:$B,[3]Gastos!$AA:$AA) -> 3308238 | J17: =_xlfn.XLOOKUP(C17,[3]Gastos!$B:$B,[3]Gastos!$AF:$AF) -> 3325364 | K17: =SUM(Tabla1[[#This Row],[april]:[june]]) -> 9914449 | L17: =_xlfn.XLOOKUP(C17,[3]Gastos!$B:$B,[3]Gastos!$AK:$AK) -> 3378694 | M17: =_xlfn.XLOOKUP(C17,[3]Gastos!$B:$B,[3]Gastos!$AP:$AP) -> 4612098 | N17: =_xlfn.XLOOKUP(Tabla1[[#This Row],[Subcuenta]],[3]Gastos!$B:$B,[3]Gastos!$AU:$AU) -> 3328613 | O17: =SUM(Tabla1[[#This Row],[july]:[september]]) -> 11319405 | P17: =_xlfn.XLOOKUP(Tabla1[[#This Row],[Subcuenta]],[3]Gastos!$B:$B,[3]Gastos!$AZ:$AZ) -> 3341394 | Q17: =_xlfn.XLOOKUP(Tabla1[[#This Row],[Subcuenta]],[3]Gastos!$B:$B,[3]Gastos!$BE:$BE) -> 3344310 | R17: =_xlfn.XLOOKUP(Tabla1[[#This Row],[Subcuenta]],[3]Gastos!$B:$B,[3]Gastos!$BJ:$BJ) -> 3368569 | S17: =SUM(Tabla1[[#This Row],[october]:[december]]) -> 10054273 | T17: =SUM(G17,K17,O17,S17) -> 41062635
... B27: Gastos de Oficina | C27: GASTOS REMODELACION OFICINAS | D27: =_xlfn.XLOOKUP(C27,[3]Gastos!$B:$B,[3]Gastos!$G:$G) -> 0 | E27: =_xlfn.XLOOKUP(C27,[3]Gastos!$B:$B,[3]Gastos!$L:$L) -> 0 | F27: =_xlfn.XLOOKUP(C27,[3]Gastos!$B:$B,[3]Gastos!$Q:$Q) -> 0 | G27: =SUM(Tabla1[[#This Row],[january]:[march]]) -> 0 | H27: =_xlfn.XLOOKUP(C27,[3]Gastos!$B:$B,[3]Gastos!$V:$V) -> 0 | I27: =_xlfn.XLOOKUP(C27,[3]Gastos!$B:$B,[3]Gastos!$AA:$AA) -> 0 | J27: =_xlfn.XLOOKUP(C27,[3]Gastos!$B:$B,[3]Gastos!$AF:$AF) -> 0 | K27: =SUM(Tabla1[[#This Row],[april]:[june]]) -> 0 | L27: =_xlfn.XLOOKUP(C27,[3]Gastos!$B:$B,[3]Gastos!$AK:$AK) -> 0 | M27: =_xlfn.XLOOKUP(C27,[3]Gastos!$B:$B,[3]Gastos!$AP:$AP) -> 0 | N27: =_xlfn.XLOOKUP(Tabla1[[#This Row],[Subcuenta]],[3]Gastos!$B:$B,[3]Gastos!$AU:$AU) -> 0 | O27: =SUM(Tabla1[[#This Row],[july]:[september]]) -> 0 | P27: =_xlfn.XLOOKUP(Tabla1[[#This Row],[Subcuenta]],[3]Gastos!$B:$B,[3]Gastos!$AZ:$AZ) -> 0 | Q27: =_xlfn.XLOOKUP(Tabla1[[#This Row],[Subcuenta]],[3]Gastos!$B:$B,[3]Gastos!$BE:$BE) -> 0 | R27: =_xlfn.XLOOKUP(Tabla1[[#This Row],[Subcuenta]],[3]Gastos!$B:$B,[3]Gastos!$BJ:$BJ) -> 0 | S27: =SUM(Tabla1[[#This Row],[october]:[december]]) -> 0 | T27: =SUM(G27,K27,O27,S27) -> 0
B28: Gastos de Oficina | C28: Gastos de OFICINA de rendiciones | D28: =_xlfn.XLOOKUP(C28,[3]Gastos!$B:$B,[3]Gastos!$G:$G) -> 284892 | E28: =_xlfn.XLOOKUP(C28,[3]Gastos!$B:$B,[3]Gastos!$L:$L) -> 427103 | F28: =_xlfn.XLOOKUP(C28,[3]Gastos!$B:$B,[3]Gastos!$Q:$Q) -> 1143587 | G28: =SUM(Tabla1[[#This Row],[january]:[march]]) -> 1855582 | H28: =_xlfn.XLOOKUP(C28,[3]Gastos!$B:$B,[3]Gastos!$V:$V) -> 1389788 | I28: =_xlfn.XLOOKUP(C28,[3]Gastos!$B:$B,[3]Gastos!$AA:$AA) -> 419287 | J28: =_xlfn.XLOOKUP(C28,[3]Gastos!$B:$B,[3]Gastos!$AF:$AF) -> 1979452 | K28: =SUM(Tabla1[[#This Row],[april]:[june]]) -> 3788527 | L28: =_xlfn.XLOOKUP(C28,[3]Gastos!$B:$B,[3]Gastos!$AK:$AK) -> 554667 | M28: =_xlfn.XLOOKUP(C28,[3]Gastos!$B:$B,[3]Gastos!$AP:$AP) -> 826890.28 | N28: =_xlfn.XLOOKUP(Tabla1[[#This Row],[Subcuenta]],[3]Gastos!$B:$B,[3]Gastos!$AU:$AU) -> 956499 | O28: =SUM(Tabla1[[#This Row],[july]:[september]]) -> 2338056.3 | P28: =_xlfn.XLOOKUP(Tabla1[[#This Row],[Subcuenta]],[3]Gastos!$B:$B,[3]Gastos!$AZ:$AZ) -> 1924381 | Q28: =_xlfn.XLOOKUP(Tabla1[[#This Row],[Subcuenta]],[3]Gastos!$B:$B,[3]Gastos!$BE:$BE) -> 722300 | R28: =_xlfn.XLOOKUP(Tabla1[[#This Row],[Subcuenta]],[3]Gastos!$B:$B,[3]Gastos!$BJ:$BJ) -> 1605403.1 | S28: =SUM(Tabla1[[#This Row],[october]:[december]]) -> 4252084 | T28: =SUM(G28,K28,O28,S28) -> 12234249 | U28: =SUM(#REF!) -> #REF!
B29: Gastos de Operaciones | C29: ASB Contadores / W & A ASESORIAS / KRESTON AUDITORES | D29: =_xlfn.XLOOKUP(C29,[3]Gastos!$B:$B,[3]Gastos!$G:$G) -> 2876438 | E29: =_xlfn.XLOOKUP(C29,[3]Gastos!$B:$B,[3]Gastos!$L:$L) -> 10090517 | F29: =_xlfn.XLOOKUP(C29,[3]Gastos!$B:$B,[3]Gastos!$Q:$Q) -> 13541392 | G29: =SUM(Tabla1[[#This Row],[january]:[march]]) -> 26508347 | H29: =_xlfn.XLOOKUP(C29,[3]Gastos!$B:$B,[3]Gastos!$V:$V) -> 3058386 | I29: =_xlfn.XLOOKUP(C29,[3]Gastos!$B:$B,[3]Gastos!$AA:$AA) -> 10408611 | J29: =_xlfn.XLOOKUP(C29,[3]Gastos!$B:$B,[3]Gastos!$AF:$AF) -> 10487407 | K29: =SUM(Tabla1[[#This Row],[april]:[june]]) -> 23954404 | L29: =_xlfn.XLOOKUP(C29,[3]Gastos!$B:$B,[3]Gastos!$AK:$AK) -> 10488024 | M29: =_xlfn.XLOOKUP(C29,[3]Gastos!$B:$B,[3]Gastos!$AP:$AP) -> 3123403 | N29: 3124075 | O29: =SUM(Tabla1[[#This Row],[july]:[september]]) -> 16735502 | P29: =_xlfn.XLOOKUP(Tabla1[[#This Row],[Subcuenta]],[3]Gastos!$B:$B,[3]Gastos!$AZ:$AZ) -> 3125981 | Q29: =_xlfn.XLOOKUP(Tabla1[[#This Row],[Subcuenta]],[3]Gastos!$B:$B,[3]Gastos!$BE:$BE) -> 3127739 | R29: =_xlfn.XLOOKUP(Tabla1[[#This Row],[Subcuenta]],[3]Gastos!$B:$B,[3]Gastos!$BJ:$BJ) -> 2345394 | S29: =SUM(Tabla1[[#This Row],[october]:[december]]) -> 8599114 | T29: =SUM(G29,K29,O29,S29) -> 75797367
B30: Gastos de Operaciones | C30: Autopista Central | D30: =_xlfn.XLOOKUP(C30,[3]Gastos!$B:$B,[3]Gastos!$G:$G) -> 275093 | E30: =_xlfn.XLOOKUP(C30,[3]Gastos!$B:$B,[3]Gastos!$L:$L) -> 245023 | F30: =_xlfn.XLOOKUP(C30,[3]Gastos!$B:$B,[3]Gastos!$Q:$Q) -> 182898 | G30: =SUM(Tabla1[[#This Row],[january]:[march]]) -> 703014 | H30: =_xlfn.XLOOKUP(C30,[3]Gastos!$B:$B,[3]Gastos!$V:$V) -> 251948 | I30: =_xlfn.XLOOKUP(C30,[3]Gastos!$B:$B,[3]Gastos!$AA:$AA) -> 213415 | J30: =_xlfn.XLOOKUP(C30,[3]Gastos!$B:$B,[3]Gastos!$AF:$AF) -> 269392 | K30: =SUM(Tabla1[[#This Row],[april]:[june]]) -> 734755 | L30: =_xlfn.XLOOKUP(C30,[3]Gastos!$B:$B,[3]Gastos!$AK:$AK) -> 226822 | M30: =_xlfn.XLOOKUP(C30,[3]Gastos!$B:$B,[3]Gastos!$AP:$AP) -> 91758 | N30: 122224.15 | O30: =SUM(Tabla1[[#This Row],[july]:[september]]) -> 440804.15 | P30: =_xlfn.XLOOKUP(Tabla1[[#This Row],[Subcuenta]],[3]Gastos!$B:$B,[3]Gastos!$AZ:$AZ) -> 19581 | Q30: =_xlfn.XLOOKUP(Tabla1[[#This Row],[Subcuenta]],[3]Gastos!$B:$B,[3]Gastos!$BE:$BE) -> 33089 | R30: =_xlfn.XLOOKUP(Tabla1[[#This Row],[Subcuenta]],[3]Gastos!$B:$B,[3]Gastos!$BJ:$BJ) -> 91754.44 | S30: =SUM(Tabla1[[#This Row],[october]:[december]]) -> 144424.44 | T30: =SUM(G30,K30,O30,S30) -> 2022997.6
B31: Gastos de Operaciones | C31: Vespucio Norte | D31: =_xlfn.XLOOKUP(C31,[3]Gastos!$B:$B,[3]Gastos!$G:$G) -> 185557 | E31: =_xlfn.XLOOKUP(C31,[3]Gastos!$B:$B,[3]Gastos!$L:$L) -> 211090 | F31: =_xlfn.XLOOKUP(C31,[3]Gastos!$B:$B,[3]Gastos!$Q:$Q) -> 192281 | G31: =SUM(Tabla1[[#This Row],[january]:[march]]) -> 588928 | H31: =_xlfn.XLOOKUP(C31,[3]Gastos!$B:$B,[3]Gastos!$V:$V) -> 251712 | I31: =_xlfn.XLOOKUP(C31,[3]Gastos!$B:$B,[3]Gastos!$AA:$AA) -> 217861 | J31: =_xlfn.XLOOKUP(C31,[3]Gastos!$B:$B,[3]Gastos!$AF:$AF) -> 208211 | K31: =SUM(Tabla1[[#This Row],[april]:[june]]) -> 677784 | L31: =_xlfn.XLOOKUP(C31,[3]Gastos!$B:$B,[3]Gastos!$AK:$AK) -> 183999 | M31: =_xlfn.XLOOKUP(C31,[3]Gastos!$B:$B,[3]Gastos!$AP:$AP) -> 21330 | N31: 8631.97 | O31: =SUM(Tabla1[[#This Row],[july]:[september]]) -> 213960.97 | P31: =_xlfn.XLOOKUP(Tabla1[[#This Row],[Subcuenta]],[3]Gastos!$B:$B,[3]Gastos!$AZ:$AZ) -> 21460 | Q31: =_xlfn.XLOOKUP(Tabla1[[#This Row],[Subcuenta]],[3]Gastos!$B:$B,[3]Gastos!$BE:$BE) -> 12500 | R31: =_xlfn.XLOOKUP(Tabla1[[#This Row],[Subcuenta]],[3]Gastos!$B:$B,[3]Gastos!$BJ:$BJ) -> 31099.47 | S31: =SUM(Tabla1[[#This Row],[october]:[december]]) -> 65059.47 | T31: =SUM(G31,K31,O31,S31) -> 1545732.4
B32: Gastos de Operaciones | C32: Vespusio Sur | D32: =_xlfn.XLOOKUP(C32,[3]Gastos!$B:$B,[3]Gastos!$G:$G) -> 217916 | E32: =_xlfn.XLOOKUP(C32,[3]Gastos!$B:$B,[3]Gastos!$L:$L) -> 185977 | F32: =_xlfn.XLOOKUP(C32,[3]Gastos!$B:$B,[3]Gastos!$Q:$Q) -> 159569 | G32: =SUM(Tabla1[[#This Row],[january]:[march]]) -> 563462 | H32: =_xlfn.XLOOKUP(C32,[3]Gastos!$B:$B,[3]Gastos!$V:$V) -> 236348 | I32: =_xlfn.XLOOKUP(C32,[3]Gastos!$B:$B,[3]Gastos!$AA:$AA) -> 246599 | J32: =_xlfn.XLOOKUP(C32,[3]Gastos!$B:$B,[3]Gastos!$AF:$AF) -> 258803 | K32: =SUM(Tabla1[[#This Row],[april]:[june]]) -> 741750 | L32: =_xlfn.XLOOKUP(C32,[3]Gastos!$B:$B,[3]Gastos!$AK:$AK) -> 248837 | M32: =_xlfn.XLOOKUP(C32,[3]Gastos!$B:$B,[3]Gastos!$AP:$AP) -> 59887 | N32: 88110.05 | O32: =SUM(Tabla1[[#This Row],[july]:[september]]) -> 396834.05 | P32: =_xlfn.XLOOKUP(Tabla1[[#This Row],[Subcuenta]],[3]Gastos!$B:$B,[3]Gastos!$AZ:$AZ) -> 71422 | Q32: =_xlfn.XLOOKUP(Tabla1[[#This Row],[Subcuenta]],[3]Gastos!$B:$B,[3]Gastos!$BE:$BE) -> 73463 | R32: =_xlfn.XLOOKUP(Tabla1[[#This Row],[Subcuenta]],[3]Gastos!$B:$B,[3]Gastos!$BJ:$BJ) -> 55663.85 | S32: =SUM(Tabla1[[#This Row],[october]:[december]]) -> 200548.85 | T32: =SUM(G32,K32,O32,S32) -> 1902594.9
B33: Gastos de Operaciones | C33: Costanera Norte | D33: =_xlfn.XLOOKUP(C33,[3]Gastos!$B:$B,[3]Gastos!$G:$G) -> 450377 | E33: =_xlfn.XLOOKUP(C33,[3]Gastos!$B:$B,[3]Gastos!$L:$L) -> 196987 | F33: =_xlfn.XLOOKUP(C33,[3]Gastos!$B:$B,[3]Gastos!$Q:$Q) -> 200151 | G33: =SUM(Tabla1[[#This Row],[january]:[march]]) -> 847515 | H33: =_xlfn.XLOOKUP(C33,[3]Gastos!$B:$B,[3]Gastos!$V:$V) -> 204795 | I33: =_xlfn.XLOOKUP(C33,[3]Gastos!$B:$B,[3]Gastos!$AA:$AA) -> 282693 | J33: =_xlfn.XLOOKUP(C33,[3]Gastos!$B:$B,[3]Gastos!$AF:$AF) -> 214627 | K33: =SUM(Tabla1[[#This Row],[april]:[june]]) -> 702115 | L33: =_xlfn.XLOOKUP(C33,[3]Gastos!$B:$B,[3]Gastos!$AK:$AK) -> 254868 | M33: =_xlfn.XLOOKUP(C33,[3]Gastos!$B:$B,[3]Gastos!$AP:$AP) -> 112746 | N33: 274539.35 | O33: =SUM(Tabla1[[#This Row],[july]:[september]]) -> 642153.35 | P33: =_xlfn.XLOOKUP(Tabla1[[#This Row],[Subcuenta]],[3]Gastos!$B:$B,[3]Gastos!$AZ:$AZ) -> 131010 | Q33: =_xlfn.XLOOKUP(Tabla1[[#This Row],[Subcuenta]],[3]Gastos!$B:$B,[3]Gastos!$BE:$BE) -> 116448 | R33: =_xlfn.XLOOKUP(Tabla1[[#This Row],[Subcuenta]],[3]Gastos!$B:$B,[3]Gastos!$BJ:$BJ) -> 124530.04 | S33: =SUM(Tabla1[[#This Row],[october]:[december]]) -> 371988.04 | T33: =SUM(G33,K33,O33,S33) -> 2563771.4
B34: Gastos de Operaciones | C34: Ruta del Maipo | D34: =_xlfn.XLOOKUP(C34,[3]Gastos!$B:$B,[3]Gastos!$G:$G) -> 47012 | E34: =_xlfn.XLOOKUP(C34,[3]Gastos!$B:$B,[3]Gastos!$L:$L) -> 25600 | F34: =_xlfn.XLOOKUP(C34,[3]Gastos!$B:$B,[3]Gastos!$Q:$Q) -> 69800 | G34: =SUM(Tabla1[[#This Row],[january]:[march]]) -> 142412 | H34: =_xlfn.XLOOKUP(C34,[3]Gastos!$B:$B,[3]Gastos!$V:$V) -> 27668 | I34: =_xlfn.XLOOKUP(C34,[3]Gastos!$B:$B,[3]Gastos!$AA:$AA) -> 61056 | J34: =_xlfn.XLOOKUP(C34,[3]Gastos!$B:$B,[3]Gastos!$AF:$AF) -> 54929 | K34: =SUM(Tabla1[[#This Row],[april]:[june]]) -> 143653 | L34: =_xlfn.XLOOKUP(C34,[3]Gastos!$B:$B,[3]Gastos!$AK:$AK) -> 69800 | M34: =_xlfn.XLOOKUP(C34,[3]Gastos!$B:$B,[3]Gastos!$AP:$AP) -> 6200 | N34: 66000 | O34: =SUM(Tabla1[[#This Row],[july]:[september]]) -> 142000 | P34: =_xlfn.XLOOKUP(Tabla1[[#This Row],[Subcuenta]],[3]Gastos!$B:$B,[3]Gastos!$AZ:$AZ) -> 17500 | Q34: =_xlfn.XLOOKUP(Tabla1[[#This Row],[Subcuenta]],[3]Gastos!$B:$B,[3]Gastos!$BE:$BE) -> 30168 | R34: =_xlfn.XLOOKUP(Tabla1[[#This Row],[Subcuenta]],[3]Gastos!$B:$B,[3]Gastos!$BJ:$BJ) -> 0 | S34: =SUM(Tabla1[[#This Row],[october]:[december]]) -> 47668 | T34: =SUM(G34,K34,O34,S34) -> 475733
B35: Gastos de Operaciones | C35: RUTA PASS 78 | D35: =_xlfn.XLOOKUP(C35,[3]Gastos!$B:$B,[3]Gastos!$G:$G) -> 61140 | E35: =_xlfn.XLOOKUP(C35,[3]Gastos!$B:$B,[3]Gastos!$L:$L) -> 46369 | F35: =_xlfn.XLOOKUP(C35,[3]Gastos!$B:$B,[3]Gastos!$Q:$Q) -> 24800 | G35: =SUM(Tabla1[[#This Row],[january]:[march]]) -> 132309 | H35: =_xlfn.XLOOKUP(C35,[3]Gastos!$B:$B,[3]Gastos!$V:$V) -> 13500 | I35: =_xlfn.XLOOKUP(C35,[3]Gastos!$B:$B,[3]Gastos!$AA:$AA) -> 24742 | J35: =_xlfn.XLOOKUP(C35,[3]Gastos!$B:$B,[3]Gastos!$AF:$AF) -> 13600 | K35: =SUM(Tabla1[[#This Row],[april]:[june]]) -> 51842 | L35: =_xlfn.XLOOKUP(C35,[3]Gastos!$B:$B,[3]Gastos!$AK:$AK) -> 11500 | M35: =_xlfn.XLOOKUP(C35,[3]Gastos!$B:$B,[3]Gastos!$AP:$AP) -> 0 | N35: 0 | O35: =SUM(Tabla1[[#This Row],[july]:[september]]) -> 11500 | P35: =_xlfn.XLOOKUP(Tabla1[[#This Row],[Subcuenta]],[3]Gastos!$B:$B,[3]Gastos!$AZ:$AZ) -> 1400 | Q35: =_xlfn.XLOOKUP(Tabla1[[#This Row],[Subcuenta]],[3]Gastos!$B:$B,[3]Gastos!$BE:$BE) -> 9000 | R35: =_xlfn.XLOOKUP(Tabla1[[#This Row],[Subcuenta]],[3]Gastos!$B:$B,[3]Gastos!$BJ:$BJ) -> 1600 | S35: =SUM(Tabla1[[#This Row],[october]:[december]]) -> 12000 | T35: =SUM(G35,K35,O35,S35) -> 207651
B36: Gastos de Operaciones | C36: VESPUCIO ORIENTE | D36: =_xlfn.XLOOKUP(C36,[3]Gastos!$B:$B,[3]Gastos!$G:$G) -> 67611 | E36: =_xlfn.XLOOKUP(C36,[3]Gastos!$B:$B,[3]Gastos!$L:$L) -> 134522 | F36: =_xlfn.XLOOKUP(C36,[3]Gastos!$B:$B,[3]Gastos!$Q:$Q) -> 58493 | G36: =SUM(Tabla1[[#This Row],[january]:[march]]) -> 260626 | H36: =_xlfn.XLOOKUP(C36,[3]Gastos!$B:$B,[3]Gastos!$V:$V) -> 80196 | I36: =_xlfn.XLOOKUP(C36,[3]Gastos!$B:$B,[3]Gastos!$AA:$AA) -> 80389 | J36: =_xlfn.XLOOKUP(C36,[3]Gastos!$B:$B,[3]Gastos!$AF:$AF) -> 77680 | K36: =SUM(Tabla1[[#This Row],[april]:[june]]) -> 238265 | L36: =_xlfn.XLOOKUP(C36,[3]Gastos!$B:$B,[3]Gastos!$AK:$AK) -> 65731 | M36: =_xlfn.XLOOKUP(C36,[3]Gastos!$B:$B,[3]Gastos!$AP:$AP) -> 43858 | N36: 59142 | O36: =SUM(Tabla1[[#This Row],[july]:[september]]) -> 168731 | P36: =_xlfn.XLOOKUP(Tabla1[[#This Row],[Subcuenta]],[3]Gastos!$B:$B,[3]Gastos!$AZ:$AZ) -> 19836 | Q36: =_xlfn.XLOOKUP(Tabla1[[#This Row],[Subcuenta]],[3]Gastos!$B:$B,[3]Gastos!$BE:$BE) -> 32687 | R36: =_xlfn.XLOOKUP(Tabla1[[#This Row],[Subcuenta]],[3]Gastos!$B:$B,[3]Gastos!$BJ:$BJ) -> 45351 | S36: =SUM(Tabla1[[#This Row],[october]:[december]]) -> 97874 | T36: =SUM(G36,K36,O36,S36) -> 765496
B37: Gastos de Operaciones | C37: GLOBALBVIA / AUTOPISTA DEL ACONCAGUA | D37: =_xlfn.XLOOKUP(C37,[3]Gastos!$B:$B,[3]Gastos!$G:$G) -> 62407 | E37: =_xlfn.XLOOKUP(C37,[3]Gastos!$B:$B,[3]Gastos!$L:$L) -> 37192 | F37: =_xlfn.XLOOKUP(C37,[3]Gastos!$B:$B,[3]Gastos!$Q:$Q) -> 41677 | G37: =SUM(Tabla1[[#This Row],[january]:[march]]) -> 141276 | H37: =_xlfn.XLOOKUP(C37,[3]Gastos!$B:$B,[3]Gastos!$V:$V) -> 43316 | I37: =_xlfn.XLOOKUP(C37,[3]Gastos!$B:$B,[3]Gastos!$AA:$AA) -> 52974 | J37: =_xlfn.XLOOKUP(C37,[3]Gastos!$B:$B,[3]Gastos!$AF:$AF) -> 42934 | K37: =SUM(Tabla1[[#This Row],[april]:[june]]) -> 139224 | L37: =_xlfn.XLOOKUP(C37,[3]Gastos!$B:$B,[3]Gastos!$AK:$AK) -> 65649 | M37: =_xlfn.XLOOKUP(C37,[3]Gastos!$B:$B,[3]Gastos!$AP:$AP) -> 0 | N37: 9290 | O37: =SUM(Tabla1[[#This Row],[july]:[september]]) -> 74939 | P37: =_xlfn.XLOOKUP(Tabla1[[#This Row],[Subcuenta]],[3]Gastos!$B:$B,[3]Gastos!$AZ:$AZ) -> 3450 | Q37: =_xlfn.XLOOKUP(Tabla1[[#This Row],[Subcuenta]],[3]Gastos!$B:$B,[3]Gastos!$BE:$BE) -> 0 | R37: =_xlfn.XLOOKUP(Tabla1[[#This Row],[Subcuenta]],[3]Gastos!$B:$B,[3]Gastos!$BJ:$BJ) -> 3410 | S37: =SUM(Tabla1[[#This Row],[october]:[december]]) -> 6860 | T37: =SUM(G37,K37,O37,S37) -> 362299
B38: Gastos de Operaciones | C38: RUTA 5 TALCA-CHILLAN | D38: =_xlfn.XLOOKUP(C38,[3]Gastos!$B:$B,[3]Gastos!$G:$G) -> 0 | E38: =_xlfn.XLOOKUP(C38,[3]Gastos!$B:$B,[3]Gastos!$L:$L) -> 16800 | F38: =_xlfn.XLOOKUP(C38,[3]Gastos!$B:$B,[3]Gastos!$Q:$Q) -> 23626 | G38: =SUM(Tabla1[[#This Row],[january]:[march]]) -> 40426 | H38: =_xlfn.XLOOKUP(C38,[3]Gastos!$B:$B,[3]Gastos!$V:$V) -> 0 | I38: =_xlfn.XLOOKUP(C38,[3]Gastos!$B:$B,[3]Gastos!$AA:$AA) -> 20800 | J38: =_xlfn.XLOOKUP(C38,[3]Gastos!$B:$B,[3]Gastos!$AF:$AF) -> 0 | K38: =SUM(Tabla1[[#This Row],[april]:[june]]) -> 20800 | L38: =_xlfn.XLOOKUP(C38,[3]Gastos!$B:$B,[3]Gastos!$AK:$AK) -> 0 | M38: =_xlfn.XLOOKUP(C38,[3]Gastos!$B:$B,[3]Gastos!$AP:$AP) -> 22400 | N38: 16800 | O38: =SUM(Tabla1[[#This Row],[july]:[september]]) -> 39200 | P38: =_xlfn.XLOOKUP(Tabla1[[#This Row],[Subcuenta]],[3]Gastos!$B:$B,[3]Gastos!$AZ:$AZ) -> 5600 | Q38: =_xlfn.XLOOKUP(Tabla1[[#This Row],[Subcuenta]],[3]Gastos!$B:$B,[3]Gastos!$BE:$BE) -> 11200 | R38: =_xlfn.XLOOKUP(Tabla1[[#This Row],[Subcuenta]],[3]Gastos!$B:$B,[3]Gastos!$BJ:$BJ) -> 0 | S38: =SUM(Tabla1[[#This Row],[october]:[december]]) -> 16800 | T38: =SUM(G38,K38,O38,S38) -> 117226
B39: Gastos de Operaciones | C39: CHILEXPRESS | D39: =_xlfn.XLOOKUP(C39,[3]Gastos!$B:$B,[3]Gastos!$G:$G) -> 2467196 | E39: =_xlfn.XLOOKUP(C39,[3]Gastos!$B:$B,[3]Gastos!$L:$L) -> 2036650 | F39: =_xlfn.XLOOKUP(C39,[3]Gastos!$B:$B,[3]Gastos!$Q:$Q) -> 1604125 | G39: =SUM(Tabla1[[#This Row],[january]:[march]]) -> 6107971 | H39: =_xlfn.XLOOKUP(C39,[3]Gastos!$B:$B,[3]Gastos!$V:$V) -> 1927155 | I39: =_xlfn.XLOOKUP(C39,[3]Gastos!$B:$B,[3]Gastos!$AA:$AA) -> 2091559 | J39: =_xlfn.XLOOKUP(C39,[3]Gastos!$B:$B,[3]Gastos!$AF:$AF) -> 2611777 | K39: =SUM(Tabla1[[#This Row],[april]:[june]]) -> 6630491 | L39: =_xlfn.XLOOKUP(C39,[3]Gastos!$B:$B,[3]Gastos!$AK:$AK) -> 1955798 | M39: =_xlfn.XLOOKUP(C39,[3]Gastos!$B:$B,[3]Gastos!$AP:$AP) -> 2020668 | N39: 2147835 | O39: =SUM(Tabla1[[#This Row],[july]:[september]]) -> 6124301 | P39: =_xlfn.XLOOKUP(Tabla1[[#This Row],[Subcuenta]],[3]Gastos!$B:$B,[3]Gastos!$AZ:$AZ) -> 2274248 | Q39: =_xlfn.XLOOKUP(Tabla1[[#This Row],[Subcuenta]],[3]Gastos!$B:$B,[3]Gastos!$BE:$BE) -> 2164142 | R39: =_xlfn.XLOOKUP(Tabla1[[#This Row],[Subcuenta]],[3]Gastos!$B:$B,[3]Gastos!$BJ:$BJ) -> 2356586 | S39: =SUM(Tabla1[[#This Row],[october]:[december]]) -> 6794976 | T39: =SUM(G39,K39,O39,S39) -> 25657739
B40: Gastos de Operaciones | C40: NOTARIA | D40: =_xlfn.XLOOKUP(C40,[3]Gastos!$B:$B,[3]Gastos!$G:$G) -> 556000 | E40: =_xlfn.XLOOKUP(C40,[3]Gastos!$B:$B,[3]Gastos!$L:$L) -> 80000 | F40: =_xlfn.XLOOKUP(C40,[3]Gastos!$B:$B,[3]Gastos!$Q:$Q) -> 20000 | G40: =SUM(Tabla1[[#This Row],[january]:[march]]) -> 656000 | H40: =_xlfn.XLOOKUP(C40,[3]Gastos!$B:$B,[3]Gastos!$V:$V) -> 520000 | I40: =_xlfn.XLOOKUP(C40,[3]Gastos!$B:$B,[3]Gastos!$AA:$AA) -> 30000 | J40: =_xlfn.XLOOKUP(C40,[3]Gastos!$B:$B,[3]Gastos!$AF:$AF) -> 10000 | K40: =SUM(Tabla1[[#This Row],[april]:[june]]) -> 560000 | L40: =_xlfn.XLOOKUP(C40,[3]Gastos!$B:$B,[3]Gastos!$AK:$AK) -> 20000 | M40: =_xlfn.XLOOKUP(C40,[3]Gastos!$B:$B,[3]Gastos!$AP:$AP) -> 417000 | N40: 179400 | O40: =SUM(Tabla1[[#This Row],[july]:[september]]) -> 616400 | P40: =_xlfn.XLOOKUP(Tabla1[[#This Row],[Subcuenta]],[3]Gastos!$B:$B,[3]Gastos!$AZ:$AZ) -> 440000 | Q40: =_xlfn.XLOOKUP(Tabla1[[#This Row],[Subcuenta]],[3]Gastos!$B:$B,[3]Gastos!$BE:$BE) -> 611000 | R40: =_xlfn.XLOOKUP(Tabla1[[#This Row],[Subcuenta]],[3]Gastos!$B:$B,[3]Gastos!$BJ:$BJ) -> 1042000 | S40: =SUM(Tabla1[[#This Row],[october]:[december]]) -> 2093000 | T40: =SUM(G40,K40,O40,S40) -> 3925400
B41: Gastos de Operaciones | C41: GASTOS FURGON | D41: =_xlfn.XLOOKUP(C41,[3]Gastos!$B:$B,[3]Gastos!$G:$G) -> 112000 | E41: =_xlfn.XLOOKUP(C41,[3]Gastos!$B:$B,[3]Gastos!$L:$L) -> 250000 | F41: =_xlfn.XLOOKUP(C41,[3]Gastos!$B:$B,[3]Gastos!$Q:$Q) -> 310000 | G41: =SUM(Tabla1[[#This Row],[january]:[march]]) -> 672000 | H41: =_xlfn.XLOOKUP(C41,[3]Gastos!$B:$B,[3]Gastos!$V:$V) -> 150000 | I41: =_xlfn.XLOOKUP(C41,[3]Gastos!$B:$B,[3]Gastos!$AA:$AA) -> 100000 | J41: =_xlfn.XLOOKUP(C41,[3]Gastos!$B:$B,[3]Gastos!$AF:$AF) -> 0 | K41: =SUM(Tabla1[[#This Row],[april]:[june]]) -> 250000 | L41: =_xlfn.XLOOKUP(C41,[3]Gastos!$B:$B,[3]Gastos!$AK:$AK) -> 0 | M41: =_xlfn.XLOOKUP(C41,[3]Gastos!$B:$B,[3]Gastos!$AP:$AP) -> 0 | N41: 100000 | O41: =SUM(Tabla1[[#This Row],[july]:[september]]) -> 100000 | P41: =_xlfn.XLOOKUP(Tabla1[[#This Row],[Subcuenta]],[3]Gastos!$B:$B,[3]Gastos!$AZ:$AZ) -> 0 | Q41: =_xlfn.XLOOKUP(Tabla1[[#This Row],[Subcuenta]],[3]Gastos!$B:$B,[3]Gastos!$BE:$BE) -> 0 | R41: =_xlfn.XLOOKUP(Tabla1[[#This Row],[Subcuenta]],[3]Gastos!$B:$B,[3]Gastos!$BJ:$BJ) -> 0 | S41: =SUM(Tabla1[[#This Row],[october]:[december]]) -> 0 | T41: =SUM(G41,K41,O41,S41) -> 1022000
B42: Gastos de Operaciones | C42: CAMARA CHILENO NORTEAMERICANA DE COMERCIO / PATENTE MUNICIPAL | D42: =_xlfn.XLOOKUP(C42,[3]Gastos!$B:$B,[3]Gastos!$G:$G) -> 0 | E42: =_xlfn.XLOOKUP(C42,[3]Gastos!$B:$B,[3]Gastos!$L:$L) -> 0 | F42: =_xlfn.XLOOKUP(C42,[3]Gastos!$B:$B,[3]Gastos!$Q:$Q) -> 0 | G42: =SUM(Tabla1[[#This Row],[january]:[march]]) -> 0 | H42: =_xlfn.XLOOKUP(C42,[3]Gastos!$B:$B,[3]Gastos!$V:$V) -> 0 | I42: =_xlfn.XLOOKUP(C42,[3]Gastos!$B:$B,[3]Gastos!$AA:$AA) -> 0 | J42: =_xlfn.XLOOKUP(C42,[3]Gastos!$B:$B,[3]Gastos!$AF:$AF) -> 0 | K42: =SUM(Tabla1[[#This Row],[april]:[june]]) -> 0 | L42: =_xlfn.XLOOKUP(C42,[3]Gastos!$B:$B,[3]Gastos!$AK:$AK) -> 0 | M42: =_xlfn.XLOOKUP(C42,[3]Gastos!$B:$B,[3]Gastos!$AP:$AP) -> 0 | O42: =SUM(Tabla1[[#This Row],[july]:[september]]) -> 0 | P42: =_xlfn.XLOOKUP(Tabla1[[#This Row],[Subcuenta]],[3]Gastos!$B:$B,[3]Gastos!$AZ:$AZ) -> 0 | Q42: =_xlfn.XLOOKUP(Tabla1[[#This Row],[Subcuenta]],[3]Gastos!$B:$B,[3]Gastos!$BE:$BE) -> 0 | R42: =_xlfn.XLOOKUP(Tabla1[[#This Row],[Subcuenta]],[3]Gastos!$B:$B,[3]Gastos!$BJ:$BJ) -> 805913 | S42: =SUM(Tabla1[[#This Row],[october]:[december]]) -> 805913 | T42: =SUM(G42,K42,O42,S42) -> 805913
B43: Gastos de Operaciones | C43: ASESORIAS LEGALES C | D43: =_xlfn.XLOOKUP(C43,[3]Gastos!$B:$B,[3]Gastos!$G:$G) -> 0 | E43: =_xlfn.XLOOKUP(C43,[3]Gastos!$B:$B,[3]Gastos!$L:$L) -> 0 | F43: =_xlfn.XLOOKUP(C43,[3]Gastos!$B:$B,[3]Gastos!$Q:$Q) -> 0 | G43: =SUM(Tabla1[[#This Row],[january]:[march]]) -> 0 | H43: =_xlfn.XLOOKUP(C43,[3]Gastos!$B:$B,[3]Gastos!$V:$V) -> 0 | I43: =_xlfn.XLOOKUP(C43,[3]Gastos!$B:$B,[3]Gastos!$AA:$AA) -> 0 | J43: =_xlfn.XLOOKUP(C43,[3]Gastos!$B:$B,[3]Gastos!$AF:$AF) -> 0 | K43: =SUM(Tabla1[[#This Row],[april]:[june]]) -> 0 | L43: =_xlfn.XLOOKUP(C43,[3]Gastos!$B:$B,[3]Gastos!$AK:$AK) -> 1442152 | M43: =_xlfn.XLOOKUP(C43,[3]Gastos!$B:$B,[3]Gastos!$AP:$AP) -> 0 | O43: =SUM(Tabla1[[#This Row],[july]:[september]]) -> 1442152 | P43: =_xlfn.XLOOKUP(Tabla1[[#This Row],[Subcuenta]],[3]Gastos!$B:$B,[3]Gastos!$AZ:$AZ) -> 0 | Q43: =_xlfn.XLOOKUP(Tabla1[[#This Row],[Subcuenta]],[3]Gastos!$B:$B,[3]Gastos!$BE:$BE) -> 0 | R43: =_xlfn.XLOOKUP(Tabla1[[#This Row],[Subcuenta]],[3]Gastos!$B:$B,[3]Gastos!$BJ:$BJ) -> 0 | S43: =SUM(Tabla1[[#This Row],[october]:[december]]) -> 0 | T43: =SUM(G43,K43,O43,S43) -> 1442152
B44: Gastos de Operaciones | C44: FLETES- AYUDANTES EXTERNOS- BONIFICACIONES- TAXI | D44: =_xlfn.XLOOKUP(C44,[3]Gastos!$B:$B,[3]Gastos!$G:$G) -> 0 | E44: =_xlfn.XLOOKUP(C44,[3]Gastos!$B:$B,[3]Gastos!$L:$L) -> 321839 | F44: =_xlfn.XLOOKUP(C44,[3]Gastos!$B:$B,[3]Gastos!$Q:$Q) -> 0 | G44: =SUM(Tabla1[[#This Row],[january]:[march]]) -> 321839 | H44: =_xlfn.XLOOKUP(C44,[3]Gastos!$B:$B,[3]Gastos!$V:$V) -> 0 | I44: =_xlfn.XLOOKUP(C44,[3]Gastos!$B:$B,[3]Gastos!$AA:$AA) -> 148000 | J44: =_xlfn.XLOOKUP(C44,[3]Gastos!$B:$B,[3]Gastos!$AF:$AF) -> 2177234 | K44: =SUM(Tabla1[[#This Row],[april]:[june]]) -> 2325234 | L44: =_xlfn.XLOOKUP(C44,[3]Gastos!$B:$B,[3]Gastos!$AK:$AK) -> 448277 | M44: =_xlfn.XLOOKUP(C44,[3]Gastos!$B:$B,[3]Gastos!$AP:$AP) -> 34483 | O44: =SUM(Tabla1[[#This Row],[july]:[september]]) -> 482760 | P44: =_xlfn.XLOOKUP(Tabla1[[#This Row],[Subcuenta]],[3]Gastos!$B:$B,[3]Gastos!$AZ:$AZ) -> 0 | Q44: =_xlfn.XLOOKUP(Tabla1[[#This Row],[Subcuenta]],[3]Gastos!$B:$B,[3]Gastos!$BE:$BE) -> 0 | R44: =_xlfn.XLOOKUP(Tabla1[[#This Row],[Subcuenta]],[3]Gastos!$B:$B,[3]Gastos!$BJ:$BJ) -> 30000 | S44: =SUM(Tabla1[[#This Row],[october]:[december]]) -> 30000 | T44: =SUM(G44,K44,O44,S44) -> 3159833
B45: Gastos de Operaciones | C45: JOSE TOMAS CASTRO | D45: =_xlfn.XLOOKUP(C45,[3]Gastos!$B:$B,[3]Gastos!$G:$G) -> 4234500 | E45: =_xlfn.XLOOKUP(C45,[3]Gastos!$B:$B,[3]Gastos!$L:$L) -> 4261162 | F45: =_xlfn.XLOOKUP(C45,[3]Gastos!$B:$B,[3]Gastos!$Q:$Q) -> 4269196 | G45: =SUM(Tabla1[[#This Row],[january]:[march]]) -> 12764858 | H45: =_xlfn.XLOOKUP(C45,[3]Gastos!$B:$B,[3]Gastos!$V:$V) -> 5727899 | I45: =_xlfn.XLOOKUP(C45,[3]Gastos!$B:$B,[3]Gastos!$AA:$AA) -> 5764149 | J45: =_xlfn.XLOOKUP(C45,[3]Gastos!$B:$B,[3]Gastos!$AF:$AF) -> 5774125 | K45: =SUM(Tabla1[[#This Row],[april]:[june]]) -> 17266173 | L45: =_xlfn.XLOOKUP(C45,[3]Gastos!$B:$B,[3]Gastos!$AK:$AK) -> 5769338 | M45: =_xlfn.XLOOKUP(C45,[3]Gastos!$B:$B,[3]Gastos!$AP:$AP) -> 5780106 | N45: 5791026 | O45: =SUM(Tabla1[[#This Row],[july]:[september]]) -> 17340470 | P45: =_xlfn.XLOOKUP(Tabla1[[#This Row],[Subcuenta]],[3]Gastos!$B:$B,[3]Gastos!$AZ:$AZ) -> 5820780 | Q45: =_xlfn.XLOOKUP(Tabla1[[#This Row],[Subcuenta]],[3]Gastos!$B:$B,[3]Gastos!$BE:$BE) -> 5849442 | R45: =_xlfn.XLOOKUP(Tabla1[[#This Row],[Subcuenta]],[3]Gastos!$B:$B,[3]Gastos!$BJ:$BJ) -> 6107326 | S45: =SUM(Tabla1[[#This Row],[october]:[december]]) -> 17777548 | T45: =SUM(G45,K45,O45,S45) -> 65149049
B46: Gastos de Operaciones | C46: DESCUENTOS / BONIFICACIONES DOCTORES | D46: =_xlfn.XLOOKUP(C46,[3]Gastos!$B:$B,[3]Gastos!$G:$G) -> 0 | E46: =_xlfn.XLOOKUP(C46,[3]Gastos!$B:$B,[3]Gastos!$L:$L) -> 0 | F46: =_xlfn.XLOOKUP(C46,[3]Gastos!$B:$B,[3]Gastos!$Q:$Q) -> 0 | G46: =SUM(Tabla1[[#This Row],[january]:[march]]) -> 0 | H46: =_xlfn.XLOOKUP(C46,[3]Gastos!$B:$B,[3]Gastos!$V:$V) -> 0 | I46: =_xlfn.XLOOKUP(C46,[3]Gastos!$B:$B,[3]Gastos!$AA:$AA) -> 0 | J46: =_xlfn.XLOOKUP(C46,[3]Gastos!$B:$B,[3]Gastos!$AF:$AF) -> 0 | K46: =SUM(Tabla1[[#This Row],[april]:[june]]) -> 0 | L46: =_xlfn.XLOOKUP(C46,[3]Gastos!$B:$B,[3]Gastos!$AK:$AK) -> 2180887 | M46: =_xlfn.XLOOKUP(C46,[3]Gastos!$B:$B,[3]Gastos!$AP:$AP) -> 0 | O46: =SUM(Tabla1[[#This Row],[july]:[september]]) -> 2180887 | P46: =_xlfn.XLOOKUP(Tabla1[[#This Row],[Subcuenta]],[3]Gastos!$B:$B,[3]Gastos!$AZ:$AZ) -> 0 | Q46: =_xlfn.XLOOKUP(Tabla1[[#This Row],[Subcuenta]],[3]Gastos!$B:$B,[3]Gastos!$BE:$BE) -> 0 | R46: =_xlfn.XLOOKUP(Tabla1[[#This Row],[Subcuenta]],[3]Gastos!$B:$B,[3]Gastos!$BJ:$BJ) -> 0 | S46: =SUM(Tabla1[[#This Row],[october]:[december]]) -> 0 | T46: =SUM(G46,K46,O46,S46) -> 2180887
B47: Gastos de Operaciones | C47: BARONI CONSULTORES | D47: =_xlfn.XLOOKUP(C47,[3]Gastos!$B:$B,[3]Gastos!$G:$G) -> 0 | E47: =_xlfn.XLOOKUP(C47,[3]Gastos!$B:$B,[3]Gastos!$L:$L) -> 0 | F47: =_xlfn.XLOOKUP(C47,[3]Gastos!$B:$B,[3]Gastos!$Q:$Q) -> 0 | G47: =SUM(Tabla1[[#This Row],[january]:[march]]) -> 0 | H47: =_xlfn.XLOOKUP(C47,[3]Gastos!$B:$B,[3]Gastos!$V:$V) -> 0 | I47: =_xlfn.XLOOKUP(C47,[3]Gastos!$B:$B,[3]Gastos!$AA:$AA) -> 0 | J47: =_xlfn.XLOOKUP(C47,[3]Gastos!$B:$B,[3]Gastos!$AF:$AF) -> 0 | K47: =SUM(Tabla1[[#This Row],[april]:[june]]) -> 0 | L47: =_xlfn.XLOOKUP(C47,[3]Gastos!$B:$B,[3]Gastos!$AK:$AK) -> 0 | M47: =_xlfn.XLOOKUP(C47,[3]Gastos!$B:$B,[3]Gastos!$AP:$AP) -> 0 | O47: =SUM(Tabla1[[#This Row],[july]:[september]]) -> 0 | P47: =_xlfn.XLOOKUP(Tabla1[[#This Row],[Subcuenta]],[3]Gastos!$B:$B,[3]Gastos!$AZ:$AZ) -> 0 | Q47: =_xlfn.XLOOKUP(Tabla1[[#This Row],[Subcuenta]],[3]Gastos!$B:$B,[3]Gastos!$BE:$BE) -> 0 | R47: =_xlfn.XLOOKUP(Tabla1[[#This Row],[Subcuenta]],[3]Gastos!$B:$B,[3]Gastos!$BJ:$BJ) -> 0 | S47: =SUM(Tabla1[[#This Row],[october]:[december]]) -> 0 | T47: =SUM(G47,K47,O47,S47) -> 0
B48: Gastos de Operaciones | C48: POLIZAS DE SEGURO HDI VEHICULOS | D48: =_xlfn.XLOOKUP(C48,[3]Gastos!$B:$B,[3]Gastos!$G:$G) -> 474000 | E48: =_xlfn.XLOOKUP(C48,[3]Gastos!$B:$B,[3]Gastos!$L:$L) -> 475172 | F48: =_xlfn.XLOOKUP(C48,[3]Gastos!$B:$B,[3]Gastos!$Q:$Q) -> 478369 | G48: =SUM(Tabla1[[#This Row],[january]:[march]]) -> 1427541 | H48: =_xlfn.XLOOKUP(C48,[3]Gastos!$B:$B,[3]Gastos!$V:$V) -> 478754 | I48: =_xlfn.XLOOKUP(C48,[3]Gastos!$B:$B,[3]Gastos!$AA:$AA) -> 483267 | J48: =_xlfn.XLOOKUP(C48,[3]Gastos!$B:$B,[3]Gastos!$AF:$AF) -> 485097 | K48: =SUM(Tabla1[[#This Row],[april]:[june]]) -> 1447118 | L48: =_xlfn.XLOOKUP(C48,[3]Gastos!$B:$B,[3]Gastos!$AK:$AK) -> 336754 | M48: =_xlfn.XLOOKUP(C48,[3]Gastos!$B:$B,[3]Gastos!$AP:$AP) -> 0 | N48: 149295 | O48: =SUM(Tabla1[[#This Row],[july]:[september]]) -> 486049 | P48: =_xlfn.XLOOKUP(Tabla1[[#This Row],[Subcuenta]],[3]Gastos!$B:$B,[3]Gastos!$AZ:$AZ) -> 2041766 | Q48: =_xlfn.XLOOKUP(Tabla1[[#This Row],[Subcuenta]],[3]Gastos!$B:$B,[3]Gastos!$BE:$BE) -> 493360 | R48: =_xlfn.XLOOKUP(Tabla1[[#This Row],[Subcuenta]],[3]Gastos!$B:$B,[3]Gastos!$BJ:$BJ) -> 495304 | S48: =SUM(Tabla1[[#This Row],[october]:[december]]) -> 3030430 | T48: =SUM(G48,K48,O48,S48) -> 6391138
B49: Gastos de Operaciones | C49: Maletas Iteros | K49: =SUM(Tabla1[[#This Row],[april]:[june]]) -> 0 | M49: =_xlfn.XLOOKUP(C49,[3]Gastos!$B:$B,[3]Gastos!$AP:$AP) -> 5807394 | O49: =SUM(Tabla1[[#This Row],[july]:[september]]) -> 5807394 | P49: =_xlfn.XLOOKUP(Tabla1[[#This Row],[Subcuenta]],[3]Gastos!$B:$B,[3]Gastos!$AZ:$AZ) -> 2819419 | Q49: =_xlfn.XLOOKUP(Tabla1[[#This Row],[Subcuenta]],[3]Gastos!$B:$B,[3]Gastos!$BE:$BE) -> 0 | R49: =_xlfn.XLOOKUP(Tabla1[[#This Row],[Subcuenta]],[3]Gastos!$B:$B,[3]Gastos!$BJ:$BJ) -> 0 | S49: =SUM(Tabla1[[#This Row],[october]:[december]]) -> 2819419 | T49: =SUM(G49,K49,O49,S49) -> 8626813
B50: Gastos de Operaciones | C50: Gastos operacionales de Rendiciones | D50: =_xlfn.XLOOKUP(C50,[3]Gastos!$B:$B,[3]Gastos!$G:$G) -> 1007199 | E50: =_xlfn.XLOOKUP(C50,[3]Gastos!$B:$B,[3]Gastos!$L:$L) -> 1777683 | F50: =_xlfn.XLOOKUP(C50,[3]Gastos!$B:$B,[3]Gastos!$Q:$Q) -> 3108359 | G50: =SUM(Tabla1[[#This Row],[january]:[march]]) -> 5893241 | H50: =_xlfn.XLOOKUP(C50,[3]Gastos!$B:$B,[3]Gastos!$V:$V) -> 1228574 | I50: =_xlfn.XLOOKUP(C50,[3]Gastos!$B:$B,[3]Gastos!$AA:$AA) -> 2251134 | J50: =_xlfn.XLOOKUP(C50,[3]Gastos!$B:$B,[3]Gastos!$AF:$AF) -> 1328718 | K50: =SUM(Tabla1[[#This Row],[april]:[june]]) -> 4808426 | L50: =_xlfn.XLOOKUP(C50,[3]Gastos!$B:$B,[3]Gastos!$AK:$AK) -> 797337 | M50: =_xlfn.XLOOKUP(C50,[3]Gastos!$B:$B,[3]Gastos!$AP:$AP) -> 2591441.6 | N50: 1909376.3 | O50: =SUM(Tabla1[[#This Row],[july]:[september]]) -> 5298155 | P50: =_xlfn.XLOOKUP(Tabla1[[#This Row],[Subcuenta]],[3]Gastos!$B:$B,[3]Gastos!$AZ:$AZ) -> 1342243 | Q50: =_xlfn.XLOOKUP(Tabla1[[#This Row],[Subcuenta]],[3]Gastos!$B:$B,[3]Gastos!$BE:$BE) -> 1588924 | R50: =_xlfn.XLOOKUP(Tabla1[[#This Row],[Subcuenta]],[3]Gastos!$B:$B,[3]Gastos!$BJ:$BJ) -> 1164647 | S50: =SUM(Tabla1[[#This Row],[october]:[december]]) -> 4095814 | T50: =SUM(G50,K50,O50,S50) -> 20095636 | U50: =SUM(#REF!) -> #REF!
B51: Siga Sonriendo | C51: Gastos Clinica 1307 | D51: =_xlfn.XLOOKUP(C51,[3]Gastos!$B:$B,[3]Gastos!$G:$G) -> 0 | E51: =_xlfn.XLOOKUP(C51,[3]Gastos!$B:$B,[3]Gastos!$L:$L) -> 0 | F51: =_xlfn.XLOOKUP(C51,[3]Gastos!$B:$B,[3]Gastos!$Q:$Q) -> 0 | G51: =SUM(Tabla1[[#This Row],[january]:[march]]) -> 0 | H51: =_xlfn.XLOOKUP(C51,[3]Gastos!$B:$B,[3]Gastos!$V:$V) -> 71400 | I51: =_xlfn.XLOOKUP(C51,[3]Gastos!$B:$B,[3]Gastos!$AA:$AA) -> 0 | J51: =_xlfn.XLOOKUP(C51,[3]Gastos!$B:$B,[3]Gastos!$AF:$AF) -> 0 | K51: =SUM(Tabla1[[#This Row],[april]:[june]]) -> 71400 | L51: =_xlfn.XLOOKUP(C51,[3]Gastos!$B:$B,[3]Gastos!$AK:$AK) -> 0 | M51: =_xlfn.XLOOKUP(C51,[3]Gastos!$B:$B,[3]Gastos!$AP:$AP) -> 0 | O51: =SUM(Tabla1[[#This Row],[july]:[september]]) -> 0 | P51: =_xlfn.XLOOKUP(Tabla1[[#This Row],[Subcuenta]],[3]Gastos!$B:$B,[3]Gastos!$AZ:$AZ) -> 0 | Q51: =_xlfn.XLOOKUP(Tabla1[[#This Row],[Subcuenta]],[3]Gastos!$B:$B,[3]Gastos!$BE:$BE) -> 0 | R51: =_xlfn.XLOOKUP(Tabla1[[#This Row],[Subcuenta]],[3]Gastos!$B:$B,[3]Gastos!$BJ:$BJ) -> 0 | S51: =SUM(Tabla1[[#This Row],[october]:[december]]) -> 0 | T51: =SUM(G51,K51,O51,S51) -> 71400
B52: Siga Sonriendo | C52: Consultorio 115 EGAÑA - Arriendo / Gasto Comun / GTD MANQUEHUE | D52: =_xlfn.XLOOKUP(C52,[3]Gastos!$B:$B,[3]Gastos!$G:$G) -> 2405332 | E52: =_xlfn.XLOOKUP(C52,[3]Gastos!$B:$B,[3]Gastos!$L:$L) -> 323404 | F52: =_xlfn.XLOOKUP(C52,[3]Gastos!$B:$B,[3]Gastos!$Q:$Q) -> 40143 | G52: =SUM(Tabla1[[#This Row],[january]:[march]]) -> 2768879 | H52: =_xlfn.XLOOKUP(C52,[3]Gastos!$B:$B,[3]Gastos!$V:$V) -> 29838 | I52: =_xlfn.XLOOKUP(C52,[3]Gastos!$B:$B,[3]Gastos!$AA:$AA) -> 0 | J52: =_xlfn.XLOOKUP(C52,[3]Gastos!$B:$B,[3]Gastos!$AF:$AF) -> 0 | K52: =SUM(Tabla1[[#This Row],[april]:[june]]) -> 29838 | L52: =_xlfn.XLOOKUP(C52,[3]Gastos!$B:$B,[3]Gastos!$AK:$AK) -> 0 | M52: =_xlfn.XLOOKUP(C52,[3]Gastos!$B:$B,[3]Gastos!$AP:$AP) -> 0 | O52: =SUM(Tabla1[[#This Row],[july]:[september]]) -> 0 | P52: =_xlfn.XLOOKUP(Tabla1[[#This Row],[Subcuenta]],[3]Gastos!$B:$B,[3]Gastos!$AZ:$AZ) -> 0 | Q52: =_xlfn.XLOOKUP(Tabla1[[#This Row],[Subcuenta]],[3]Gastos!$B:$B,[3]Gastos!$BE:$BE) -> 0 | R52: =_xlfn.XLOOKUP(Tabla1[[#This Row],[Subcuenta]],[3]Gastos!$B:$B,[3]Gastos!$BJ:$BJ) -> 0 | S52: =SUM(Tabla1[[#This Row],[october]:[december]]) -> 0 | T52: =SUM(G52,K52,O52,S52) -> 2798717
B53: Siga Sonriendo | C53: Consultorio 115 EGAÑA - AGUAS ANDINAS / ENEL / VERISURE | D53: =_xlfn.XLOOKUP(C53,[3]Gastos!$B:$B,[3]Gastos!$G:$G) -> 64448 | E53: =_xlfn.XLOOKUP(C53,[3]Gastos!$B:$B,[3]Gastos!$L:$L) -> 61406 | F53: =_xlfn.XLOOKUP(C53,[3]Gastos!$B:$B,[3]Gastos!$Q:$Q) -> 50722 | G53: =SUM(Tabla1[[#This Row],[january]:[march]]) -> 176576 | H53: =_xlfn.XLOOKUP(C53,[3]Gastos!$B:$B,[3]Gastos!$V:$V) -> 50800 | I53: =_xlfn.XLOOKUP(C53,[3]Gastos!$B:$B,[3]Gastos!$AA:$AA) -> 51196 | J53: =_xlfn.XLOOKUP(C53,[3]Gastos!$B:$B,[3]Gastos!$AF:$AF) -> 51460 | K53: =SUM(Tabla1[[#This Row],[april]:[june]]) -> 153456 | L53: =_xlfn.XLOOKUP(C53,[3]Gastos!$B:$B,[3]Gastos!$AK:$AK) -> 0 | M53: =_xlfn.XLOOKUP(C53,[3]Gastos!$B:$B,[3]Gastos!$AP:$AP) -> 0 | O53: =SUM(Tabla1[[#This Row],[july]:[september]]) -> 0 | P53: 51692 | Q53: 51974 | R53: =_xlfn.XLOOKUP(Tabla1[[#This Row],[Subcuenta]],[3]Gastos!$B:$B,[3]Gastos!$BJ:$BJ) -> 52220 | S53: =SUM(Tabla1[[#This Row],[october]:[december]]) -> 155886 | T53: =SUM(G53,K53,O53,S53) -> 485918
B54: Siga Sonriendo | C54: AGUA MINERAL / ENTEL CELULARES | D54: =_xlfn.XLOOKUP(C54,[3]Gastos!$B:$B,[3]Gastos!$G:$G) -> 16790 | E54: =_xlfn.XLOOKUP(C54,[3]Gastos!$B:$B,[3]Gastos!$L:$L) -> 18470 | F54: =_xlfn.XLOOKUP(C54,[3]Gastos!$B:$B,[3]Gastos!$Q:$Q) -> 18470 | G54: =SUM(Tabla1[[#This Row],[january]:[march]]) -> 53730 | H54: =_xlfn.XLOOKUP(C54,[3]Gastos!$B:$B,[3]Gastos!$V:$V) -> 18470 | I54: =_xlfn.XLOOKUP(C54,[3]Gastos!$B:$B,[3]Gastos!$AA:$AA) -> 9235 | J54: =_xlfn.XLOOKUP(C54,[3]Gastos!$B:$B,[3]Gastos!$AF:$AF) -> 9235 | K54: =SUM(Tabla1[[#This Row],[april]:[june]]) -> 36940 | L54: =_xlfn.XLOOKUP(C54,[3]Gastos!$B:$B,[3]Gastos!$AK:$AK) -> 9235 | M54: =_xlfn.XLOOKUP(C54,[3]Gastos!$B:$B,[3]Gastos!$AP:$AP) -> 9235 | N54: 21275 | O54: =SUM(Tabla1[[#This Row],[july]:[september]]) -> 39745 | P54: =_xlfn.XLOOKUP(Tabla1[[#This Row],[Subcuenta]],[3]Gastos!$B:$B,[3]Gastos!$AZ:$AZ) -> 9235 | Q54: =_xlfn.XLOOKUP(Tabla1[[#This Row],[Subcuenta]],[3]Gastos!$B:$B,[3]Gastos!$BE:$BE) -> 9235 | R54: =_xlfn.XLOOKUP(Tabla1[[#This Row],[Subcuenta]],[3]Gastos!$B:$B,[3]Gastos!$BJ:$BJ) -> 9235 | S54: =SUM(Tabla1[[#This Row],[october]:[december]]) -> 27705 | T54: =SUM(G54,K54,O54,S54) -> 158120
B55: Siga Sonriendo | C55: OFICINA 375 - ARRIENDO / GASTO COMUN / ENTEL INTERNET | D55: =_xlfn.XLOOKUP(C55,[3]Gastos!$B:$B,[3]Gastos!$G:$G) -> 883344 | E55: =_xlfn.XLOOKUP(C55,[3]Gastos!$B:$B,[3]Gastos!$L:$L) -> 833217 | F55: =_xlfn.XLOOKUP(C55,[3]Gastos!$B:$B,[3]Gastos!$Q:$Q) -> 902882 | G55: =SUM(Tabla1[[#This Row],[january]:[march]]) -> 2619443 | H55: =_xlfn.XLOOKUP(C55,[3]Gastos!$B:$B,[3]Gastos!$V:$V) -> 905178 | I55: =_xlfn.XLOOKUP(C55,[3]Gastos!$B:$B,[3]Gastos!$AA:$AA) -> 916557 | J55: =_xlfn.XLOOKUP(C55,[3]Gastos!$B:$B,[3]Gastos!$AF:$AF) -> 921778 | K55: =SUM(Tabla1[[#This Row],[april]:[june]]) -> 2743513 | L55: =_xlfn.XLOOKUP(C55,[3]Gastos!$B:$B,[3]Gastos!$AK:$AK) -> 976608 | M55: =_xlfn.XLOOKUP(C55,[3]Gastos!$B:$B,[3]Gastos!$AP:$AP) -> 930857 | N55: =784129+125944+20640 -> 930713 | O55: =SUM(Tabla1[[#This Row],[july]:[september]]) -> 2838178 | P55: =_xlfn.XLOOKUP(Tabla1[[#This Row],[Subcuenta]],[3]Gastos!$B:$B,[3]Gastos!$AZ:$AZ) -> 935988 | Q55: =_xlfn.XLOOKUP(Tabla1[[#This Row],[Subcuenta]],[3]Gastos!$B:$B,[3]Gastos!$BE:$BE) -> 942329 | R55: =_xlfn.XLOOKUP(Tabla1[[#This Row],[Subcuenta]],[3]Gastos!$B:$B,[3]Gastos!$BJ:$BJ) -> 971197 | S55: =SUM(Tabla1[[#This Row],[october]:[december]]) -> 2849514 | T55: =SUM(G55,K55,O55,S55) -> 11050648
B56: Siga Sonriendo | C56: OFICINA 375 - AGUAS ANDINAS - ENEL | D56: =_xlfn.XLOOKUP(C56,[3]Gastos!$B:$B,[3]Gastos!$G:$G) -> 3885 | E56: =_xlfn.XLOOKUP(C56,[3]Gastos!$B:$B,[3]Gastos!$L:$L) -> 3492 | F56: =_xlfn.XLOOKUP(C56,[3]Gastos!$B:$B,[3]Gastos!$Q:$Q) -> 2178 | G56: =SUM(Tabla1[[#This Row],[january]:[march]]) -> 9555 | H56: =_xlfn.XLOOKUP(C56,[3]Gastos!$B:$B,[3]Gastos!$V:$V) -> 4966 | I56: =_xlfn.XLOOKUP(C56,[3]Gastos!$B:$B,[3]Gastos!$AA:$AA) -> 7667 | J56: =_xlfn.XLOOKUP(C56,[3]Gastos!$B:$B,[3]Gastos!$AF:$AF) -> 14083 | K56: =SUM(Tabla1[[#This Row],[april]:[june]]) -> 26716 | L56: =_xlfn.XLOOKUP(C56,[3]Gastos!$B:$B,[3]Gastos!$AK:$AK) -> 4230 | M56: =_xlfn.XLOOKUP(C56,[3]Gastos!$B:$B,[3]Gastos!$AP:$AP) -> 10356 | N56: =830+4233 -> 5063 | O56: =SUM(Tabla1[[#This Row],[july]:[september]]) -> 19649 | P56: =_xlfn.XLOOKUP(Tabla1[[#This Row],[Subcuenta]],[3]Gastos!$B:$B,[3]Gastos!$AZ:$AZ) -> 5115 | Q56: =_xlfn.XLOOKUP(Tabla1[[#This Row],[Subcuenta]],[3]Gastos!$B:$B,[3]Gastos!$BE:$BE) -> 9604 | R56: =_xlfn.XLOOKUP(Tabla1[[#This Row],[Subcuenta]],[3]Gastos!$B:$B,[3]Gastos!$BJ:$BJ) -> 4861 | S56: =SUM(Tabla1[[#This Row],[october]:[december]]) -> 19580 | T56: =SUM(G56,K56,O56,S56) -> 75500
B57: Siga Sonriendo | C57: Consultorio 1307 LA FLORIDA - Arriendo / Gasto Comun / ENEL / ENTEL | D57: =_xlfn.XLOOKUP(C57,[3]Gastos!$B:$B,[3]Gastos!$G:$G) -> 367675 | E57: =_xlfn.XLOOKUP(C57,[3]Gastos!$B:$B,[3]Gastos!$L:$L) -> 406360 | F57: =_xlfn.XLOOKUP(C57,[3]Gastos!$B:$B,[3]Gastos!$Q:$Q) -> 399456 | G57: =SUM(Tabla1[[#This Row],[january]:[march]]) -> 1173491 | H57: =_xlfn.XLOOKUP(C57,[3]Gastos!$B:$B,[3]Gastos!$V:$V) -> 400259 | I57: =_xlfn.XLOOKUP(C57,[3]Gastos!$B:$B,[3]Gastos!$AA:$AA) -> 397565 | J57: =_xlfn.XLOOKUP(C57,[3]Gastos!$B:$B,[3]Gastos!$AF:$AF) -> 397039 | K57: =SUM(Tabla1[[#This Row],[april]:[june]]) -> 1194863 | L57: =_xlfn.XLOOKUP(C57,[3]Gastos!$B:$B,[3]Gastos!$AK:$AK) -> 391412 | M57: =_xlfn.XLOOKUP(C57,[3]Gastos!$B:$B,[3]Gastos!$AP:$AP) -> 383571 | N57: =305000+79869+2203+22705 -> 409777 | O57: =SUM(Tabla1[[#This Row],[july]:[september]]) -> 1184760 | P57: =_xlfn.XLOOKUP(Tabla1[[#This Row],[Subcuenta]],[3]Gastos!$B:$B,[3]Gastos!$AZ:$AZ) -> 409531 | Q57: =_xlfn.XLOOKUP(Tabla1[[#This Row],[Subcuenta]],[3]Gastos!$B:$B,[3]Gastos!$BE:$BE) -> 425569 | R57: =_xlfn.XLOOKUP(Tabla1[[#This Row],[Subcuenta]],[3]Gastos!$B:$B,[3]Gastos!$BJ:$BJ) -> 408388 | S57: =SUM(Tabla1[[#This Row],[october]:[december]]) -> 1243488 | T57: =SUM(G57,K57,O57,S57) -> 4796602
B58: Siga Sonriendo | C58: MERCADO PAGO SS | D58: =_xlfn.XLOOKUP(C58,[3]Gastos!$B:$B,[3]Gastos!$G:$G) -> 21595 | E58: =_xlfn.XLOOKUP(C58,[3]Gastos!$B:$B,[3]Gastos!$L:$L) -> 19980 | F58: =_xlfn.XLOOKUP(C58,[3]Gastos!$B:$B,[3]Gastos!$Q:$Q) -> 0 | G58: =SUM(Tabla1[[#This Row],[january]:[march]]) -> 41575 | H58: =_xlfn.XLOOKUP(C58,[3]Gastos!$B:$B,[3]Gastos!$V:$V) -> 17900 | I58: =_xlfn.XLOOKUP(C58,[3]Gastos!$B:$B,[3]Gastos!$AA:$AA) -> 23639 | J58: =_xlfn.XLOOKUP(C58,[3]Gastos!$B:$B,[3]Gastos!$AF:$AF) -> 106640 | K58: =SUM(Tabla1[[#This Row],[april]:[june]]) -> 148179 | L58: =_xlfn.XLOOKUP(C58,[3]Gastos!$B:$B,[3]Gastos!$AK:$AK) -> 0 | M58: =_xlfn.XLOOKUP(C58,[3]Gastos!$B:$B,[3]Gastos!$AP:$AP) -> 0 | N58: 12040 | O58: =SUM(Tabla1[[#This Row],[july]:[september]]) -> 12040 | Q58: =_xlfn.XLOOKUP(Tabla1[[#This Row],[Subcuenta]],[3]Gastos!$B:$B,[3]Gastos!$BE:$BE) -> 12040 | R58: =_xlfn.XLOOKUP(Tabla1[[#This Row],[Subcuenta]],[3]Gastos!$B:$B,[3]Gastos!$BJ:$BJ) -> 107357 | S58: =SUM(Tabla1[[#This Row],[october]:[december]]) -> 119397 | T58: =SUM(G58,K58,O58,S58) -> 321191
B59: Siga Sonriendo | C59: JESSICA MOROCHO | D59: =_xlfn.XLOOKUP(C59,[3]Gastos!$B:$B,[3]Gastos!$G:$G) -> 1000000 | E59: =_xlfn.XLOOKUP(C59,[3]Gastos!$B:$B,[3]Gastos!$L:$L) -> 0 | F59: =_xlfn.XLOOKUP(C59,[3]Gastos!$B:$B,[3]Gastos!$Q:$Q) -> 0 | G59: =SUM(Tabla1[[#This Row],[january]:[march]]) -> 1000000 | H59: =_xlfn.XLOOKUP(C59,[3]Gastos!$B:$B,[3]Gastos!$V:$V) -> 0 | I59: =_xlfn.XLOOKUP(C59,[3]Gastos!$B:$B,[3]Gastos!$AA:$AA) -> 0 | J59: =_xlfn.XLOOKUP(C59,[3]Gastos!$B:$B,[3]Gastos!$AF:$AF) -> 0 | K59: =SUM(Tabla1[[#This Row],[april]:[june]]) -> 0 | L59: =_xlfn.XLOOKUP(C59,[3]Gastos!$B:$B,[3]Gastos!$AK:$AK) -> 0 | M59: =_xlfn.XLOOKUP(C59,[3]Gastos!$B:$B,[3]Gastos!$AP:$AP) -> 0 | O59: =SUM(Tabla1[[#This Row],[july]:[september]]) -> 0 | P59: =_xlfn.XLOOKUP(Tabla1[[#This Row],[Subcuenta]],[3]Gastos!$B:$B,[3]Gastos!$AZ:$AZ) -> 0 | Q59: =_xlfn.XLOOKUP(Tabla1[[#This Row],[Subcuenta]],[3]Gastos!$B:$B,[3]Gastos!$BE:$BE) -> 0 | R59: =_xlfn.XLOOKUP(Tabla1[[#This Row],[Subcuenta]],[3]Gastos!$B:$B,[3]Gastos!$BJ:$BJ) -> 0 | S59: =SUM(Tabla1[[#This Row],[october]:[december]]) -> 0 | T59: =SUM(G59,K59,O59,S59) -> 1000000
B60: Siga Sonriendo | C60: SEBASTIAN URETA | D60: =_xlfn.XLOOKUP(C60,[3]Gastos!$B:$B,[3]Gastos!$G:$G) -> 1956016 | E60: =_xlfn.XLOOKUP(C60,[3]Gastos!$B:$B,[3]Gastos!$L:$L) -> 0 | F60: =_xlfn.XLOOKUP(C60,[3]Gastos!$B:$B,[3]Gastos!$Q:$Q) -> 0 | G60: =SUM(Tabla1[[#This Row],[january]:[march]]) -> 1956016 | H60: =_xlfn.XLOOKUP(C60,[3]Gastos!$B:$B,[3]Gastos!$V:$V) -> 0 | I60: =_xlfn.XLOOKUP(C60,[3]Gastos!$B:$B,[3]Gastos!$AA:$AA) -> 0 | J60: =_xlfn.XLOOKUP(C60,[3]Gastos!$B:$B,[3]Gastos!$AF:$AF) -> 0 | K60: =SUM(Tabla1[[#This Row],[april]:[june]]) -> 0 | L60: =_xlfn.XLOOKUP(C60,[3]Gastos!$B:$B,[3]Gastos!$AK:$AK) -> 0 | M60: =_xlfn.XLOOKUP(C60,[3]Gastos!$B:$B,[3]Gastos!$AP:$AP) -> 0 | O60: =SUM(Tabla1[[#This Row],[july]:[september]]) -> 0 | P60: =_xlfn.XLOOKUP(Tabla1[[#This Row],[Subcuenta]],[3]Gastos!$B:$B,[3]Gastos!$AZ:$AZ) -> 0 | Q60: =_xlfn.XLOOKUP(Tabla1[[#This Row],[Subcuenta]],[3]Gastos!$B:$B,[3]Gastos!$BE:$BE) -> 0 | R60: =_xlfn.XLOOKUP(Tabla1[[#This Row],[Subcuenta]],[3]Gastos!$B:$B,[3]Gastos!$BJ:$BJ) -> 0 | S60: =SUM(Tabla1[[#This Row],[october]:[december]]) -> 0 | T60: =SUM(G60,K60,O60,S60) -> 1956016 | U60: =SUM(#REF!) -> #REF!
B61: Gastos de Viaje | C61: Alojamientos | D61: =_xlfn.XLOOKUP(C61,[3]Gastos!$B:$B,[3]Gastos!$G:$G) -> 0 | E61: =_xlfn.XLOOKUP(C61,[3]Gastos!$B:$B,[3]Gastos!$L:$L) -> 0 | F61: =_xlfn.XLOOKUP(C61,[3]Gastos!$B:$B,[3]Gastos!$Q:$Q) -> 0 | G61: =SUM(Tabla1[[#This Row],[january]:[march]]) -> 0 | H61: =_xlfn.XLOOKUP(C61,[3]Gastos!$B:$B,[3]Gastos!$V:$V) -> 0 | I61: =_xlfn.XLOOKUP(C61,[3]Gastos!$B:$B,[3]Gastos!$AA:$AA) -> 0 | J61: =_xlfn.XLOOKUP(C61,[3]Gastos!$B:$B,[3]Gastos!$AF:$AF) -> 0 | K61: =SUM(Tabla1[[#This Row],[april]:[june]]) -> 0 | L61: =_xlfn.XLOOKUP(C61,[3]Gastos!$B:$B,[3]Gastos!$AK:$AK) -> 0 | M61: =_xlfn.XLOOKUP(C61,[3]Gastos!$B:$B,[3]Gastos!$AP:$AP) -> 0 | O61: =SUM(Tabla1[[#This Row],[july]:[september]]) -> 0 | P61: =_xlfn.XLOOKUP(Tabla1[[#This Row],[Subcuenta]],[3]Gastos!$B:$B,[3]Gastos!$AZ:$AZ) -> 0 | Q61: =_xlfn.XLOOKUP(Tabla1[[#This Row],[Subcuenta]],[3]Gastos!$B:$B,[3]Gastos!$BE:$BE) -> 0 | R61: =_xlfn.XLOOKUP(Tabla1[[#This Row],[Subcuenta]],[3]Gastos!$B:$B,[3]Gastos!$BJ:$BJ) -> 0 | S61: =SUM(Tabla1[[#This Row],[october]:[december]]) -> 0 | T61: =SUM(G61,K61,O61,S61) -> 0
B62: Gastos de Viaje | C62: Pasajes | D62: =_xlfn.XLOOKUP(C62,[3]Gastos!$B:$B,[3]Gastos!$G:$G) -> 0 | E62: =_xlfn.XLOOKUP(C62,[3]Gastos!$B:$B,[3]Gastos!$L:$L) -> 557138 | F62: =_xlfn.XLOOKUP(C62,[3]Gastos!$B:$B,[3]Gastos!$Q:$Q) -> 0 | G62: =SUM(Tabla1[[#This Row],[january]:[march]]) -> 557138 | H62: =_xlfn.XLOOKUP(C62,[3]Gastos!$B:$B,[3]Gastos!$V:$V) -> 2505540 | I62: =_xlfn.XLOOKUP(C62,[3]Gastos!$B:$B,[3]Gastos!$AA:$AA) -> 557956 | J62: =_xlfn.XLOOKUP(C62,[3]Gastos!$B:$B,[3]Gastos!$AF:$AF) -> 0 | K62: =SUM(Tabla1[[#This Row],[april]:[june]]) -> 3063496 | L62: =_xlfn.XLOOKUP(C62,[3]Gastos!$B:$B,[3]Gastos!$AK:$AK) -> 0 | M62: =_xlfn.XLOOKUP(C62,[3]Gastos!$B:$B,[3]Gastos!$AP:$AP) -> 404759 | N62: 977243 | O62: =SUM(Tabla1[[#This Row],[july]:[september]]) -> 1382002 | P62: =_xlfn.XLOOKUP(Tabla1[[#This Row],[Subcuenta]],[3]Gastos!$B:$B,[3]Gastos!$AZ:$AZ) -> 0 | Q62: =_xlfn.XLOOKUP(Tabla1[[#This Row],[Subcuenta]],[3]Gastos!$B:$B,[3]Gastos!$BE:$BE) -> 0 | R62: =_xlfn.XLOOKUP(Tabla1[[#This Row],[Subcuenta]],[3]Gastos!$B:$B,[3]Gastos!$BJ:$BJ) -> 0 | S62: =SUM(Tabla1[[#This Row],[october]:[december]]) -> 0 | T62: =SUM(G62,K62,O62,S62) -> 5002636
B63: Gastos de Viaje | C63: Gastos de viajes de rendiciones | D63: =_xlfn.XLOOKUP(C63,[3]Gastos!$B:$B,[3]Gastos!$G:$G) -> 0 | E63: =_xlfn.XLOOKUP(C63,[3]Gastos!$B:$B,[3]Gastos!$L:$L) -> 0 | F63: =_xlfn.XLOOKUP(C63,[3]Gastos!$B:$B,[3]Gastos!$Q:$Q) -> 0 | G63: =SUM(Tabla1[[#This Row],[january]:[march]]) -> 0 | H63: =_xlfn.XLOOKUP(C63,[3]Gastos!$B:$B,[3]Gastos!$V:$V) -> 0 | I63: =_xlfn.XLOOKUP(C63,[3]Gastos!$B:$B,[3]Gastos!$AA:$AA) -> 785739 | J63: =_xlfn.XLOOKUP(C63,[3]Gastos!$B:$B,[3]Gastos!$AF:$AF) -> 0 | K63: =SUM(Tabla1[[#This Row],[april]:[june]]) -> 785739 | L63: =_xlfn.XLOOKUP(C63,[3]Gastos!$B:$B,[3]Gastos!$AK:$AK) -> 0 | M63: =_xlfn.XLOOKUP(C63,[3]Gastos!$B:$B,[3]Gastos!$AP:$AP) -> 65981 | O63: =SUM(Tabla1[[#This Row],[july]:[september]]) -> 65981 | P63: =_xlfn.XLOOKUP(Tabla1[[#This Row],[Subcuenta]],[3]Gastos!$B:$B,[3]Gastos!$AZ:$AZ) -> 271431 | Q63: =_xlfn.XLOOKUP(Tabla1[[#This Row],[Subcuenta]],[3]Gastos!$B:$B,[3]Gastos!$BE:$BE) -> 277171 | R63: =_xlfn.XLOOKUP(Tabla1[[#This Row],[Subcuenta]],[3]Gastos!$B:$B,[3]Gastos!$BJ:$BJ) -> 0 | S63: =SUM(Tabla1[[#This Row],[october]:[december]]) -> 548602 | T63: =SUM(G63,K63,O63,S63) -> 1400322 | U63: =SUM(#REF!) -> #REF!
B64: Gastos de Importacion Invisalign | C64: TGR IMPUESTOS Invisalign | D64: =_xlfn.XLOOKUP(C64,[3]Gastos!$B:$B,[3]Gastos!$G:$G) -> 0 | E64: =_xlfn.XLOOKUP(C64,[3]Gastos!$B:$B,[3]Gastos!$L:$L) -> 0 | F64: =_xlfn.XLOOKUP(C64,[3]Gastos!$B:$B,[3]Gastos!$Q:$Q) -> 0 | G64: =SUM(Tabla1[[#This Row],[january]:[march]]) -> 0 | H64: =_xlfn.XLOOKUP(C64,[3]Gastos!$B:$B,[3]Gastos!$V:$V) -> 0 | I64: =_xlfn.XLOOKUP(C64,[3]Gastos!$B:$B,[3]Gastos!$AA:$AA) -> 0 | J64: =_xlfn.XLOOKUP(C64,[3]Gastos!$B:$B,[3]Gastos!$AF:$AF) -> 0 | K64: =SUM(Tabla1[[#This Row],[april]:[june]]) -> 0 | L64: =_xlfn.XLOOKUP(C64,[3]Gastos!$B:$B,[3]Gastos!$AK:$AK) -> 0 | M64: =_xlfn.XLOOKUP(C64,[3]Gastos!$B:$B,[3]Gastos!$AP:$AP) -> 0 | O64: =SUM(Tabla1[[#This Row],[july]:[september]]) -> 0 | P64: =_xlfn.XLOOKUP(Tabla1[[#This Row],[Subcuenta]],[3]Gastos!$B:$B,[3]Gastos!$AZ:$AZ) -> 0 | Q64: =_xlfn.XLOOKUP(Tabla1[[#This Row],[Subcuenta]],[3]Gastos!$B:$B,[3]Gastos!$BE:$BE) -> 0 | R64: =_xlfn.XLOOKUP(Tabla1[[#This Row],[Subcuenta]],[3]Gastos!$B:$B,[3]Gastos!$BJ:$BJ) -> 0 | S64: =SUM(Tabla1[[#This Row],[october]:[december]]) -> 0 | T64: =SUM(G64,K64,O64,S64) -> 0
B65: Gastos de Importacion Invisalign | C65: FLETE INTERNO Invisalign | D65: =_xlfn.XLOOKUP(C65,[3]Gastos!$B:$B,[3]Gastos!$G:$G) -> 0 | E65: =_xlfn.XLOOKUP(C65,[3]Gastos!$B:$B,[3]Gastos!$L:$L) -> 0 | F65: =_xlfn.XLOOKUP(C65,[3]Gastos!$B:$B,[3]Gastos!$Q:$Q) -> 0 | G65: =SUM(Tabla1[[#This Row],[january]:[march]]) -> 0 | H65: =_xlfn.XLOOKUP(C65,[3]Gastos!$B:$B,[3]Gastos!$V:$V) -> 124950 | I65: =_xlfn.XLOOKUP(C65,[3]Gastos!$B:$B,[3]Gastos!$AA:$AA) -> 0 | J65: =_xlfn.XLOOKUP(C65,[3]Gastos!$B:$B,[3]Gastos!$AF:$AF) -> 0 | K65: =SUM(Tabla1[[#This Row],[april]:[june]]) -> 124950 | L65: =_xlfn.XLOOKUP(C65,[3]Gastos!$B:$B,[3]Gastos!$AK:$AK) -> 0 | M65: =_xlfn.XLOOKUP(C65,[3]Gastos!$B:$B,[3]Gastos!$AP:$AP) -> 404600 | N65: 95200 | O65: =SUM(Tabla1[[#This Row],[july]:[september]]) -> 499800 | P65: =_xlfn.XLOOKUP(Tabla1[[#This Row],[Subcuenta]],[3]Gastos!$B:$B,[3]Gastos!$AZ:$AZ) -> 0 | Q65: =_xlfn.XLOOKUP(Tabla1[[#This Row],[Subcuenta]],[3]Gastos!$B:$B,[3]Gastos!$BE:$BE) -> 0 | R65: =_xlfn.XLOOKUP(Tabla1[[#This Row],[Subcuenta]],[3]Gastos!$B:$B,[3]Gastos!$BJ:$BJ) -> 0 | S65: =SUM(Tabla1[[#This Row],[october]:[december]]) -> 0 | T65: =SUM(G65,K65,O65,S65) -> 624750
B66: Gastos de Importacion Invisalign | C66: UPS / ALMACENAJE Invisalign | D66: =_xlfn.XLOOKUP(C66,[3]Gastos!$B:$B,[3]Gastos!$G:$G) -> 1754301 | E66: =_xlfn.XLOOKUP(C66,[3]Gastos!$B:$B,[3]Gastos!$L:$L) -> 1652469 | F66: =_xlfn.XLOOKUP(C66,[3]Gastos!$B:$B,[3]Gastos!$Q:$Q) -> 1813994 | G66: =SUM(Tabla1[[#This Row],[january]:[march]]) -> 5220764 | H66: =_xlfn.XLOOKUP(C66,[3]Gastos!$B:$B,[3]Gastos!$V:$V) -> 1676574 | I66: =_xlfn.XLOOKUP(C66,[3]Gastos!$B:$B,[3]Gastos!$AA:$AA) -> 1717382 | J66: =_xlfn.XLOOKUP(C66,[3]Gastos!$B:$B,[3]Gastos!$AF:$AF) -> 1711419 | K66: =SUM(Tabla1[[#This Row],[april]:[june]]) -> 5105375 | L66: =_xlfn.XLOOKUP(C66,[3]Gastos!$B:$B,[3]Gastos!$AK:$AK) -> 1709439 | M66: =_xlfn.XLOOKUP(C66,[3]Gastos!$B:$B,[3]Gastos!$AP:$AP) -> 1478329 | N66: 1735716 | O66: =SUM(Tabla1[[#This Row],[july]:[september]]) -> 4923484 | P66: =_xlfn.XLOOKUP(Tabla1[[#This Row],[Subcuenta]],[3]Gastos!$B:$B,[3]Gastos!$AZ:$AZ) -> 2524551 | Q66: =_xlfn.XLOOKUP(Tabla1[[#This Row],[Subcuenta]],[3]Gastos!$B:$B,[3]Gastos!$BE:$BE) -> 1676488 | R66: =_xlfn.XLOOKUP(Tabla1[[#This Row],[Subcuenta]],[3]Gastos!$B:$B,[3]Gastos!$BJ:$BJ) -> 1570052 | S66: =SUM(Tabla1[[#This Row],[october]:[december]]) -> 5771091 | T66: =SUM(G66,K66,O66,S66) -> 21020714
B67: Gastos de Importacion Invisalign | C67: TGR ARANCEL Y SEGURO Invisalign | D67: =_xlfn.XLOOKUP(C67,[3]Gastos!$B:$B,[3]Gastos!$G:$G) -> 131701 | E67: =_xlfn.XLOOKUP(C67,[3]Gastos!$B:$B,[3]Gastos!$L:$L) -> 127908 | F67: =_xlfn.XLOOKUP(C67,[3]Gastos!$B:$B,[3]Gastos!$Q:$Q) -> 126280 | G67: =SUM(Tabla1[[#This Row],[january]:[march]]) -> 385889 | H67: =_xlfn.XLOOKUP(C67,[3]Gastos!$B:$B,[3]Gastos!$V:$V) -> 76818 | I67: =_xlfn.XLOOKUP(C67,[3]Gastos!$B:$B,[3]Gastos!$AA:$AA) -> 19583 | J67: =_xlfn.XLOOKUP(C67,[3]Gastos!$B:$B,[3]Gastos!$AF:$AF) -> 0 | K67: =SUM(Tabla1[[#This Row],[april]:[june]]) -> 96401 | L67: =_xlfn.XLOOKUP(C67,[3]Gastos!$B:$B,[3]Gastos!$AK:$AK) -> 29080 | M67: =_xlfn.XLOOKUP(C67,[3]Gastos!$B:$B,[3]Gastos!$AP:$AP) -> 0 | O67: =SUM(Tabla1[[#This Row],[july]:[september]]) -> 29080 | P67: =_xlfn.XLOOKUP(Tabla1[[#This Row],[Subcuenta]],[3]Gastos!$B:$B,[3]Gastos!$AZ:$AZ) -> 0 | Q67: =_xlfn.XLOOKUP(Tabla1[[#This Row],[Subcuenta]],[3]Gastos!$B:$B,[3]Gastos!$BE:$BE) -> 0 | R67: =_xlfn.XLOOKUP(Tabla1[[#This Row],[Subcuenta]],[3]Gastos!$B:$B,[3]Gastos!$BJ:$BJ) -> 2525323.4 | S67: =SUM(Tabla1[[#This Row],[october]:[december]]) -> 2525323.4 | T67: =SUM(G67,K67,O67,S67) -> 3036693.4
B68: Gastos de Importacion Invisalign | C68: Instituto Salud Publica (CDA) Invisalign | D68: =_xlfn.XLOOKUP(C68,[3]Gastos!$B:$B,[3]Gastos!$G:$G) -> 785849 | E68: =_xlfn.XLOOKUP(C68,[3]Gastos!$B:$B,[3]Gastos!$L:$L) -> 876918 | F68: =_xlfn.XLOOKUP(C68,[3]Gastos!$B:$B,[3]Gastos!$Q:$Q) -> 876918 | G68: =SUM(Tabla1[[#This Row],[january]:[march]]) -> 2539685 | H68: =_xlfn.XLOOKUP(C68,[3]Gastos!$B:$B,[3]Gastos!$V:$V) -> 876918 | I68: =_xlfn.XLOOKUP(C68,[3]Gastos!$B:$B,[3]Gastos!$AA:$AA) -> 814281 | J68: =_xlfn.XLOOKUP(C68,[3]Gastos!$B:$B,[3]Gastos!$AF:$AF) -> 814281 | K68: =SUM(Tabla1[[#This Row],[april]:[june]]) -> 2505480 | L68: =_xlfn.XLOOKUP(C68,[3]Gastos!$B:$B,[3]Gastos!$AK:$AK) -> 751644 | M68: =_xlfn.XLOOKUP(C68,[3]Gastos!$B:$B,[3]Gastos!$AP:$AP) -> 876918 | N68: 814281 | O68: =SUM(Tabla1[[#This Row],[july]:[september]]) -> 2442843 | P68: =_xlfn.XLOOKUP(Tabla1[[#This Row],[Subcuenta]],[3]Gastos!$B:$B,[3]Gastos!$AZ:$AZ) -> 1064829 | Q68: =_xlfn.XLOOKUP(Tabla1[[#This Row],[Subcuenta]],[3]Gastos!$B:$B,[3]Gastos!$BE:$BE) -> 1127466 | R68: =_xlfn.XLOOKUP(Tabla1[[#This Row],[Subcuenta]],[3]Gastos!$B:$B,[3]Gastos!$BJ:$BJ) -> 689007 | S68: =SUM(Tabla1[[#This Row],[october]:[december]]) -> 2881302 | T68: =SUM(G68,K68,O68,S68) -> 10369310
B69: Gastos de Importacion Invisalign | C69: AGENCIA DE ADUANA Invisalign | D69: =_xlfn.XLOOKUP(C69,[3]Gastos!$B:$B,[3]Gastos!$G:$G) -> 2629900 | E69: =_xlfn.XLOOKUP(C69,[3]Gastos!$B:$B,[3]Gastos!$L:$L) -> 2629900 | F69: =_xlfn.XLOOKUP(C69,[3]Gastos!$B:$B,[3]Gastos!$Q:$Q) -> 2832200 | G69: =SUM(Tabla1[[#This Row],[january]:[march]]) -> 8092000 | H69: =_xlfn.XLOOKUP(C69,[3]Gastos!$B:$B,[3]Gastos!$V:$V) -> 2629900 | I69: =_xlfn.XLOOKUP(C69,[3]Gastos!$B:$B,[3]Gastos!$AA:$AA) -> 2629900 | J69: =_xlfn.XLOOKUP(C69,[3]Gastos!$B:$B,[3]Gastos!$AF:$AF) -> 2629900 | K69: =SUM(Tabla1[[#This Row],[april]:[june]]) -> 7889700 | L69: =_xlfn.XLOOKUP(C69,[3]Gastos!$B:$B,[3]Gastos!$AK:$AK) -> 2629900 | M69: =_xlfn.XLOOKUP(C69,[3]Gastos!$B:$B,[3]Gastos!$AP:$AP) -> 2665600 | N69: 2427600 | O69: =SUM(Tabla1[[#This Row],[july]:[september]]) -> 7723100 | P69: =_xlfn.XLOOKUP(Tabla1[[#This Row],[Subcuenta]],[3]Gastos!$B:$B,[3]Gastos!$AZ:$AZ) -> 3439100 | Q69: =_xlfn.XLOOKUP(Tabla1[[#This Row],[Subcuenta]],[3]Gastos!$B:$B,[3]Gastos!$BE:$BE) -> 2225300 | R69: =_xlfn.XLOOKUP(Tabla1[[#This Row],[Subcuenta]],[3]Gastos!$B:$B,[3]Gastos!$BJ:$BJ) -> 2225300 | S69: =SUM(Tabla1[[#This Row],[october]:[december]]) -> 7889700 | T69: =SUM(G69,K69,O69,S69) -> 31594500 | U69: =SUM(#REF!) -> #REF!
B70: Gastos de Importacion Itero | C70: AGENCIA DE ADUANA Itero | D70: =_xlfn.XLOOKUP(C70,[3]Gastos!$B:$B,[3]Gastos!$G:$G) -> 202300 | E70: =_xlfn.XLOOKUP(C70,[3]Gastos!$B:$B,[3]Gastos!$L:$L) -> 0 | F70: =_xlfn.XLOOKUP(C70,[3]Gastos!$B:$B,[3]Gastos!$Q:$Q) -> 404600 | G70: =SUM(Tabla1[[#This Row],[january]:[march]]) -> 606900 | H70: =_xlfn.XLOOKUP(C70,[3]Gastos!$B:$B,[3]Gastos!$V:$V) -> 404600 | I70: =_xlfn.XLOOKUP(C70,[3]Gastos!$B:$B,[3]Gastos!$AA:$AA) -> 202300 | J70: =_xlfn.XLOOKUP(C70,[3]Gastos!$B:$B,[3]Gastos!$AF:$AF) -> 404600 | K70: =SUM(Tabla1[[#This Row],[april]:[june]]) -> 1011500 | L70: =_xlfn.XLOOKUP(C70,[3]Gastos!$B:$B,[3]Gastos!$AK:$AK) -> 606900 | M70: =_xlfn.XLOOKUP(C70,[3]Gastos!$B:$B,[3]Gastos!$AP:$AP) -> 606900 | O70: =SUM(Tabla1[[#This Row],[july]:[september]]) -> 1213800 | P70: =_xlfn.XLOOKUP(Tabla1[[#This Row],[Subcuenta]],[3]Gastos!$B:$B,[3]Gastos!$AZ:$AZ) -> 404600 | Q70: =_xlfn.XLOOKUP(Tabla1[[#This Row],[Subcuenta]],[3]Gastos!$B:$B,[3]Gastos!$BE:$BE) -> 404600 | R70: =_xlfn.XLOOKUP(Tabla1[[#This Row],[Subcuenta]],[3]Gastos!$B:$B,[3]Gastos!$BJ:$BJ) -> 0 | S70: =SUM(Tabla1[[#This Row],[october]:[december]]) -> 809200 | T70: =SUM(G70,K70,O70,S70) -> 3641400
B71: Gastos de Importacion Itero | C71: FLETE INTERNO - FEDEX OCASIONAL Itero | D71: =_xlfn.XLOOKUP(C71,[3]Gastos!$B:$B,[3]Gastos!$G:$G) -> 0 | E71: =_xlfn.XLOOKUP(C71,[3]Gastos!$B:$B,[3]Gastos!$L:$L) -> 0 | F71: =_xlfn.XLOOKUP(C71,[3]Gastos!$B:$B,[3]Gastos!$Q:$Q) -> 0 | G71: =SUM(Tabla1[[#This Row],[january]:[march]]) -> 0 | H71: =_xlfn.XLOOKUP(C71,[3]Gastos!$B:$B,[3]Gastos!$V:$V) -> 238000 | I71: =_xlfn.XLOOKUP(C71,[3]Gastos!$B:$B,[3]Gastos!$AA:$AA) -> 0 | J71: =_xlfn.XLOOKUP(C71,[3]Gastos!$B:$B,[3]Gastos!$AF:$AF) -> 214200 | K71: =SUM(Tabla1[[#This Row],[april]:[june]]) -> 452200 | L71: =_xlfn.XLOOKUP(C71,[3]Gastos!$B:$B,[3]Gastos!$AK:$AK) -> 0 | M71: =_xlfn.XLOOKUP(C71,[3]Gastos!$B:$B,[3]Gastos!$AP:$AP) -> 309400 | O71: =SUM(Tabla1[[#This Row],[july]:[september]]) -> 309400 | P71: =_xlfn.XLOOKUP(Tabla1[[#This Row],[Subcuenta]],[3]Gastos!$B:$B,[3]Gastos!$AZ:$AZ) -> 190400 | Q71: =_xlfn.XLOOKUP(Tabla1[[#This Row],[Subcuenta]],[3]Gastos!$B:$B,[3]Gastos!$BE:$BE) -> 0 | R71: =_xlfn.XLOOKUP(Tabla1[[#This Row],[Subcuenta]],[3]Gastos!$B:$B,[3]Gastos!$BJ:$BJ) -> 0 | S71: =SUM(Tabla1[[#This Row],[october]:[december]]) -> 190400 | T71: =SUM(G71,K71,O71,S71) -> 952000
B72: Gastos de Importacion Itero | C72: DESCONSOLIDADO (DHL, UPS) Itero | D72: =_xlfn.XLOOKUP(C72,[3]Gastos!$B:$B,[3]Gastos!$G:$G) -> 0 | E72: =_xlfn.XLOOKUP(C72,[3]Gastos!$B:$B,[3]Gastos!$L:$L) -> 0 | F72: =_xlfn.XLOOKUP(C72,[3]Gastos!$B:$B,[3]Gastos!$Q:$Q) -> 347796 | G72: =SUM(Tabla1[[#This Row],[january]:[march]]) -> 347796 | H72: =_xlfn.XLOOKUP(C72,[3]Gastos!$B:$B,[3]Gastos!$V:$V) -> 353067 | I72: =_xlfn.XLOOKUP(C72,[3]Gastos!$B:$B,[3]Gastos!$AA:$AA) -> 252806 | J72: =_xlfn.XLOOKUP(C72,[3]Gastos!$B:$B,[3]Gastos!$AF:$AF) -> 491473 | K72: =SUM(Tabla1[[#This Row],[april]:[june]]) -> 1097346 | L72: =_xlfn.XLOOKUP(C72,[3]Gastos!$B:$B,[3]Gastos!$AK:$AK) -> 622546 | M72: =_xlfn.XLOOKUP(C72,[3]Gastos!$B:$B,[3]Gastos!$AP:$AP) -> 689477 | N72: 766537 | O72: =SUM(Tabla1[[#This Row],[july]:[september]]) -> 2078560 | P72: =_xlfn.XLOOKUP(Tabla1[[#This Row],[Subcuenta]],[3]Gastos!$B:$B,[3]Gastos!$AZ:$AZ) -> 396295 | Q72: =_xlfn.XLOOKUP(Tabla1[[#This Row],[Subcuenta]],[3]Gastos!$B:$B,[3]Gastos!$BE:$BE) -> 505501 | R72: =_xlfn.XLOOKUP(Tabla1[[#This Row],[Subcuenta]],[3]Gastos!$B:$B,[3]Gastos!$BJ:$BJ) -> 0 | S72: =SUM(Tabla1[[#This Row],[october]:[december]]) -> 901796 | T72: =SUM(G72,K72,O72,S72) -> 4425498
B73: Gastos de Importacion Itero | C73: Almacenaje (Depocargo, Aerosan, FAST AIR, UPS) Itero | D73: =_xlfn.XLOOKUP(C73,[3]Gastos!$B:$B,[3]Gastos!$G:$G) -> 135599 | E73: =_xlfn.XLOOKUP(C73,[3]Gastos!$B:$B,[3]Gastos!$L:$L) -> 0 | F73: =_xlfn.XLOOKUP(C73,[3]Gastos!$B:$B,[3]Gastos!$Q:$Q) -> 0 | G73: =SUM(Tabla1[[#This Row],[january]:[march]]) -> 135599 | H73: =_xlfn.XLOOKUP(C73,[3]Gastos!$B:$B,[3]Gastos!$V:$V) -> 350399 | I73: =_xlfn.XLOOKUP(C73,[3]Gastos!$B:$B,[3]Gastos!$AA:$AA) -> 49347 | J73: =_xlfn.XLOOKUP(C73,[3]Gastos!$B:$B,[3]Gastos!$AF:$AF) -> 362498 | K73: =SUM(Tabla1[[#This Row],[april]:[june]]) -> 762244 | L73: =_xlfn.XLOOKUP(C73,[3]Gastos!$B:$B,[3]Gastos!$AK:$AK) -> 416556 | M73: =_xlfn.XLOOKUP(C73,[3]Gastos!$B:$B,[3]Gastos!$AP:$AP) -> 735520 | N73: 152120 | O73: =SUM(Tabla1[[#This Row],[july]:[september]]) -> 1304196 | P73: =_xlfn.XLOOKUP(Tabla1[[#This Row],[Subcuenta]],[3]Gastos!$B:$B,[3]Gastos!$AZ:$AZ) -> 496474 | Q73: =_xlfn.XLOOKUP(Tabla1[[#This Row],[Subcuenta]],[3]Gastos!$B:$B,[3]Gastos!$BE:$BE) -> 69989 | R73: =_xlfn.XLOOKUP(Tabla1[[#This Row],[Subcuenta]],[3]Gastos!$B:$B,[3]Gastos!$BJ:$BJ) -> 0 | S73: =SUM(Tabla1[[#This Row],[october]:[december]]) -> 566463 | T73: =SUM(G73,K73,O73,S73) -> 2768502
B74: Gastos de Importacion Itero | C74: TGR ARANCEL Y SEGURO Itero | D74: =_xlfn.XLOOKUP(C74,[3]Gastos!$B:$B,[3]Gastos!$G:$G) -> 209735 | E74: =_xlfn.XLOOKUP(C74,[3]Gastos!$B:$B,[3]Gastos!$L:$L) -> 0 | F74: =_xlfn.XLOOKUP(C74,[3]Gastos!$B:$B,[3]Gastos!$Q:$Q) -> 318372 | G74: =SUM(Tabla1[[#This Row],[january]:[march]]) -> 528107 | H74: =_xlfn.XLOOKUP(C74,[3]Gastos!$B:$B,[3]Gastos!$V:$V) -> 1974992 | I74: =_xlfn.XLOOKUP(C74,[3]Gastos!$B:$B,[3]Gastos!$AA:$AA) -> 876511.35 | J74: =_xlfn.XLOOKUP(C74,[3]Gastos!$B:$B,[3]Gastos!$AF:$AF) -> 1736192 | K74: =SUM(Tabla1[[#This Row],[april]:[june]]) -> 4587695.3 | L74: =_xlfn.XLOOKUP(C74,[3]Gastos!$B:$B,[3]Gastos!$AK:$AK) -> 677762 | M74: =_xlfn.XLOOKUP(C74,[3]Gastos!$B:$B,[3]Gastos!$AP:$AP) -> 1845446.8 | O74: =SUM(Tabla1[[#This Row],[july]:[september]]) -> 2523208.8 | P74: =_xlfn.XLOOKUP(Tabla1[[#This Row],[Subcuenta]],[3]Gastos!$B:$B,[3]Gastos!$AZ:$AZ) -> 2254756 | Q74: =_xlfn.XLOOKUP(Tabla1[[#This Row],[Subcuenta]],[3]Gastos!$B:$B,[3]Gastos!$BE:$BE) -> 1134795.5 | R74: =_xlfn.XLOOKUP(Tabla1[[#This Row],[Subcuenta]],[3]Gastos!$B:$B,[3]Gastos!$BJ:$BJ) -> 0 | S74: =SUM(Tabla1[[#This Row],[october]:[december]]) -> 3389551.5 | T74: =SUM(G74,K74,O74,S74) -> 11028563
B75: Gastos de Importacion Itero | C75: Instituto Salud Publica (CDA) Intero | D75: =_xlfn.XLOOKUP(C75,[3]Gastos!$B:$B,[3]Gastos!$G:$G) -> 55529 | E75: =_xlfn.XLOOKUP(C75,[3]Gastos!$B:$B,[3]Gastos!$L:$L) -> 0 | F75: =_xlfn.XLOOKUP(C75,[3]Gastos!$B:$B,[3]Gastos!$Q:$Q) -> 125274 | G75: =SUM(Tabla1[[#This Row],[january]:[march]]) -> 180803 | H75: =_xlfn.XLOOKUP(C75,[3]Gastos!$B:$B,[3]Gastos!$V:$V) -> 125274 | I75: =_xlfn.XLOOKUP(C75,[3]Gastos!$B:$B,[3]Gastos!$AA:$AA) -> 62637 | J75: =_xlfn.XLOOKUP(C75,[3]Gastos!$B:$B,[3]Gastos!$AF:$AF) -> 125274 | K75: =SUM(Tabla1[[#This Row],[april]:[june]]) -> 313185 | L75: =_xlfn.XLOOKUP(C75,[3]Gastos!$B:$B,[3]Gastos!$AK:$AK) -> 187911 | M75: =_xlfn.XLOOKUP(C75,[3]Gastos!$B:$B,[3]Gastos!$AP:$AP) -> 187911 | O75: =SUM(Tabla1[[#This Row],[july]:[september]]) -> 375822 | P75: =_xlfn.XLOOKUP(Tabla1[[#This Row],[Subcuenta]],[3]Gastos!$B:$B,[3]Gastos!$AZ:$AZ) -> 125274 | Q75: =_xlfn.XLOOKUP(Tabla1[[#This Row],[Subcuenta]],[3]Gastos!$B:$B,[3]Gastos!$BE:$BE) -> 125274 | R75: =_xlfn.XLOOKUP(Tabla1[[#This Row],[Subcuenta]],[3]Gastos!$B:$B,[3]Gastos!$BJ:$BJ) -> 0 | S75: =SUM(Tabla1[[#This Row],[october]:[december]]) -> 250548 | T75: =SUM(G75,K75,O75,S75) -> 1120358 | U75: =SUM(#REF!) -> #REF!
B76: Gastos Extras | C76: Fastmark - USA EXPRESS CS / DSV | D76: =_xlfn.XLOOKUP(C76,[3]Gastos!$B:$B,[3]Gastos!$G:$G) -> 2105886 | E76: =_xlfn.XLOOKUP(C76,[3]Gastos!$B:$B,[3]Gastos!$L:$L) -> 256534 | F76: =_xlfn.XLOOKUP(C76,[3]Gastos!$B:$B,[3]Gastos!$Q:$Q) -> 0 | G76: =SUM(Tabla1[[#This Row],[january]:[march]]) -> 2362420 | H76: =_xlfn.XLOOKUP(C76,[3]Gastos!$B:$B,[3]Gastos!$V:$V) -> 81633 | I76: =_xlfn.XLOOKUP(C76,[3]Gastos!$B:$B,[3]Gastos!$AA:$AA) -> 0 | J76: =_xlfn.XLOOKUP(C76,[3]Gastos!$B:$B,[3]Gastos!$AF:$AF) -> 1556129 | K76: =SUM(Tabla1[[#This Row],[april]:[june]]) -> 1637762 | L76: =_xlfn.XLOOKUP(C76,[3]Gastos!$B:$B,[3]Gastos!$AK:$AK) -> 0 | M76: =_xlfn.XLOOKUP(C76,[3]Gastos!$B:$B,[3]Gastos!$AP:$AP) -> 283968 | N76: =_xlfn.XLOOKUP(Tabla1[[#This Row],[Subcuenta]],[3]Gastos!$B:$B,[3]Gastos!$AU:$AU) -> 701680 | O76: =SUM(Tabla1[[#This Row],[july]:[september]]) -> 985648 | P76: =_xlfn.XLOOKUP(Tabla1[[#This Row],[Subcuenta]],[3]Gastos!$B:$B,[3]Gastos!$AZ:$AZ) -> 1246648 | Q76: =_xlfn.XLOOKUP(Tabla1[[#This Row],[Subcuenta]],[3]Gastos!$B:$B,[3]Gastos!$BE:$BE) -> 1481578 | R76: =_xlfn.XLOOKUP(Tabla1[[#This Row],[Subcuenta]],[3]Gastos!$B:$B,[3]Gastos!$BJ:$BJ) -> 1559117 | S76: =SUM(Tabla1[[#This Row],[october]:[december]]) -> 4287343 | T76: =SUM(G76,K76,O76,S76) -> 9273173
B77: Gastos Extras | C77: ALMACENAJE CS / FLETE INTERNO | D77: =_xlfn.XLOOKUP(C77,[3]Gastos!$B:$B,[3]Gastos!$G:$G) -> 0 | E77: =_xlfn.XLOOKUP(C77,[3]Gastos!$B:$B,[3]Gastos!$L:$L) -> 0 | F77: =_xlfn.XLOOKUP(C77,[3]Gastos!$B:$B,[3]Gastos!$Q:$Q) -> 0 | G77: =SUM(Tabla1[[#This Row],[january]:[march]]) -> 0 | H77: =_xlfn.XLOOKUP(C77,[3]Gastos!$B:$B,[3]Gastos!$V:$V) -> 0 | I77: =_xlfn.XLOOKUP(C77,[3]Gastos!$B:$B,[3]Gastos!$AA:$AA) -> 0 | J77: =_xlfn.XLOOKUP(C77,[3]Gastos!$B:$B,[3]Gastos!$AF:$AF) -> 239428 | K77: =SUM(Tabla1[[#This Row],[april]:[june]]) -> 239428 | L77: =_xlfn.XLOOKUP(C77,[3]Gastos!$B:$B,[3]Gastos!$AK:$AK) -> 0 | M77: =_xlfn.XLOOKUP(C77,[3]Gastos!$B:$B,[3]Gastos!$AP:$AP) -> 0 | N77: =_xlfn.XLOOKUP(Tabla1[[#This Row],[Subcuenta]],[3]Gastos!$B:$B,[3]Gastos!$AU:$AU) -> 0 | O77: =SUM(Tabla1[[#This Row],[july]:[september]]) -> 0 | P77: =_xlfn.XLOOKUP(Tabla1[[#This Row],[Subcuenta]],[3]Gastos!$B:$B,[3]Gastos!$AZ:$AZ) -> 0 | Q77: =_xlfn.XLOOKUP(Tabla1[[#This Row],[Subcuenta]],[3]Gastos!$B:$B,[3]Gastos!$BE:$BE) -> 0 | R77: =_xlfn.XLOOKUP(Tabla1[[#This Row],[Subcuenta]],[3]Gastos!$B:$B,[3]Gastos!$BJ:$BJ) -> 0 | S77: =SUM(Tabla1[[#This Row],[october]:[december]]) -> 0 | T77: =SUM(G77,K77,O77,S77) -> 239428
B78: Gastos Extras | C78: AGENCIA DE ADUANA CS | D78: =_xlfn.XLOOKUP(C78,[3]Gastos!$B:$B,[3]Gastos!$G:$G) -> 0 | E78: =_xlfn.XLOOKUP(C78,[3]Gastos!$B:$B,[3]Gastos!$L:$L) -> 0 | F78: =_xlfn.XLOOKUP(C78,[3]Gastos!$B:$B,[3]Gastos!$Q:$Q) -> 0 | G78: =SUM(Tabla1[[#This Row],[january]:[march]]) -> 0 | H78: =_xlfn.XLOOKUP(C78,[3]Gastos!$B:$B,[3]Gastos!$V:$V) -> 0 | I78: =_xlfn.XLOOKUP(C78,[3]Gastos!$B:$B,[3]Gastos!$AA:$AA) -> 0 | J78: =_xlfn.XLOOKUP(C78,[3]Gastos!$B:$B,[3]Gastos!$AF:$AF) -> 232050 | K78: =SUM(Tabla1[[#This Row],[april]:[june]]) -> 232050 | L78: =_xlfn.XLOOKUP(C78,[3]Gastos!$B:$B,[3]Gastos!$AK:$AK) -> 0 | M78: =_xlfn.XLOOKUP(C78,[3]Gastos!$B:$B,[3]Gastos!$AP:$AP) -> 0 | N78: =_xlfn.XLOOKUP(Tabla1[[#This Row],[Subcuenta]],[3]Gastos!$B:$B,[3]Gastos!$AU:$AU) -> 0 | O78: =SUM(Tabla1[[#This Row],[july]:[september]]) -> 0 | P78: =_xlfn.XLOOKUP(Tabla1[[#This Row],[Subcuenta]],[3]Gastos!$B:$B,[3]Gastos!$AZ:$AZ) -> 0 | Q78: =_xlfn.XLOOKUP(Tabla1[[#This Row],[Subcuenta]],[3]Gastos!$B:$B,[3]Gastos!$BE:$BE) -> 250548 | R78: =_xlfn.XLOOKUP(Tabla1[[#This Row],[Subcuenta]],[3]Gastos!$B:$B,[3]Gastos!$BJ:$BJ) -> 0 | S78: =SUM(Tabla1[[#This Row],[october]:[december]]) -> 250548 | T78: =SUM(G78,K78,O78,S78) -> 482598
B79: Gastos Extras | C79: TGR | D79: =_xlfn.XLOOKUP(C79,[3]Gastos!$B:$B,[3]Gastos!$G:$G) -> 0 | E79: =_xlfn.XLOOKUP(C79,[3]Gastos!$B:$B,[3]Gastos!$L:$L) -> 0 | F79: =_xlfn.XLOOKUP(C79,[3]Gastos!$B:$B,[3]Gastos!$Q:$Q) -> 0 | G79: =SUM(Tabla1[[#This Row],[january]:[march]]) -> 0 | H79: =_xlfn.XLOOKUP(C79,[3]Gastos!$B:$B,[3]Gastos!$V:$V) -> 0 | I79: =_xlfn.XLOOKUP(C79,[3]Gastos!$B:$B,[3]Gastos!$AA:$AA) -> 0 | J79: =_xlfn.XLOOKUP(C79,[3]Gastos!$B:$B,[3]Gastos!$AF:$AF) -> 606907 | K79: =SUM(Tabla1[[#This Row],[april]:[june]]) -> 606907 | L79: =_xlfn.XLOOKUP(C79,[3]Gastos!$B:$B,[3]Gastos!$AK:$AK) -> 0 | M79: =_xlfn.XLOOKUP(C79,[3]Gastos!$B:$B,[3]Gastos!$AP:$AP) -> 0 | N79: =_xlfn.XLOOKUP(Tabla1[[#This Row],[Subcuenta]],[3]Gastos!$B:$B,[3]Gastos!$AU:$AU) -> 0 | O79: =SUM(Tabla1[[#This Row],[july]:[september]]) -> 0 | P79: =_xlfn.XLOOKUP(Tabla1[[#This Row],[Subcuenta]],[3]Gastos!$B:$B,[3]Gastos!$AZ:$AZ) -> 0 | Q79: =_xlfn.XLOOKUP(Tabla1[[#This Row],[Subcuenta]],[3]Gastos!$B:$B,[3]Gastos!$BE:$BE) -> 1741084 | R79: =_xlfn.XLOOKUP(Tabla1[[#This Row],[Subcuenta]],[3]Gastos!$B:$B,[3]Gastos!$BJ:$BJ) -> 0 | S79: =SUM(Tabla1[[#This Row],[october]:[december]]) -> 1741084 | T79: =SUM(G79,K79,O79,S79) -> 2347991
B80: Gastos Extras | C80: SUELDO CLAUDIA BLANCO / IMPOSICIONES CS | D80: =_xlfn.XLOOKUP(C80,[3]Gastos!$B:$B,[3]Gastos!$G:$G) -> 4039479 | E80: =_xlfn.XLOOKUP(C80,[3]Gastos!$B:$B,[3]Gastos!$L:$L) -> 4039704 | F80: =_xlfn.XLOOKUP(C80,[3]Gastos!$B:$B,[3]Gastos!$Q:$Q) -> 3289505 | G80: =SUM(Tabla1[[#This Row],[january]:[march]]) -> 11368688 | H80: =_xlfn.XLOOKUP(C80,[3]Gastos!$B:$B,[3]Gastos!$V:$V) -> 3263589 | I80: =_xlfn.XLOOKUP(C80,[3]Gastos!$B:$B,[3]Gastos!$AA:$AA) -> 3390065 | J80: =_xlfn.XLOOKUP(C80,[3]Gastos!$B:$B,[3]Gastos!$AF:$AF) -> 3452660 | K80: =SUM(Tabla1[[#This Row],[april]:[june]]) -> 10106314 | L80: =_xlfn.XLOOKUP(C80,[3]Gastos!$B:$B,[3]Gastos!$AK:$AK) -> 3440192 | M80: =_xlfn.XLOOKUP(C80,[3]Gastos!$B:$B,[3]Gastos!$AP:$AP) -> 4261203.8 | N80: =_xlfn.XLOOKUP(Tabla1[[#This Row],[Subcuenta]],[3]Gastos!$B:$B,[3]Gastos!$AU:$AU) -> 6272534.5 | O80: =SUM(Tabla1[[#This Row],[july]:[september]]) -> 13973930 | P80: =_xlfn.XLOOKUP(Tabla1[[#This Row],[Subcuenta]],[3]Gastos!$B:$B,[3]Gastos!$AZ:$AZ) -> 6291267.5 | Q80: =_xlfn.XLOOKUP(Tabla1[[#This Row],[Subcuenta]],[3]Gastos!$B:$B,[3]Gastos!$BE:$BE) -> 6325531.7 | R80: =_xlfn.XLOOKUP(Tabla1[[#This Row],[Subcuenta]],[3]Gastos!$B:$B,[3]Gastos!$BJ:$BJ) -> 6340726 | S80: =SUM(Tabla1[[#This Row],[october]:[december]]) -> 18957525 | T80: =SUM(G80,K80,O80,S80) -> 54406458
B81: Gastos Extras | C81: GASTOS CS (BANCO SECURITY - INTERNACIONAL) | D81: =_xlfn.XLOOKUP(C81,[3]Gastos!$B:$B,[3]Gastos!$G:$G) -> 58569881 | E81: =_xlfn.XLOOKUP(C81,[3]Gastos!$B:$B,[3]Gastos!$L:$L) -> 67420824 | F81: =_xlfn.XLOOKUP(C81,[3]Gastos!$B:$B,[3]Gastos!$Q:$Q) -> 24342789 | G81: =SUM(Tabla1[[#This Row],[january]:[march]]) -> 150333494 | H81: =_xlfn.XLOOKUP(C81,[3]Gastos!$B:$B,[3]Gastos!$V:$V) -> 47353484 | I81: =_xlfn.XLOOKUP(C81,[3]Gastos!$B:$B,[3]Gastos!$AA:$AA) -> 38946156 | J81: =_xlfn.XLOOKUP(C81,[3]Gastos!$B:$B,[3]Gastos!$AF:$AF) -> 12546857 | K81: =SUM(Tabla1[[#This Row],[april]:[june]]) -> 98846497 | L81: =_xlfn.XLOOKUP(C81,[3]Gastos!$B:$B,[3]Gastos!$AK:$AK) -> 37979581 | M81: =_xlfn.XLOOKUP(C81,[3]Gastos!$B:$B,[3]Gastos!$AP:$AP) -> 22826698 | N81: =_xlfn.XLOOKUP(Tabla1[[#This Row],[Subcuenta]],[3]Gastos!$B:$B,[3]Gastos!$AU:$AU) -> 27210785 | O81: =SUM(Tabla1[[#This Row],[july]:[september]]) -> 88017064 | P81: =_xlfn.XLOOKUP(Tabla1[[#This Row],[Subcuenta]],[3]Gastos!$B:$B,[3]Gastos!$AZ:$AZ) -> 24848543 | Q81: =_xlfn.XLOOKUP(Tabla1[[#This Row],[Subcuenta]],[3]Gastos!$B:$B,[3]Gastos!$BE:$BE) -> 14223027 | R81: =_xlfn.XLOOKUP(Tabla1[[#This Row],[Subcuenta]],[3]Gastos!$B:$B,[3]Gastos!$BJ:$BJ) -> 137958420 | S81: =SUM(Tabla1[[#This Row],[october]:[december]]) -> 177029990 | T81: =SUM(G81,K81,O81,S81) -> 514227045
B82: Gastos Extras | C82: ENTEL CLAUDIA Y TERESA | D82: =_xlfn.XLOOKUP(C82,[3]Gastos!$B:$B,[3]Gastos!$G:$G) -> 18585 | E82: =_xlfn.XLOOKUP(C82,[3]Gastos!$B:$B,[3]Gastos!$L:$L) -> 22337 | F82: =_xlfn.XLOOKUP(C82,[3]Gastos!$B:$B,[3]Gastos!$Q:$Q) -> 21832 | G82: =SUM(Tabla1[[#This Row],[january]:[march]]) -> 62754 | H82: =_xlfn.XLOOKUP(C82,[3]Gastos!$B:$B,[3]Gastos!$V:$V) -> 21884 | I82: =_xlfn.XLOOKUP(C82,[3]Gastos!$B:$B,[3]Gastos!$AA:$AA) -> 21832 | J82: =_xlfn.XLOOKUP(C82,[3]Gastos!$B:$B,[3]Gastos!$AF:$AF) -> 22493 | K82: =SUM(Tabla1[[#This Row],[april]:[june]]) -> 66209 | L82: =_xlfn.XLOOKUP(C82,[3]Gastos!$B:$B,[3]Gastos!$AK:$AK) -> 28361 | M82: =_xlfn.XLOOKUP(C82,[3]Gastos!$B:$B,[3]Gastos!$AP:$AP) -> 23842 | N82: =_xlfn.XLOOKUP(Tabla1[[#This Row],[Subcuenta]],[3]Gastos!$B:$B,[3]Gastos!$AU:$AU) -> 22084 | O82: =SUM(Tabla1[[#This Row],[july]:[september]]) -> 74287 | P82: =_xlfn.XLOOKUP(Tabla1[[#This Row],[Subcuenta]],[3]Gastos!$B:$B,[3]Gastos!$AZ:$AZ) -> 21924 | Q82: =_xlfn.XLOOKUP(Tabla1[[#This Row],[Subcuenta]],[3]Gastos!$B:$B,[3]Gastos!$BE:$BE) -> 21832 | R82: =_xlfn.XLOOKUP(Tabla1[[#This Row],[Subcuenta]],[3]Gastos!$B:$B,[3]Gastos!$BJ:$BJ) -> 21832 | S82: =SUM(Tabla1[[#This Row],[october]:[december]]) -> 65588 | T82: =SUM(G82,K82,O82,S82) -> 268838
B83: Gastos Extras | C83: VERISURE SRA. TERESA | D83: =_xlfn.XLOOKUP(C83,[3]Gastos!$B:$B,[3]Gastos!$G:$G) -> 47214 | E83: =_xlfn.XLOOKUP(C83,[3]Gastos!$B:$B,[3]Gastos!$L:$L) -> 47456 | F83: =_xlfn.XLOOKUP(C83,[3]Gastos!$B:$B,[3]Gastos!$Q:$Q) -> 47763 | G83: =SUM(Tabla1[[#This Row],[january]:[march]]) -> 142433 | H83: =_xlfn.XLOOKUP(C83,[3]Gastos!$B:$B,[3]Gastos!$V:$V) -> 47837 | I83: =_xlfn.XLOOKUP(C83,[3]Gastos!$B:$B,[3]Gastos!$AA:$AA) -> 48210 | J83: =_xlfn.XLOOKUP(C83,[3]Gastos!$B:$B,[3]Gastos!$AF:$AF) -> 48458 | K83: =SUM(Tabla1[[#This Row],[april]:[june]]) -> 144505 | L83: =_xlfn.XLOOKUP(C83,[3]Gastos!$B:$B,[3]Gastos!$AK:$AK) -> 48531 | M83: =_xlfn.XLOOKUP(C83,[3]Gastos!$B:$B,[3]Gastos!$AP:$AP) -> 48469 | N83: =_xlfn.XLOOKUP(Tabla1[[#This Row],[Subcuenta]],[3]Gastos!$B:$B,[3]Gastos!$AU:$AU) -> 48591 | O83: =SUM(Tabla1[[#This Row],[july]:[september]]) -> 145591 | P83: =_xlfn.XLOOKUP(Tabla1[[#This Row],[Subcuenta]],[3]Gastos!$B:$B,[3]Gastos!$AZ:$AZ) -> 48676 | Q83: =_xlfn.XLOOKUP(Tabla1[[#This Row],[Subcuenta]],[3]Gastos!$B:$B,[3]Gastos!$BE:$BE) -> 48942 | R83: =_xlfn.XLOOKUP(Tabla1[[#This Row],[Subcuenta]],[3]Gastos!$B:$B,[3]Gastos!$BJ:$BJ) -> 49174 | S83: =SUM(Tabla1[[#This Row],[october]:[december]]) -> 146792 | T83: =SUM(G83,K83,O83,S83) -> 579321
B84: Gastos Extras | C84: SERVIPAG | D84: =_xlfn.XLOOKUP(C84,[3]Gastos!$B:$B,[3]Gastos!$G:$G) -> 100095 | E84: =_xlfn.XLOOKUP(C84,[3]Gastos!$B:$B,[3]Gastos!$L:$L) -> 41301 | F84: =_xlfn.XLOOKUP(C84,[3]Gastos!$B:$B,[3]Gastos!$Q:$Q) -> 228626 | G84: =SUM(Tabla1[[#This Row],[january]:[march]]) -> 370022 | H84: =_xlfn.XLOOKUP(C84,[3]Gastos!$B:$B,[3]Gastos!$V:$V) -> 136991 | I84: =_xlfn.XLOOKUP(C84,[3]Gastos!$B:$B,[3]Gastos!$AA:$AA) -> 59200 | J84: =_xlfn.XLOOKUP(C84,[3]Gastos!$B:$B,[3]Gastos!$AF:$AF) -> 93744 | K84: =SUM(Tabla1[[#This Row],[april]:[june]]) -> 289935 | L84: =_xlfn.XLOOKUP(C84,[3]Gastos!$B:$B,[3]Gastos!$AK:$AK) -> 56375 | M84: =_xlfn.XLOOKUP(C84,[3]Gastos!$B:$B,[3]Gastos!$AP:$AP) -> 130693 | N84: =_xlfn.XLOOKUP(Tabla1[[#This Row],[Subcuenta]],[3]Gastos!$B:$B,[3]Gastos!$AU:$AU) -> 314897 | O84: =SUM(Tabla1[[#This Row],[july]:[september]]) -> 501965 | P84: =_xlfn.XLOOKUP(Tabla1[[#This Row],[Subcuenta]],[3]Gastos!$B:$B,[3]Gastos!$AZ:$AZ) -> 104016 | Q84: =_xlfn.XLOOKUP(Tabla1[[#This Row],[Subcuenta]],[3]Gastos!$B:$B,[3]Gastos!$BE:$BE) -> 334467 | R84: =_xlfn.XLOOKUP(Tabla1[[#This Row],[Subcuenta]],[3]Gastos!$B:$B,[3]Gastos!$BJ:$BJ) -> 247895 | S84: =SUM(Tabla1[[#This Row],[october]:[december]]) -> 686378 | T84: =SUM(G84,K84,O84,S84) -> 1848300
B85: Gastos Extras | C85: ABOGADOS CS / NOTARIA | D85: =_xlfn.XLOOKUP(C85,[3]Gastos!$B:$B,[3]Gastos!$G:$G) -> 180000 | E85: =_xlfn.XLOOKUP(C85,[3]Gastos!$B:$B,[3]Gastos!$L:$L) -> 257632 | F85: =_xlfn.XLOOKUP(C85,[3]Gastos!$B:$B,[3]Gastos!$Q:$Q) -> 26000 | G85: =SUM(Tabla1[[#This Row],[january]:[march]]) -> 463632 | H85: =_xlfn.XLOOKUP(C85,[3]Gastos!$B:$B,[3]Gastos!$V:$V) -> 0 | I85: =_xlfn.XLOOKUP(C85,[3]Gastos!$B:$B,[3]Gastos!$AA:$AA) -> 280000 | J85: =_xlfn.XLOOKUP(C85,[3]Gastos!$B:$B,[3]Gastos!$AF:$AF) -> 237000 | K85: =SUM(Tabla1[[#This Row],[april]:[june]]) -> 517000 | L85: =_xlfn.XLOOKUP(C85,[3]Gastos!$B:$B,[3]Gastos!$AK:$AK) -> 534882 | M85: =_xlfn.XLOOKUP(C85,[3]Gastos!$B:$B,[3]Gastos!$AP:$AP) -> 0 | N85: =_xlfn.XLOOKUP(Tabla1[[#This Row],[Subcuenta]],[3]Gastos!$B:$B,[3]Gastos!$AU:$AU) -> 0 | O85: =SUM(Tabla1[[#This Row],[july]:[september]]) -> 534882 | P85: =_xlfn.XLOOKUP(Tabla1[[#This Row],[Subcuenta]],[3]Gastos!$B:$B,[3]Gastos!$AZ:$AZ) -> 407026 | Q85: =_xlfn.XLOOKUP(Tabla1[[#This Row],[Subcuenta]],[3]Gastos!$B:$B,[3]Gastos!$BE:$BE) -> 0 | R85: =_xlfn.XLOOKUP(Tabla1[[#This Row],[Subcuenta]],[3]Gastos!$B:$B,[3]Gastos!$BJ:$BJ) -> 926600 | S85: =SUM(Tabla1[[#This Row],[october]:[december]]) -> 1333626 | T85: =SUM(G85,K85,O85,S85) -> 2849140
B86: Gastos Extras | C86: GASTOS TERRENOS NATALIO STEIN / LAS GOLONDRINAS / LOS SUEÑOS | D86: =_xlfn.XLOOKUP(C86,[3]Gastos!$B:$B,[3]Gastos!$G:$G) -> 0 | E86: =_xlfn.XLOOKUP(C86,[3]Gastos!$B:$B,[3]Gastos!$L:$L) -> 0 | F86: =_xlfn.XLOOKUP(C86,[3]Gastos!$B:$B,[3]Gastos!$Q:$Q) -> 1379310 | G86: =SUM(Tabla1[[#This Row],[january]:[march]]) -> 1379310 | H86: =_xlfn.XLOOKUP(C86,[3]Gastos!$B:$B,[3]Gastos!$V:$V) -> 2631975 | I86: =_xlfn.XLOOKUP(C86,[3]Gastos!$B:$B,[3]Gastos!$AA:$AA) -> 1111543 | J86: =_xlfn.XLOOKUP(C86,[3]Gastos!$B:$B,[3]Gastos!$AF:$AF) -> 1200000 | K86: =SUM(Tabla1[[#This Row],[april]:[june]]) -> 4943518 | L86: =_xlfn.XLOOKUP(C86,[3]Gastos!$B:$B,[3]Gastos!$AK:$AK) -> 1111543 | M86: =_xlfn.XLOOKUP(C86,[3]Gastos!$B:$B,[3]Gastos!$AP:$AP) -> 150091 | N86: =_xlfn.XLOOKUP(Tabla1[[#This Row],[Subcuenta]],[3]Gastos!$B:$B,[3]Gastos!$AU:$AU) -> 0 | O86: =SUM(Tabla1[[#This Row],[july]:[september]]) -> 1261634 | P86: =_xlfn.XLOOKUP(Tabla1[[#This Row],[Subcuenta]],[3]Gastos!$B:$B,[3]Gastos!$AZ:$AZ) -> 0 | Q86: =_xlfn.XLOOKUP(Tabla1[[#This Row],[Subcuenta]],[3]Gastos!$B:$B,[3]Gastos!$BE:$BE) -> 0 | R86: =_xlfn.XLOOKUP(Tabla1[[#This Row],[Subcuenta]],[3]Gastos!$B:$B,[3]Gastos!$BJ:$BJ) -> 320000 | S86: =SUM(Tabla1[[#This Row],[october]:[december]]) -> 320000 | T86: =SUM(G86,K86,O86,S86) -> 7904462
B87: Gastos Extras | C87: Gastos extras de rendiciones | D87: =_xlfn.XLOOKUP(C87,[3]Gastos!$B:$B,[3]Gastos!$G:$G) -> 1521095 | E87: =_xlfn.XLOOKUP(C87,[3]Gastos!$B:$B,[3]Gastos!$L:$L) -> 6107971 | F87: =_xlfn.XLOOKUP(C87,[3]Gastos!$B:$B,[3]Gastos!$Q:$Q) -> 1681157 | G87: =SUM(Tabla1[[#This Row],[january]:[march]]) -> 9310223 | H87: =_xlfn.XLOOKUP(C87,[3]Gastos!$B:$B,[3]Gastos!$V:$V) -> 2773748 | I87: =_xlfn.XLOOKUP(C87,[3]Gastos!$B:$B,[3]Gastos!$AA:$AA) -> 4031092 | J87: =_xlfn.XLOOKUP(C87,[3]Gastos!$B:$B,[3]Gastos!$AF:$AF) -> 991569 | K87: =SUM(Tabla1[[#This Row],[april]:[june]]) -> 7796409 | L87: =_xlfn.XLOOKUP(C87,[3]Gastos!$B:$B,[3]Gastos!$AK:$AK) -> 7891815 | M87: =_xlfn.XLOOKUP(C87,[3]Gastos!$B:$B,[3]Gastos!$AP:$AP) -> 8343605.3 | N87: =_xlfn.XLOOKUP(Tabla1[[#This Row],[Subcuenta]],[3]Gastos!$B:$B,[3]Gastos!$AU:$AU) -> 962410 | O87: =SUM(Tabla1[[#This Row],[july]:[september]]) -> 17197830 | P87: =_xlfn.XLOOKUP(Tabla1[[#This Row],[Subcuenta]],[3]Gastos!$B:$B,[3]Gastos!$AZ:$AZ) -> 106376 | Q87: =_xlfn.XLOOKUP(Tabla1[[#This Row],[Subcuenta]],[3]Gastos!$B:$B,[3]Gastos!$BE:$BE) -> 271183.17 | R87: =_xlfn.XLOOKUP(Tabla1[[#This Row],[Subcuenta]],[3]Gastos!$B:$B,[3]Gastos!$BJ:$BJ) -> 1225440 | S87: =SUM(Tabla1[[#This Row],[october]:[december]]) -> 1602999.2 | T87: =SUM(G87,K87,O87,S87) -> 35907461
... B97: Gastos Extras | C97: Adolfo Raul Quintana Giannoni OP | D97: =_xlfn.XLOOKUP(C97,[3]Gastos!$B:$B,[3]Gastos!$G:$G) -> 4073609 | E97: =_xlfn.XLOOKUP(C97,[3]Gastos!$B:$B,[3]Gastos!$L:$L) -> 4070359.2 | F97: =_xlfn.XLOOKUP(C97,[3]Gastos!$B:$B,[3]Gastos!$Q:$Q) -> 4069396.9 | G97: =SUM(Tabla1[[#This Row],[january]:[march]]) -> 12213365 | H97: =_xlfn.XLOOKUP(C97,[3]Gastos!$B:$B,[3]Gastos!$V:$V) -> 4065548.9 | I97: =_xlfn.XLOOKUP(C97,[3]Gastos!$B:$B,[3]Gastos!$AA:$AA) -> 4062706.5 | J97: =_xlfn.XLOOKUP(C97,[3]Gastos!$B:$B,[3]Gastos!$AF:$AF) -> 4058631.9 | K97: =SUM(Tabla1[[#This Row],[april]:[june]]) -> 12186887 | L97: =_xlfn.XLOOKUP(C97,[3]Gastos!$B:$B,[3]Gastos!$AK:$AK) -> 4069913.4 | M97: =_xlfn.XLOOKUP(C97,[3]Gastos!$B:$B,[3]Gastos!$AP:$AP) -> 4068717.3 | N97: =_xlfn.XLOOKUP(Tabla1[[#This Row],[Subcuenta]],[3]Gastos!$B:$B,[3]Gastos!$AU:$AU) -> 4277352.6 | O97: =SUM(Tabla1[[#This Row],[july]:[september]]) -> 12415983 | P97: =_xlfn.XLOOKUP(Tabla1[[#This Row],[Subcuenta]],[3]Gastos!$B:$B,[3]Gastos!$AZ:$AZ) -> 4072048.2 | Q97: =_xlfn.XLOOKUP(Tabla1[[#This Row],[Subcuenta]],[3]Gastos!$B:$B,[3]Gastos!$BE:$BE) -> 4069461.6 | R97: =_xlfn.XLOOKUP(Tabla1[[#This Row],[Subcuenta]],[3]Gastos!$B:$B,[3]Gastos!$BJ:$BJ) -> 4319267.4 | S97: =SUM(Tabla1[[#This Row],[october]:[december]]) -> 12460777 | T97: =SUM(G97,K97,O97,S97) -> 49277013
B98: Gastos Extras | C98: Lara Schroeder OP | K98: =SUM(Tabla1[[#This Row],[april]:[june]]) -> 0 | L98: =_xlfn.XLOOKUP(C98,[3]Gastos!$B:$B,[3]Gastos!$AK:$AK) -> 1009788 | M98: =_xlfn.XLOOKUP(C98,[3]Gastos!$B:$B,[3]Gastos!$AP:$AP) -> 1009788 | N98: =_xlfn.XLOOKUP(Tabla1[[#This Row],[Subcuenta]],[3]Gastos!$B:$B,[3]Gastos!$AU:$AU) -> 1016312.4 | O98: =SUM(Tabla1[[#This Row],[july]:[september]]) -> 3035888.4 | P98: =_xlfn.XLOOKUP(Tabla1[[#This Row],[Subcuenta]],[3]Gastos!$B:$B,[3]Gastos!$AZ:$AZ) -> 1016312.4 | Q98: =_xlfn.XLOOKUP(Tabla1[[#This Row],[Subcuenta]],[3]Gastos!$B:$B,[3]Gastos!$BE:$BE) -> 1010369.8 | R98: =_xlfn.XLOOKUP(Tabla1[[#This Row],[Subcuenta]],[3]Gastos!$B:$B,[3]Gastos!$BJ:$BJ) -> 1010369.8 | S98: =SUM(Tabla1[[#This Row],[october]:[december]]) -> 3037052.1 | T98: =SUM(G98,K98,O98,S98) -> 6072940.5
B99: Gastos Extras | C99: Alfonso Camps Nielsen OP | J99: =_xlfn.XLOOKUP(C99,[3]Gastos!$B:$B,[3]Gastos!$AF:$AF) -> 2975463 | K99: =SUM(Tabla1[[#This Row],[april]:[june]]) -> 2975463 | L99: =_xlfn.XLOOKUP(C99,[3]Gastos!$B:$B,[3]Gastos!$AK:$AK) -> 0 | M99: =_xlfn.XLOOKUP(C99,[3]Gastos!$B:$B,[3]Gastos!$AP:$AP) -> 0 | N99: =_xlfn.XLOOKUP(Tabla1[[#This Row],[Subcuenta]],[3]Gastos!$B:$B,[3]Gastos!$AU:$AU) -> 0 | O99: =SUM(Tabla1[[#This Row],[july]:[september]]) -> 0 | P99: =_xlfn.XLOOKUP(Tabla1[[#This Row],[Subcuenta]],[3]Gastos!$B:$B,[3]Gastos!$AZ:$AZ) -> 0 | Q99: =_xlfn.XLOOKUP(Tabla1[[#This Row],[Subcuenta]],[3]Gastos!$B:$B,[3]Gastos!$BE:$BE) -> 0 | R99: =_xlfn.XLOOKUP(Tabla1[[#This Row],[Subcuenta]],[3]Gastos!$B:$B,[3]Gastos!$BJ:$BJ) -> 0 | S99: =SUM(Tabla1[[#This Row],[october]:[december]]) -> 0 | T99: =SUM(G99,K99,O99,S99) -> 2975463
B100: Gastos Extras | C100: Aleibys Veronica Rodriguez Lopez OP | J100: =_xlfn.XLOOKUP(C100,[3]Gastos!$B:$B,[3]Gastos!$AF:$AF) -> 0 | K100: =SUM(Tabla1[[#This Row],[april]:[june]]) -> 0 | L100: =_xlfn.XLOOKUP(C100,[3]Gastos!$B:$B,[3]Gastos!$AK:$AK) -> 850168.57 | M100: =_xlfn.XLOOKUP(C100,[3]Gastos!$B:$B,[3]Gastos!$AP:$AP) -> 724333.07 | N100: =_xlfn.XLOOKUP(Tabla1[[#This Row],[Subcuenta]],[3]Gastos!$B:$B,[3]Gastos!$AU:$AU) -> 1004656.9 | O100: =SUM(Tabla1[[#This Row],[july]:[september]]) -> 2579158.5 | P100: =_xlfn.XLOOKUP(Tabla1[[#This Row],[Subcuenta]],[3]Gastos!$B:$B,[3]Gastos!$AZ:$AZ) -> 683015.29 | Q100: =_xlfn.XLOOKUP(Tabla1[[#This Row],[Subcuenta]],[3]Gastos!$B:$B,[3]Gastos!$BE:$BE) -> 840184.56 | R100: =_xlfn.XLOOKUP(Tabla1[[#This Row],[Subcuenta]],[3]Gastos!$B:$B,[3]Gastos!$BJ:$BJ) -> 1057858 | S100: =SUM(Tabla1[[#This Row],[october]:[december]]) -> 2581057.9 | T100: =SUM(G100,K100,O100,S100) -> 5160216.4
B101: Gastos Extras | C101: Teresa Espinoza Cerón | D101: =_xlfn.XLOOKUP(C101,[3]Gastos!$B:$B,[3]Gastos!$G:$G) -> 0 | E101: =_xlfn.XLOOKUP(C101,[3]Gastos!$B:$B,[3]Gastos!$L:$L) -> 0 | F101: =_xlfn.XLOOKUP(C101,[3]Gastos!$B:$B,[3]Gastos!$Q:$Q) -> 0 | G101: =SUM(Tabla1[[#This Row],[january]:[march]]) -> 0 | H101: =_xlfn.XLOOKUP(C101,[3]Gastos!$B:$B,[3]Gastos!$V:$V) -> 0 | I101: =_xlfn.XLOOKUP(C101,[3]Gastos!$B:$B,[3]Gastos!$AA:$AA) -> 0 | J101: =_xlfn.XLOOKUP(C101,[3]Gastos!$B:$B,[3]Gastos!$AF:$AF) -> 0 | K101: =SUM(Tabla1[[#This Row],[april]:[june]]) -> 0 | L101: =_xlfn.XLOOKUP(C101,[3]Gastos!$B:$B,[3]Gastos!$AK:$AK) -> 0 | M101: =_xlfn.XLOOKUP(C101,[3]Gastos!$B:$B,[3]Gastos!$AP:$AP) -> 0 | N101: =_xlfn.XLOOKUP(Tabla1[[#This Row],[Subcuenta]],[3]Gastos!$B:$B,[3]Gastos!$AU:$AU) -> 775510 | O101: =SUM(Tabla1[[#This Row],[july]:[september]]) -> 775510 | P101: =_xlfn.XLOOKUP(Tabla1[[#This Row],[Subcuenta]],[3]Gastos!$B:$B,[3]Gastos!$AZ:$AZ) -> 775510 | Q101: =_xlfn.XLOOKUP(Tabla1[[#This Row],[Subcuenta]],[3]Gastos!$B:$B,[3]Gastos!$BE:$BE) -> 775510 | R101: =_xlfn.XLOOKUP(Tabla1[[#This Row],[Subcuenta]],[3]Gastos!$B:$B,[3]Gastos!$BJ:$BJ) -> 816250.43 | S101: =SUM(Tabla1[[#This Row],[october]:[december]]) -> 2367270.4 | T101: =SUM(G101,K101,O101,S101) -> 3142780.4
B102: Gastos Extras | C102: Castaña Niñoles Díaz OP | D102: =_xlfn.XLOOKUP(C102,[3]Gastos!$B:$B,[3]Gastos!$G:$G) -> 0 | E102: =_xlfn.XLOOKUP(C102,[3]Gastos!$B:$B,[3]Gastos!$L:$L) -> 0 | F102: =_xlfn.XLOOKUP(C102,[3]Gastos!$B:$B,[3]Gastos!$Q:$Q) -> 0 | G102: =SUM(Tabla1[[#This Row],[january]:[march]]) -> 0 | H102: =_xlfn.XLOOKUP(C102,[3]Gastos!$B:$B,[3]Gastos!$V:$V) -> 0 | I102: =_xlfn.XLOOKUP(C102,[3]Gastos!$B:$B,[3]Gastos!$AA:$AA) -> 0 | J102: =_xlfn.XLOOKUP(C102,[3]Gastos!$B:$B,[3]Gastos!$AF:$AF) -> 0 | K102: =SUM(Tabla1[[#This Row],[april]:[june]]) -> 0 | L102: =_xlfn.XLOOKUP(C102,[3]Gastos!$B:$B,[3]Gastos!$AK:$AK) -> 0 | M102: =_xlfn.XLOOKUP(C102,[3]Gastos!$B:$B,[3]Gastos!$AP:$AP) -> 0 | O102: =SUM(Tabla1[[#This Row],[july]:[september]]) -> 0 | P102: =_xlfn.XLOOKUP(Tabla1[[#This Row],[Subcuenta]],[3]Gastos!$B:$B,[3]Gastos!$AZ:$AZ) -> 1712057.3 | Q102: =_xlfn.XLOOKUP(Tabla1[[#This Row],[Subcuenta]],[3]Gastos!$B:$B,[3]Gastos!$BE:$BE) -> 1439419.9 | R102: =_xlfn.XLOOKUP(Tabla1[[#This Row],[Subcuenta]],[3]Gastos!$B:$B,[3]Gastos!$BJ:$BJ) -> 51137.5 | S102: =SUM(Tabla1[[#This Row],[october]:[december]]) -> 3202614.7 | T102: =SUM(G102,K102,O102,S102) -> 3202614.7
B103: Gastos Extras | C103: Austerlitz Eduardo Capriles Rodriguez OP | D103: =_xlfn.XLOOKUP(C103,[3]Gastos!$B:$B,[3]Gastos!$G:$G) -> 0 | E103: =_xlfn.XLOOKUP(C103,[3]Gastos!$B:$B,[3]Gastos!$L:$L) -> 0 | F103: =_xlfn.XLOOKUP(C103,[3]Gastos!$B:$B,[3]Gastos!$Q:$Q) -> 0 | G103: =SUM(Tabla1[[#This Row],[january]:[march]]) -> 0 | H103: =_xlfn.XLOOKUP(C103,[3]Gastos!$B:$B,[3]Gastos!$V:$V) -> 0 | I103: =_xlfn.XLOOKUP(C103,[3]Gastos!$B:$B,[3]Gastos!$AA:$AA) -> 0 | J103: =_xlfn.XLOOKUP(C103,[3]Gastos!$B:$B,[3]Gastos!$AF:$AF) -> 0 | K103: =SUM(Tabla1[[#This Row],[april]:[june]]) -> 0 | L103: =_xlfn.XLOOKUP(C103,[3]Gastos!$B:$B,[3]Gastos!$AK:$AK) -> 0 | M103: =_xlfn.XLOOKUP(C103,[3]Gastos!$B:$B,[3]Gastos!$AP:$AP) -> 0 | O103: =SUM(Tabla1[[#This Row],[july]:[september]]) -> 0 | P103: =_xlfn.XLOOKUP(Tabla1[[#This Row],[Subcuenta]],[3]Gastos!$B:$B,[3]Gastos!$AZ:$AZ) -> 1919817 | Q103: =_xlfn.XLOOKUP(Tabla1[[#This Row],[Subcuenta]],[3]Gastos!$B:$B,[3]Gastos!$BE:$BE) -> 1985863 | R103: =_xlfn.XLOOKUP(Tabla1[[#This Row],[Subcuenta]],[3]Gastos!$B:$B,[3]Gastos!$BJ:$BJ) -> 1985863 | S103: =SUM(Tabla1[[#This Row],[october]:[december]]) -> 5891543.1 | T103: =SUM(G103,K103,O103,S103) -> 5891543.1
B104: Gastos Extras | C104: ORCI LATAM HOLDING / BARONI CONSULTORES/ Adsformance | D104: =_xlfn.XLOOKUP(C104,[3]Gastos!$B:$B,[3]Gastos!$G:$G) -> 629821 | E104: =_xlfn.XLOOKUP(C104,[3]Gastos!$B:$B,[3]Gastos!$L:$L) -> 632406 | F104: =_xlfn.XLOOKUP(C104,[3]Gastos!$B:$B,[3]Gastos!$Q:$Q) -> 635042 | G104: =SUM(Tabla1[[#This Row],[january]:[march]]) -> 1897269 | H104: =_xlfn.XLOOKUP(C104,[3]Gastos!$B:$B,[3]Gastos!$V:$V) -> 637622 | I104: =_xlfn.XLOOKUP(C104,[3]Gastos!$B:$B,[3]Gastos!$AA:$AA) -> 642380 | J104: =_xlfn.XLOOKUP(C104,[3]Gastos!$B:$B,[3]Gastos!$AF:$AF) -> 643833 | K104: =SUM(Tabla1[[#This Row],[april]:[june]]) -> 1923835 | L104: =_xlfn.XLOOKUP(C104,[3]Gastos!$B:$B,[3]Gastos!$AK:$AK) -> 1500733 | M104: =_xlfn.XLOOKUP(C104,[3]Gastos!$B:$B,[3]Gastos!$AP:$AP) -> 644014 | N104: =_xlfn.XLOOKUP(Tabla1[[#This Row],[Subcuenta]],[3]Gastos!$B:$B,[3]Gastos!$AU:$AU) -> 645911 | O104: =SUM(Tabla1[[#This Row],[july]:[september]]) -> 2790658 | P104: =_xlfn.XLOOKUP(Tabla1[[#This Row],[Subcuenta]],[3]Gastos!$B:$B,[3]Gastos!$AZ:$AZ) -> 7326535 | Q104: =_xlfn.XLOOKUP(Tabla1[[#This Row],[Subcuenta]],[3]Gastos!$B:$B,[3]Gastos!$BE:$BE) -> 651798 | R104: =_xlfn.XLOOKUP(Tabla1[[#This Row],[Subcuenta]],[3]Gastos!$B:$B,[3]Gastos!$BJ:$BJ) -> 7319066 | S104: =SUM(Tabla1[[#This Row],[october]:[december]]) -> 15297399 | T104: =SUM(G104,K104,O104,S104) -> 21909161
B105: Gastos Extras | C105: GASTOS DE EXPORTACIONES ARGENTINA | D105: =_xlfn.XLOOKUP(C105,[3]Gastos!$B:$B,[3]Gastos!$G:$G) -> 1883324 | E105: =_xlfn.XLOOKUP(C105,[3]Gastos!$B:$B,[3]Gastos!$L:$L) -> 718345 | F105: =_xlfn.XLOOKUP(C105,[3]Gastos!$B:$B,[3]Gastos!$Q:$Q) -> 762045 | G105: =SUM(Tabla1[[#This Row],[january]:[march]]) -> 3363714 | H105: =_xlfn.XLOOKUP(C105,[3]Gastos!$B:$B,[3]Gastos!$V:$V) -> 1336763 | I105: =_xlfn.XLOOKUP(C105,[3]Gastos!$B:$B,[3]Gastos!$AA:$AA) -> 198400 | J105: =_xlfn.XLOOKUP(C105,[3]Gastos!$B:$B,[3]Gastos!$AF:$AF) -> 561526 | K105: =SUM(Tabla1[[#This Row],[april]:[june]]) -> 2096689 | L105: =_xlfn.XLOOKUP(C105,[3]Gastos!$B:$B,[3]Gastos!$AK:$AK) -> 1517575 | M105: =_xlfn.XLOOKUP(C105,[3]Gastos!$B:$B,[3]Gastos!$AP:$AP) -> 595200 | N105: =_xlfn.XLOOKUP(Tabla1[[#This Row],[Subcuenta]],[3]Gastos!$B:$B,[3]Gastos!$AU:$AU) -> 396800 | O105: =SUM(Tabla1[[#This Row],[july]:[september]]) -> 2509575 | P105: =_xlfn.XLOOKUP(Tabla1[[#This Row],[Subcuenta]],[3]Gastos!$B:$B,[3]Gastos!$AZ:$AZ) -> 985510 | Q105: =_xlfn.XLOOKUP(Tabla1[[#This Row],[Subcuenta]],[3]Gastos!$B:$B,[3]Gastos!$BE:$BE) -> 1032070 | R105: =_xlfn.XLOOKUP(Tabla1[[#This Row],[Subcuenta]],[3]Gastos!$B:$B,[3]Gastos!$BJ:$BJ) -> 1583356 | S105: =SUM(Tabla1[[#This Row],[october]:[december]]) -> 3600936 | T105: =SUM(G105,K105,O105,S105) -> 11570914
B106: Gastos Extras | C106: GASTOS DE EXPORTACIONES O IMPORTACIONES PARA URUGUAY | D106: =_xlfn.XLOOKUP(C106,[3]Gastos!$B:$B,[3]Gastos!$G:$G) -> 0 | E106: =_xlfn.XLOOKUP(C106,[3]Gastos!$B:$B,[3]Gastos!$L:$L) -> 149112 | F106: =_xlfn.XLOOKUP(C106,[3]Gastos!$B:$B,[3]Gastos!$Q:$Q) -> 0 | G106: =SUM(Tabla1[[#This Row],[january]:[march]]) -> 149112 | H106: =_xlfn.XLOOKUP(C106,[3]Gastos!$B:$B,[3]Gastos!$V:$V) -> 0 | I106: =_xlfn.XLOOKUP(C106,[3]Gastos!$B:$B,[3]Gastos!$AA:$AA) -> 0 | J106: =_xlfn.XLOOKUP(C106,[3]Gastos!$B:$B,[3]Gastos!$AF:$AF) -> 0 | K106: =SUM(Tabla1[[#This Row],[april]:[june]]) -> 0 | L106: =_xlfn.XLOOKUP(C106,[3]Gastos!$B:$B,[3]Gastos!$AK:$AK) -> 0 | M106: =_xlfn.XLOOKUP(C106,[3]Gastos!$B:$B,[3]Gastos!$AP:$AP) -> 0 | N106: =_xlfn.XLOOKUP(Tabla1[[#This Row],[Subcuenta]],[3]Gastos!$B:$B,[3]Gastos!$AU:$AU) -> 0 | O106: =SUM(Tabla1[[#This Row],[july]:[september]]) -> 0 | P106: =_xlfn.XLOOKUP(Tabla1[[#This Row],[Subcuenta]],[3]Gastos!$B:$B,[3]Gastos!$AZ:$AZ) -> 0 | Q106: =_xlfn.XLOOKUP(Tabla1[[#This Row],[Subcuenta]],[3]Gastos!$B:$B,[3]Gastos!$BE:$BE) -> 0 | R106: =_xlfn.XLOOKUP(Tabla1[[#This Row],[Subcuenta]],[3]Gastos!$B:$B,[3]Gastos!$BJ:$BJ) -> 0 | S106: =SUM(Tabla1[[#This Row],[october]:[december]]) -> 0 | T106: =SUM(G106,K106,O106,S106) -> 149112
B107: Gastos Extras | C107: GASTOS DE IMPORTACIONES PARA ARGENTINA | D107: =_xlfn.XLOOKUP(C107,[3]Gastos!$B:$B,[3]Gastos!$G:$G) -> 0 | E107: =_xlfn.XLOOKUP(C107,[3]Gastos!$B:$B,[3]Gastos!$L:$L) -> 2051440 | F107: =_xlfn.XLOOKUP(C107,[3]Gastos!$B:$B,[3]Gastos!$Q:$Q) -> 1155094 | G107: =SUM(Tabla1[[#This Row],[january]:[march]]) -> 3206534 | H107: =_xlfn.XLOOKUP(C107,[3]Gastos!$B:$B,[3]Gastos!$V:$V) -> 0 | I107: =_xlfn.XLOOKUP(C107,[3]Gastos!$B:$B,[3]Gastos!$AA:$AA) -> 264937 | J107: =_xlfn.XLOOKUP(C107,[3]Gastos!$B:$B,[3]Gastos!$AF:$AF) -> 0 | K107: =SUM(Tabla1[[#This Row],[april]:[june]]) -> 264937 | L107: =_xlfn.XLOOKUP(C107,[3]Gastos!$B:$B,[3]Gastos!$AK:$AK) -> 0 | M107: =_xlfn.XLOOKUP(C107,[3]Gastos!$B:$B,[3]Gastos!$AP:$AP) -> 0 | N107: =_xlfn.XLOOKUP(Tabla1[[#This Row],[Subcuenta]],[3]Gastos!$B:$B,[3]Gastos!$AU:$AU) -> 0 | O107: =SUM(Tabla1[[#This Row],[july]:[september]]) -> 0 | P107: =_xlfn.XLOOKUP(Tabla1[[#This Row],[Subcuenta]],[3]Gastos!$B:$B,[3]Gastos!$AZ:$AZ) -> 0 | Q107: =_xlfn.XLOOKUP(Tabla1[[#This Row],[Subcuenta]],[3]Gastos!$B:$B,[3]Gastos!$BE:$BE) -> 264937 | R107: =_xlfn.XLOOKUP(Tabla1[[#This Row],[Subcuenta]],[3]Gastos!$B:$B,[3]Gastos!$BJ:$BJ) -> 0 | S107: =SUM(Tabla1[[#This Row],[october]:[december]]) -> 264937 | T107: =SUM(G107,K107,O107,S107) -> 3736408
B108: Gastos Extras | C108: GASTOS DE IMPORTACIONES OTROS PAISES | D108: =_xlfn.XLOOKUP(C108,[3]Gastos!$B:$B,[3]Gastos!$G:$G) -> 0 | E108: =_xlfn.XLOOKUP(C108,[3]Gastos!$B:$B,[3]Gastos!$L:$L) -> 0 | F108: =_xlfn.XLOOKUP(C108,[3]Gastos!$B:$B,[3]Gastos!$Q:$Q) -> 0 | G108: =SUM(Tabla1[[#This Row],[january]:[march]]) -> 0 | H108: =_xlfn.XLOOKUP(C108,[3]Gastos!$B:$B,[3]Gastos!$V:$V) -> 0 | I108: =_xlfn.XLOOKUP(C108,[3]Gastos!$B:$B,[3]Gastos!$AA:$AA) -> 0 | J108: =_xlfn.XLOOKUP(C108,[3]Gastos!$B:$B,[3]Gastos!$AF:$AF) -> 0 | K108: =SUM(Tabla1[[#This Row],[april]:[june]]) -> 0 | L108: =_xlfn.XLOOKUP(C108,[3]Gastos!$B:$B,[3]Gastos!$AK:$AK) -> 0 | M108: =_xlfn.XLOOKUP(C108,[3]Gastos!$B:$B,[3]Gastos!$AP:$AP) -> 0 | N108: =_xlfn.XLOOKUP(Tabla1[[#This Row],[Subcuenta]],[3]Gastos!$B:$B,[3]Gastos!$AU:$AU) -> 758242 | O108: =SUM(Tabla1[[#This Row],[july]:[september]]) -> 758242 | P108: =_xlfn.XLOOKUP(Tabla1[[#This Row],[Subcuenta]],[3]Gastos!$B:$B,[3]Gastos!$AZ:$AZ) -> 0 | Q108: =_xlfn.XLOOKUP(Tabla1[[#This Row],[Subcuenta]],[3]Gastos!$B:$B,[3]Gastos!$BE:$BE) -> 0 | R108: =_xlfn.XLOOKUP(Tabla1[[#This Row],[Subcuenta]],[3]Gastos!$B:$B,[3]Gastos!$BJ:$BJ) -> 0 | S108: =SUM(Tabla1[[#This Row],[october]:[december]]) -> 0 | T108: =SUM(G108,K108,O108,S108) -> 758242
B109: Gastos Extras | C109: GASTOS DE EXPORTACIONES OTROS PAISES | D109: =_xlfn.XLOOKUP(C109,[3]Gastos!$B:$B,[3]Gastos!$G:$G) -> 0 | E109: =_xlfn.XLOOKUP(C109,[3]Gastos!$B:$B,[3]Gastos!$L:$L) -> 0 | F109: =_xlfn.XLOOKUP(C109,[3]Gastos!$B:$B,[3]Gastos!$Q:$Q) -> 0 | G109: =SUM(Tabla1[[#This Row],[january]:[march]]) -> 0 | H109: =_xlfn.XLOOKUP(C109,[3]Gastos!$B:$B,[3]Gastos!$V:$V) -> 0 | I109: =_xlfn.XLOOKUP(C109,[3]Gastos!$B:$B,[3]Gastos!$AA:$AA) -> 0 | J109: =_xlfn.XLOOKUP(C109,[3]Gastos!$B:$B,[3]Gastos!$AF:$AF) -> 0 | K109: =SUM(Tabla1[[#This Row],[april]:[june]]) -> 0 | L109: =_xlfn.XLOOKUP(C109,[3]Gastos!$B:$B,[3]Gastos!$AK:$AK) -> 0 | M109: =_xlfn.XLOOKUP(C109,[3]Gastos!$B:$B,[3]Gastos!$AP:$AP) -> 2431676 | N109: =_xlfn.XLOOKUP(Tabla1[[#This Row],[Subcuenta]],[3]Gastos!$B:$B,[3]Gastos!$AU:$AU) -> 0 | O109: =SUM(Tabla1[[#This Row],[july]:[september]]) -> 2431676 | P109: =_xlfn.XLOOKUP(Tabla1[[#This Row],[Subcuenta]],[3]Gastos!$B:$B,[3]Gastos!$AZ:$AZ) -> 148503 | Q109: =_xlfn.XLOOKUP(Tabla1[[#This Row],[Subcuenta]],[3]Gastos!$B:$B,[3]Gastos!$BE:$BE) -> 0 | R109: =_xlfn.XLOOKUP(Tabla1[[#This Row],[Subcuenta]],[3]Gastos!$B:$B,[3]Gastos!$BJ:$BJ) -> 0 | S109: =SUM(Tabla1[[#This Row],[october]:[december]]) -> 148503 | T109: =SUM(G109,K109,O109,S109) -> 2580179
B110: Gastos Extras | C110: ALIGNERCLICK ODONTOLOGA LIMITADA OTROS PAISES | D110: =_xlfn.XLOOKUP(C110,[3]Gastos!$B:$B,[3]Gastos!$G:$G) -> 0 | E110: =_xlfn.XLOOKUP(C110,[3]Gastos!$B:$B,[3]Gastos!$L:$L) -> 0 | F110: =_xlfn.XLOOKUP(C110,[3]Gastos!$B:$B,[3]Gastos!$Q:$Q) -> 0 | G110: =SUM(Tabla1[[#This Row],[january]:[march]]) -> 0 | H110: =_xlfn.XLOOKUP(C110,[3]Gastos!$B:$B,[3]Gastos!$V:$V) -> 0 | I110: =_xlfn.XLOOKUP(C110,[3]Gastos!$B:$B,[3]Gastos!$AA:$AA) -> 0 | J110: =_xlfn.XLOOKUP(C110,[3]Gastos!$B:$B,[3]Gastos!$AF:$AF) -> 0 | K110: =SUM(Tabla1[[#This Row],[april]:[june]]) -> 0 | L110: =_xlfn.XLOOKUP(C110,[3]Gastos!$B:$B,[3]Gastos!$AK:$AK) -> 0 | M110: =_xlfn.XLOOKUP(C110,[3]Gastos!$B:$B,[3]Gastos!$AP:$AP) -> 5734512 | N110: =_xlfn.XLOOKUP(Tabla1[[#This Row],[Subcuenta]],[3]Gastos!$B:$B,[3]Gastos!$AU:$AU) -> 4597684 | O110: =SUM(Tabla1[[#This Row],[july]:[september]]) -> 10332196 | P110: =_xlfn.XLOOKUP(Tabla1[[#This Row],[Subcuenta]],[3]Gastos!$B:$B,[3]Gastos!$AZ:$AZ) -> 2673816 | Q110: =_xlfn.XLOOKUP(Tabla1[[#This Row],[Subcuenta]],[3]Gastos!$B:$B,[3]Gastos!$BE:$BE) -> 0 | R110: =_xlfn.XLOOKUP(Tabla1[[#This Row],[Subcuenta]],[3]Gastos!$B:$B,[3]Gastos!$BJ:$BJ) -> 4348432 | S110: =SUM(Tabla1[[#This Row],[october]:[december]]) -> 7022248 | T110: =SUM(G110,K110,O110,S110) -> 17354444
B111: Gastos Extras | C111: MARTHA SOCARRAS - ERNESTO SEPULVEDA - ALG - FURQAN | D111: =_xlfn.XLOOKUP(C111,[3]Gastos!$B:$B,[3]Gastos!$G:$G) -> 12586943 | E111: =_xlfn.XLOOKUP(C111,[3]Gastos!$B:$B,[3]Gastos!$L:$L) -> 2217831 | F111: =_xlfn.XLOOKUP(C111,[3]Gastos!$B:$B,[3]Gastos!$Q:$Q) -> 34125775 | G111: =SUM(Tabla1[[#This Row],[january]:[march]]) -> 48930549 | H111: =_xlfn.XLOOKUP(C111,[3]Gastos!$B:$B,[3]Gastos!$V:$V) -> 21405654 | I111: =_xlfn.XLOOKUP(C111,[3]Gastos!$B:$B,[3]Gastos!$AA:$AA) -> 11951748 | J111: =_xlfn.XLOOKUP(C111,[3]Gastos!$B:$B,[3]Gastos!$AF:$AF) -> 13760307 | K111: =SUM(Tabla1[[#This Row],[april]:[june]]) -> 47117709 | L111: =_xlfn.XLOOKUP(C111,[3]Gastos!$B:$B,[3]Gastos!$AK:$AK) -> 0 | M111: =_xlfn.XLOOKUP(C111,[3]Gastos!$B:$B,[3]Gastos!$AP:$AP) -> 11994620 | N111: =_xlfn.XLOOKUP(Tabla1[[#This Row],[Subcuenta]],[3]Gastos!$B:$B,[3]Gastos!$AU:$AU) -> 2439223 | O111: =SUM(Tabla1[[#This Row],[july]:[september]]) -> 14433843 | P111: =_xlfn.XLOOKUP(Tabla1[[#This Row],[Subcuenta]],[3]Gastos!$B:$B,[3]Gastos!$AZ:$AZ) -> 0 | Q111: =_xlfn.XLOOKUP(Tabla1[[#This Row],[Subcuenta]],[3]Gastos!$B:$B,[3]Gastos!$BE:$BE) -> 0 | R111: =_xlfn.XLOOKUP(Tabla1[[#This Row],[Subcuenta]],[3]Gastos!$B:$B,[3]Gastos!$BJ:$BJ) -> 0 | S111: =SUM(Tabla1[[#This Row],[october]:[december]]) -> 0 | T111: =SUM(G111,K111,O111,S111) -> 110482101
B112: Gastos Extras | C112: AGENCIA DE VIAJE OTROS PAISES HECA | D112: =_xlfn.XLOOKUP(C112,[3]Gastos!$B:$B,[3]Gastos!$G:$G) -> 10793157 | E112: =_xlfn.XLOOKUP(C112,[3]Gastos!$B:$B,[3]Gastos!$L:$L) -> 2831136 | F112: =_xlfn.XLOOKUP(C112,[3]Gastos!$B:$B,[3]Gastos!$Q:$Q) -> 13302722 | G112: =SUM(Tabla1[[#This Row],[january]:[march]]) -> 26927015 | H112: =_xlfn.XLOOKUP(C112,[3]Gastos!$B:$B,[3]Gastos!$V:$V) -> 1320315 | I112: =_xlfn.XLOOKUP(C112,[3]Gastos!$B:$B,[3]Gastos!$AA:$AA) -> 12051421 | J112: =_xlfn.XLOOKUP(C112,[3]Gastos!$B:$B,[3]Gastos!$AF:$AF) -> 13081099 | K112: =SUM(Tabla1[[#This Row],[april]:[june]]) -> 26452835 | L112: =_xlfn.XLOOKUP(C112,[3]Gastos!$B:$B,[3]Gastos!$AK:$AK) -> 12242032 | M112: =_xlfn.XLOOKUP(C112,[3]Gastos!$B:$B,[3]Gastos!$AP:$AP) -> 19115896 | N112: =_xlfn.XLOOKUP(Tabla1[[#This Row],[Subcuenta]],[3]Gastos!$B:$B,[3]Gastos!$AU:$AU) -> 17833394 | O112: =SUM(Tabla1[[#This Row],[july]:[september]]) -> 49191322 | P112: =_xlfn.XLOOKUP(Tabla1[[#This Row],[Subcuenta]],[3]Gastos!$B:$B,[3]Gastos!$AZ:$AZ) -> 12571890 | Q112: =_xlfn.XLOOKUP(Tabla1[[#This Row],[Subcuenta]],[3]Gastos!$B:$B,[3]Gastos!$BE:$BE) -> 1599218 | R112: =_xlfn.XLOOKUP(Tabla1[[#This Row],[Subcuenta]],[3]Gastos!$B:$B,[3]Gastos!$BJ:$BJ) -> 2024627 | S112: =SUM(Tabla1[[#This Row],[october]:[december]]) -> 16195735 | T112: =SUM(G112,K112,O112,S112) -> 118766907
B113: Gastos Extras | C113: UPS ENVIOS A OTROS PAISES HECA | D113: =_xlfn.XLOOKUP(C113,[3]Gastos!$B:$B,[3]Gastos!$G:$G) -> 0 | E113: =_xlfn.XLOOKUP(C113,[3]Gastos!$B:$B,[3]Gastos!$L:$L) -> 23062.221 | F113: =_xlfn.XLOOKUP(C113,[3]Gastos!$B:$B,[3]Gastos!$Q:$Q) -> 160289 | G113: =SUM(Tabla1[[#This Row],[january]:[march]]) -> 183351.22 | H113: =_xlfn.XLOOKUP(C113,[3]Gastos!$B:$B,[3]Gastos!$V:$V) -> 106056 | I113: =_xlfn.XLOOKUP(C113,[3]Gastos!$B:$B,[3]Gastos!$AA:$AA) -> 188369.78 | J113: =_xlfn.XLOOKUP(C113,[3]Gastos!$B:$B,[3]Gastos!$AF:$AF) -> 143011 | K113: =SUM(Tabla1[[#This Row],[april]:[june]]) -> 437436.78 | L113: =_xlfn.XLOOKUP(C113,[3]Gastos!$B:$B,[3]Gastos!$AK:$AK) -> 0 | M113: =_xlfn.XLOOKUP(C113,[3]Gastos!$B:$B,[3]Gastos!$AP:$AP) -> 17617 | N113: =_xlfn.XLOOKUP(Tabla1[[#This Row],[Subcuenta]],[3]Gastos!$B:$B,[3]Gastos!$AU:$AU) -> 0 | O113: =SUM(Tabla1[[#This Row],[july]:[september]]) -> 17617 | P113: =_xlfn.XLOOKUP(Tabla1[[#This Row],[Subcuenta]],[3]Gastos!$B:$B,[3]Gastos!$AZ:$AZ) -> 54848 | Q113: =_xlfn.XLOOKUP(Tabla1[[#This Row],[Subcuenta]],[3]Gastos!$B:$B,[3]Gastos!$BE:$BE) -> 0 | R113: =_xlfn.XLOOKUP(Tabla1[[#This Row],[Subcuenta]],[3]Gastos!$B:$B,[3]Gastos!$BJ:$BJ) -> 0 | S113: =SUM(Tabla1[[#This Row],[october]:[december]]) -> 54848 | T113: =SUM(G113,K113,O113,S113) -> 693253
